Workbook
Name TodayDate: Settings!$B$5
Name CurMonthStart: Settings!$B$6
Name CurMonthEnd: Settings!$B$7
Name LastMonthStart: Settings!$B$8
Name LastMonthEnd: Settings!$B$9
Name CurYearStart: Settings!$B$10
Name CurYearEnd: Settings!$B$11
Name List_YesNo: Settings!$A$25:$A$26
Name List_NeedWant: Settings!$B$25:$B$26
Name PaymentMethodList: Dim_PaymentMethod[MethodName]
Name CategoryNameList: Dim_Category[CategoryName]
Name ExpenseCategoryList: Dim_Category[CategoryName]
Name VendorNameList: Dim_Vendor[VendorName]
Name AccountNameList: Dim_Account[AccountName]
Name SourceNameList: Dim_Source[SourceName]
Name SignConvention: 'Bank Import'!$D$13

Sheet Dashboard
A1: Personal Finance Planner
A3: ="Data as of " & TEXT(TodayDate,"mmmm d, yyyy") & " | Refresh: Data > Refresh All, then Ctrl+Alt+F9 to recalculate"
A5: MONTHLY INCOME | E5: MONTHLY EXPENSES | I5: MONTHLY SAVINGS | M5: SAVINGS RATE %
A6: =SUMIFS(Fact_Income[NetAmount],Fact_Income[Date],">="&CurMonthStart,Fact_Income[Date],"<="&CurMonthEnd)+SUMIFS(BankImportRaw[AbsAmount],BankImportRaw[TransactionType],"Income",BankImportRaw[Date],">="&CurMonthStart,BankImportRaw[Date],"<="&CurMonthEnd) | E6: =SUMIFS(Fact_Expenses[Amount],Fact_Expenses[Date],">="&CurMonthStart,Fact_Expenses[Date],"<="&CurMonthEnd)+SUMIFS(BankImportRaw[AbsAmount],BankImportRaw[TransactionType],"Expense",BankImportRaw[Date],">="&CurMonthStart,BankImportRaw[Date],"<="&CurMonthEnd) | I6: =A6-E6 | M6: =IFERROR(I6/A6,0)
A10: NET CASH FLOW | E10: BUDGET UTILIZATION % | I10: EMERGENCY FUND | M10: TOTAL SAVED (ALL GOALS)
A11: =I6-SUMIFS(Fact_SavingsTransfers[Amount],Fact_SavingsTransfers[Date],">="&CurMonthStart,Fact_SavingsTransfers[Date],"<="&CurMonthEnd) | E11: =IFERROR(SUM(Budget[Actual])/SUM(Budget[MonthlyBudget]),0) | I11: =SUMIFS(Fact_SavingsTransfers[Amount],Fact_SavingsTransfers[GoalName],"Emergency Fund") | M11: =SUM(Dim_Goal[CurrentAmount])
A67: Widgets & Quick Insights
A69: Top Expenses (This Month, Expenses tab only) | E69: Largest Vendors (This Month) | H69: Largest Categories (This Month) | K69: Behavior Metrics
A70: Vendor | B70: Category | C70: Amount | E70: Vendor | F70: Amount | H70: Category | I70: Amount
A71: =IFERROR(INDEX(Fact_Expenses[VendorName],MATCH($C71,Fact_Expenses[CurMonthAmt],0)),"") | B71: =IFERROR(INDEX(Fact_Expenses[CategoryName],MATCH($C71,Fact_Expenses[CurMonthAmt],0)),"") | C71: =IFERROR(LARGE(Fact_Expenses[CurMonthAmt],1),0) | E71: =IFERROR(INDEX(Dim_Vendor[VendorName],MATCH($F71,Dim_Vendor[CurMonthSpend],0)),"") | F71: =IFERROR(LARGE(Dim_Vendor[CurMonthSpend],1),0) | H71: =IFERROR(INDEX(Budget[CategoryName],MATCH($I71,Budget[Actual],0)),"") | I71: =IFERROR(LARGE(Budget[Actual],1),0) | K71: Need vs Want % | M71: =IFERROR((SUMIFS(Fact_Expenses[Amount],Fact_Expenses[NeedWantFlag],"Need")+SUMIFS(BankImportRaw[AbsAmount],BankImportRaw[NeedWantFlag],"Need",BankImportRaw[TransactionType],"Expense"))/(SUM(Fact_Expenses[Amount])+SUMIFS(BankImportRaw[AbsAmount],BankImportRaw[TransactionType],"Expense")),0)
A72: =IFERROR(INDEX(Fact_Expenses[VendorName],MATCH($C72,Fact_Expenses[CurMonthAmt],0)),"") | B72: =IFERROR(INDEX(Fact_Expenses[CategoryName],MATCH($C72,Fact_Expenses[CurMonthAmt],0)),"") | C72: =IFERROR(LARGE(Fact_Expenses[CurMonthAmt],2),0) | E72: =IFERROR(INDEX(Dim_Vendor[VendorName],MATCH($F72,Dim_Vendor[CurMonthSpend],0)),"") | F72: =IFERROR(LARGE(Dim_Vendor[CurMonthSpend],2),0) | H72: =IFERROR(INDEX(Budget[CategoryName],MATCH($I72,Budget[Actual],0)),"") | I72: =IFERROR(LARGE(Budget[Actual],2),0) | K72: Recurring Spend / mo (manual entries only) | M72: =SUMIFS(Fact_Expenses[Amount],Fact_Expenses[RecurringFlag],"Yes",Fact_Expenses[Date],">="&CurMonthStart,Fact_Expenses[Date],"<="&CurMonthEnd)
A73: =IFERROR(INDEX(Fact_Expenses[VendorName],MATCH($C73,Fact_Expenses[CurMonthAmt],0)),"") | B73: =IFERROR(INDEX(Fact_Expenses[CategoryName],MATCH($C73,Fact_Expenses[CurMonthAmt],0)),"") | C73: =IFERROR(LARGE(Fact_Expenses[CurMonthAmt],3),0) | E73: =IFERROR(INDEX(Dim_Vendor[VendorName],MATCH($F73,Dim_Vendor[CurMonthSpend],0)),"") | F73: =IFERROR(LARGE(Dim_Vendor[CurMonthSpend],3),0) | H73: =IFERROR(INDEX(Budget[CategoryName],MATCH($I73,Budget[Actual],0)),"") | I73: =IFERROR(LARGE(Budget[Actual],3),0)
A74: =IFERROR(INDEX(Fact_Expenses[VendorName],MATCH($C74,Fact_Expenses[CurMonthAmt],0)),"") | B74: =IFERROR(INDEX(Fact_Expenses[CategoryName],MATCH($C74,Fact_Expenses[CurMonthAmt],0)),"") | C74: =IFERROR(LARGE(Fact_Expenses[CurMonthAmt],4),0) | E74: =IFERROR(INDEX(Dim_Vendor[VendorName],MATCH($F74,Dim_Vendor[CurMonthSpend],0)),"") | F74: =IFERROR(LARGE(Dim_Vendor[CurMonthSpend],4),0) | H74: =IFERROR(INDEX(Budget[CategoryName],MATCH($I74,Budget[Actual],0)),"") | I74: =IFERROR(LARGE(Budget[Actual],4),0)
A75: =IFERROR(INDEX(Fact_Expenses[VendorName],MATCH($C75,Fact_Expenses[CurMonthAmt],0)),"") | B75: =IFERROR(INDEX(Fact_Expenses[CategoryName],MATCH($C75,Fact_Expenses[CurMonthAmt],0)),"") | C75: =IFERROR(LARGE(Fact_Expenses[CurMonthAmt],5),0) | E75: =IFERROR(INDEX(Dim_Vendor[VendorName],MATCH($F75,Dim_Vendor[CurMonthSpend],0)),"") | F75: =IFERROR(LARGE(Dim_Vendor[CurMonthSpend],5),0) | H75: =IFERROR(INDEX(Budget[CategoryName],MATCH($I75,Budget[Actual],0)),"") | I75: =IFERROR(LARGE(Budget[Actual],5),0)
A78: Budget Status (red = over budget) | D78: Recent Transactions (Expenses tab only)
A79: Category | B79: Status | D79: Date | E79: Vendor | F79: Category | G79: Amount
A80: =Budget!A11 | B80: =Budget!F11 | D80: =IFERROR(INDEX(Fact_Expenses[Date],COUNTA(Fact_Expenses[ExpenseID])-0),"") | E80: =IFERROR(INDEX(Fact_Expenses[VendorName],COUNTA(Fact_Expenses[ExpenseID])-0),"") | F80: =IFERROR(INDEX(Fact_Expenses[CategoryName],COUNTA(Fact_Expenses[ExpenseID])-0),"") | G80: =IFERROR(INDEX(Fact_Expenses[Amount],COUNTA(Fact_Expenses[ExpenseID])-0),"")
A81: =Budget!A12 | B81: =Budget!F12 | D81: =IFERROR(INDEX(Fact_Expenses[Date],COUNTA(Fact_Expenses[ExpenseID])-1),"") | E81: =IFERROR(INDEX(Fact_Expenses[VendorName],COUNTA(Fact_Expenses[ExpenseID])-1),"") | F81: =IFERROR(INDEX(Fact_Expenses[CategoryName],COUNTA(Fact_Expenses[ExpenseID])-1),"") | G81: =IFERROR(INDEX(Fact_Expenses[Amount],COUNTA(Fact_Expenses[ExpenseID])-1),"")
A82: =Budget!A13 | B82: =Budget!F13 | D82: =IFERROR(INDEX(Fact_Expenses[Date],COUNTA(Fact_Expenses[ExpenseID])-2),"") | E82: =IFERROR(INDEX(Fact_Expenses[VendorName],COUNTA(Fact_Expenses[ExpenseID])-2),"") | F82: =IFERROR(INDEX(Fact_Expenses[CategoryName],COUNTA(Fact_Expenses[ExpenseID])-2),"") | G82: =IFERROR(INDEX(Fact_Expenses[Amount],COUNTA(Fact_Expenses[ExpenseID])-2),"")
A83: =Budget!A14 | B83: =Budget!F14 | D83: =IFERROR(INDEX(Fact_Expenses[Date],COUNTA(Fact_Expenses[ExpenseID])-3),"") | E83: =IFERROR(INDEX(Fact_Expenses[VendorName],COUNTA(Fact_Expenses[ExpenseID])-3),"") | F83: =IFERROR(INDEX(Fact_Expenses[CategoryName],COUNTA(Fact_Expenses[ExpenseID])-3),"") | G83: =IFERROR(INDEX(Fact_Expenses[Amount],COUNTA(Fact_Expenses[ExpenseID])-3),"")
A84: =Budget!A15 | B84: =Budget!F15 | D84: =IFERROR(INDEX(Fact_Expenses[Date],COUNTA(Fact_Expenses[ExpenseID])-4),"") | E84: =IFERROR(INDEX(Fact_Expenses[VendorName],COUNTA(Fact_Expenses[ExpenseID])-4),"") | F84: =IFERROR(INDEX(Fact_Expenses[CategoryName],COUNTA(Fact_Expenses[ExpenseID])-4),"") | G84: =IFERROR(INDEX(Fact_Expenses[Amount],COUNTA(Fact_Expenses[ExpenseID])-4),"")
A85: =Budget!A16 | B85: =Budget!F16 | D85: =IFERROR(INDEX(Fact_Expenses[Date],COUNTA(Fact_Expenses[ExpenseID])-5),"") | E85: =IFERROR(INDEX(Fact_Expenses[VendorName],COUNTA(Fact_Expenses[ExpenseID])-5),"") | F85: =IFERROR(INDEX(Fact_Expenses[CategoryName],COUNTA(Fact_Expenses[ExpenseID])-5),"") | G85: =IFERROR(INDEX(Fact_Expenses[Amount],COUNTA(Fact_Expenses[ExpenseID])-5),"")
A86: =Budget!A17 | B86: =Budget!F17 | D86: =IFERROR(INDEX(Fact_Expenses[Date],COUNTA(Fact_Expenses[ExpenseID])-6),"") | E86: =IFERROR(INDEX(Fact_Expenses[VendorName],COUNTA(Fact_Expenses[ExpenseID])-6),"") | F86: =IFERROR(INDEX(Fact_Expenses[CategoryName],COUNTA(Fact_Expenses[ExpenseID])-6),"") | G86: =IFERROR(INDEX(Fact_Expenses[Amount],COUNTA(Fact_Expenses[ExpenseID])-6),"")
A87: =Budget!A18 | B87: =Budget!F18 | D87: =IFERROR(INDEX(Fact_Expenses[Date],COUNTA(Fact_Expenses[ExpenseID])-7),"") | E87: =IFERROR(INDEX(Fact_Expenses[VendorName],COUNTA(Fact_Expenses[ExpenseID])-7),"") | F87: =IFERROR(INDEX(Fact_Expenses[CategoryName],COUNTA(Fact_Expenses[ExpenseID])-7),"") | G87: =IFERROR(INDEX(Fact_Expenses[Amount],COUNTA(Fact_Expenses[ExpenseID])-7),"")
A88: =Budget!A19 | B88: =Budget!F19
A89: =Budget!A20 | B89: =Budget!F20
A91: Cut-Back Analyzer
A92: Category | B92: Monthly Cost | C92: Annual Cost | D92: Potential Savings | E92: Priority | F92: Recommendation
A93: Dining & Entertainment | B93: =SUMIFS(Fact_Expenses[Amount],Fact_Expenses[CategoryName],"Dining & Entertainment",Fact_Expenses[Date],">="&EOMONTH(TodayDate,-2)+1,Fact_Expenses[Date],"<="&EOMONTH(TodayDate,-1))+SUMIFS(BankImportRaw[AbsAmount],BankImportRaw[CategoryName],"Dining & Entertainment",BankImportRaw[TransactionType],"Expense",BankImportRaw[Date],">="&EOMONTH(TodayDate,-2)+1,BankImportRaw[Date],"<="&EOMONTH(TodayDate,-1)) | C93: =B93*12 | D93: =C93*0.3 | E93: =RANK(D93,$D$93:$D$96) | F93: =IF(D93>500,"High-impact — consider cutting significantly",IF(D93>150,"Moderate — trim where possible","Low-impact — monitor only"))
A94: Shopping | B94: =SUMIFS(Fact_Expenses[Amount],Fact_Expenses[CategoryName],"Shopping",Fact_Expenses[Date],">="&EOMONTH(TodayDate,-2)+1,Fact_Expenses[Date],"<="&EOMONTH(TodayDate,-1))+SUMIFS(BankImportRaw[AbsAmount],BankImportRaw[CategoryName],"Shopping",BankImportRaw[TransactionType],"Expense",BankImportRaw[Date],">="&EOMONTH(TodayDate,-2)+1,BankImportRaw[Date],"<="&EOMONTH(TodayDate,-1)) | C94: =B94*12 | D94: =C94*0.3 | E94: =RANK(D94,$D$93:$D$96) | F94: =IF(D94>500,"High-impact — consider cutting significantly",IF(D94>150,"Moderate — trim where possible","Low-impact — monitor only"))
A95: Personal Care | B95: =SUMIFS(Fact_Expenses[Amount],Fact_Expenses[CategoryName],"Personal Care",Fact_Expenses[Date],">="&EOMONTH(TodayDate,-2)+1,Fact_Expenses[Date],"<="&EOMONTH(TodayDate,-1))+SUMIFS(BankImportRaw[AbsAmount],BankImportRaw[CategoryName],"Personal Care",BankImportRaw[TransactionType],"Expense",BankImportRaw[Date],">="&EOMONTH(TodayDate,-2)+1,BankImportRaw[Date],"<="&EOMONTH(TodayDate,-1)) | C95: =B95*12 | D95: =C95*0.3 | E95: =RANK(D95,$D$93:$D$96) | F95: =IF(D95>500,"High-impact — consider cutting significantly",IF(D95>150,"Moderate — trim where possible","Low-impact — monitor only"))
A96: Non-Essential Wants (all categories) | B96: =SUMIFS(Fact_Expenses[Amount],Fact_Expenses[NeedWantFlag],"Want",Fact_Expenses[Date],">="&EOMONTH(TodayDate,-2)+1,Fact_Expenses[Date],"<="&EOMONTH(TodayDate,-1))+SUMIFS(BankImportRaw[AbsAmount],BankImportRaw[NeedWantFlag],"Want",BankImportRaw[TransactionType],"Expense",BankImportRaw[Date],">="&EOMONTH(TodayDate,-2)+1,BankImportRaw[Date],"<="&EOMONTH(TodayDate,-1)) | C96: =B96*12 | D96: =C96*0.3 | E96: =RANK(D96,$D$93:$D$96) | F96: =IF(D96>500,"High-impact — consider cutting significantly",IF(D96>150,"Moderate — trim where possible","Low-impact — monitor only"))

Sheet Data Entry
A1: Data Entry
B4: Personal Finance Planner — Quick Start
B5: 1. Got a bank/credit-card CSV export? Go to the Bank Import tab first — paste it there, pick a Vendor per row, and it auto-suggests the Category and splits Expense vs Income for you.
B6: 2. Otherwise, enter transactions directly: Income for paychecks, Expenses for purchases, Savings for transfers toward a goal.
B7: 3. Use the dropdowns for Vendor / Category / Account / Payment Method — never type free text — so every report stays consistent.
B8: 4. Set your monthly budget per category on the Budget tab.
B9: 5. Press Ctrl+Alt+F9 (Formulas > Calculate Now) so every KPI, chart, and report recalculates.
B10: 6. Open the Dashboard tab to review updated KPIs, charts, and the Cut-Back Analyzer.
B12: Jump to a tab
B13: Bank Import | C13: Paste a bank/credit-card CSV export here first
B14: Income | C14: Log paychecks
B15: Expenses | C15: Log every purchase — the most-used tab
B16: Savings | C16: Set goals and log transfers toward them
B17: Budget | C17: Set your monthly budget per category
B18: Categories | C18: Add a new expense/income category
B19: Vendors | C19: Add a new vendor
B20: Accounts | C20: Add a new bank/credit account
B23: Adding new categories, vendors, or accounts
B24: New category: add a row to Dim_Category on the Categories tab. It appears in every dropdown and report automatically — no formulas anywhere else need to change.
B25: New vendor: add a row to Dim_Vendor on the Vendors tab, with its default category.
B26: New account: add a row to Dim_Account on the Accounts tab, with its starting Balance.
B27: All dropdowns use structured references (e.g. =Dim_Category[CategoryName]), which automatically grow to include new rows — not a fixed cell range — so nothing else needs to be touched.
B29: Where your data lives
B30: Everything is stored inside this workbook — the Excel Tables on each tab (Fact_Income, Fact_Expenses, Fact_SavingsTransfers, Dim_Category, Dim_Vendor, Dim_Account, Dim_Goal, Budget) ARE the database. There is no external server, cloud account, or database connection involved. That means: (1) this file is the only copy of your data — back it up (save a copy, or keep it in a synced folder / version control) the same way you would any important document; (2) if you keep this file in a git repo for versioning, remember that committing it puts your real transaction data into that repo's history — use a private repo if the numbers are real.

Sheet Bank Import
A1: Bank Import
A4: HOW TO USE THIS TAB
A5: 1. Export a CSV of transactions from your bank or credit card's website (usually Accounts > Download/Export).
A6: 2. Open that CSV, copy its Date / Description / Amount columns, and paste them into columns A, B, C of the table below — into the first blank row, not over existing rows — paste values only (Home > Paste > Values) so formatting doesn't fight the table.
A7: 3. Set 'Sign Convention' below to match how your export shows amounts (see the dropdown note).
A8: 4. Column D (Vendor) tries to auto-fill itself from any earlier row in this tab with the exact same bank description — if it's blank (new or slightly different wording), pick a Vendor from the dropdown. Category (E) then auto-fills from that vendor's default category; override it if needed.
A9: That's it — every row here counts immediately in the Dashboard KPIs, charts, Budget, and Vendor totals. There's no copy step: this tab IS the ledger for bank-derived transactions, the same way Expenses/Income are the ledger for anything you enter by hand. Don't delete rows after importing — deleting a row removes that transaction from every report.
A10: Note: the auto-fill in step 4 only recognizes an EXACT repeat of a description string. Recurring bills and subscriptions usually post with identical text every time, so those learn fast. If your bank appends a unique date or reference number to every line, matching won't catch it — you'll just pick the vendor again, same as the first time.
A11: Note: the Dashboard's 'Top Expenses' and 'Recent Transactions' widgets only look at the Expenses tab (a limitation of ranking individual transactions across two separate tables) — everything else (KPIs, Budget, Vendor totals, charts, Cut-Back Analyzer) includes this tab.
A13: Sign Convention for this import: | D13: Negative = Expense | E13: Most bank/debit exports show purchases as negative numbers (“Negative = Expense”). Most credit-card exports show charges as positive numbers and payments as negative (“Positive = Expense”). Check one real row against your bank statement to confirm.
A15: Paste your CSV's Date / Description / Amount into columns A-C — Vendor (D) auto-fills from earlier rows when it recognizes the description
A16: Date | B16: Description | C16: Amount | D16: VendorName | E16: CategoryName | F16: AccountName | G16: PaymentMethod | H16: TransactionType | I16: AbsAmount | J16: NeedWantFlag | K16: Notes
D17: ="" | E17: =IFERROR(INDEX(Dim_Category[CategoryName],MATCH(INDEX(Dim_Vendor[DefaultCategoryID],MATCH($D17,Dim_Vendor[VendorName],0)),Dim_Category[CategoryID],0)),"") | H17: =IF($C17="","",IF(SignConvention="Negative = Expense",IF($C17<0,"Expense","Income"),IF($C17>0,"Expense","Income"))) | I17: =IF($C17="","",ABS($C17))
D18: =IF($B18="","",IFERROR(INDEX($D$17:$D$17,MATCH($B18,$B$17:$B$17,0)),"")) | E18: =IFERROR(INDEX(Dim_Category[CategoryName],MATCH(INDEX(Dim_Vendor[DefaultCategoryID],MATCH($D18,Dim_Vendor[VendorName],0)),Dim_Category[CategoryID],0)),"") | H18: =IF($C18="","",IF(SignConvention="Negative = Expense",IF($C18<0,"Expense","Income"),IF($C18>0,"Expense","Income"))) | I18: =IF($C18="","",ABS($C18))
D19: =IF($B19="","",IFERROR(INDEX($D$17:$D$18,MATCH($B19,$B$17:$B$18,0)),"")) | E19: =IFERROR(INDEX(Dim_Category[CategoryName],MATCH(INDEX(Dim_Vendor[DefaultCategoryID],MATCH($D19,Dim_Vendor[VendorName],0)),Dim_Category[CategoryID],0)),"") | H19: =IF($C19="","",IF(SignConvention="Negative = Expense",IF($C19<0,"Expense","Income"),IF($C19>0,"Expense","Income"))) | I19: =IF($C19="","",ABS($C19))
D20: =IF($B20="","",IFERROR(INDEX($D$17:$D$19,MATCH($B20,$B$17:$B$19,0)),"")) | E20: =IFERROR(INDEX(Dim_Category[CategoryName],MATCH(INDEX(Dim_Vendor[DefaultCategoryID],MATCH($D20,Dim_Vendor[VendorName],0)),Dim_Category[CategoryID],0)),"") | H20: =IF($C20="","",IF(SignConvention="Negative = Expense",IF($C20<0,"Expense","Income"),IF($C20>0,"Expense","Income"))) | I20: =IF($C20="","",ABS($C20))
D21: =IF($B21="","",IFERROR(INDEX($D$17:$D$20,MATCH($B21,$B$17:$B$20,0)),"")) | E21: =IFERROR(INDEX(Dim_Category[CategoryName],MATCH(INDEX(Dim_Vendor[DefaultCategoryID],MATCH($D21,Dim_Vendor[VendorName],0)),Dim_Category[CategoryID],0)),"") | H21: =IF($C21="","",IF(SignConvention="Negative = Expense",IF($C21<0,"Expense","Income"),IF($C21>0,"Expense","Income"))) | I21: =IF($C21="","",ABS($C21))
D22: =IF($B22="","",IFERROR(INDEX($D$17:$D$21,MATCH($B22,$B$17:$B$21,0)),"")) | E22: =IFERROR(INDEX(Dim_Category[CategoryName],MATCH(INDEX(Dim_Vendor[DefaultCategoryID],MATCH($D22,Dim_Vendor[VendorName],0)),Dim_Category[CategoryID],0)),"") | H22: =IF($C22="","",IF(SignConvention="Negative = Expense",IF($C22<0,"Expense","Income"),IF($C22>0,"Expense","Income"))) | I22: =IF($C22="","",ABS($C22))
D23: =IF($B23="","",IFERROR(INDEX($D$17:$D$22,MATCH($B23,$B$17:$B$22,0)),"")) | E23: =IFERROR(INDEX(Dim_Category[CategoryName],MATCH(INDEX(Dim_Vendor[DefaultCategoryID],MATCH($D23,Dim_Vendor[VendorName],0)),Dim_Category[CategoryID],0)),"") | H23: =IF($C23="","",IF(SignConvention="Negative = Expense",IF($C23<0,"Expense","Income"),IF($C23>0,"Expense","Income"))) | I23: =IF($C23="","",ABS($C23))
D24: =IF($B24="","",IFERROR(INDEX($D$17:$D$23,MATCH($B24,$B$17:$B$23,0)),"")) | E24: =IFERROR(INDEX(Dim_Category[CategoryName],MATCH(INDEX(Dim_Vendor[DefaultCategoryID],MATCH($D24,Dim_Vendor[VendorName],0)),Dim_Category[CategoryID],0)),"") | H24: =IF($C24="","",IF(SignConvention="Negative = Expense",IF($C24<0,"Expense","Income"),IF($C24>0,"Expense","Income"))) | I24: =IF($C24="","",ABS($C24))
D25: =IF($B25="","",IFERROR(INDEX($D$17:$D$24,MATCH($B25,$B$17:$B$24,0)),"")) | E25: =IFERROR(INDEX(Dim_Category[CategoryName],MATCH(INDEX(Dim_Vendor[DefaultCategoryID],MATCH($D25,Dim_Vendor[VendorName],0)),Dim_Category[CategoryID],0)),"") | H25: =IF($C25="","",IF(SignConvention="Negative = Expense",IF($C25<0,"Expense","Income"),IF($C25>0,"Expense","Income"))) | I25: =IF($C25="","",ABS($C25))
D26: =IF($B26="","",IFERROR(INDEX($D$17:$D$25,MATCH($B26,$B$17:$B$25,0)),"")) | E26: =IFERROR(INDEX(Dim_Category[CategoryName],MATCH(INDEX(Dim_Vendor[DefaultCategoryID],MATCH($D26,Dim_Vendor[VendorName],0)),Dim_Category[CategoryID],0)),"") | H26: =IF($C26="","",IF(SignConvention="Negative = Expense",IF($C26<0,"Expense","Income"),IF($C26>0,"Expense","Income"))) | I26: =IF($C26="","",ABS($C26))
D27: =IF($B27="","",IFERROR(INDEX($D$17:$D$26,MATCH($B27,$B$17:$B$26,0)),"")) | E27: =IFERROR(INDEX(Dim_Category[CategoryName],MATCH(INDEX(Dim_Vendor[DefaultCategoryID],MATCH($D27,Dim_Vendor[VendorName],0)),Dim_Category[CategoryID],0)),"") | H27: =IF($C27="","",IF(SignConvention="Negative = Expense",IF($C27<0,"Expense","Income"),IF($C27>0,"Expense","Income"))) | I27: =IF($C27="","",ABS($C27))
D28: =IF($B28="","",IFERROR(INDEX($D$17:$D$27,MATCH($B28,$B$17:$B$27,0)),"")) | E28: =IFERROR(INDEX(Dim_Category[CategoryName],MATCH(INDEX(Dim_Vendor[DefaultCategoryID],MATCH($D28,Dim_Vendor[VendorName],0)),Dim_Category[CategoryID],0)),"") | H28: =IF($C28="","",IF(SignConvention="Negative = Expense",IF($C28<0,"Expense","Income"),IF($C28>0,"Expense","Income"))) | I28: =IF($C28="","",ABS($C28))
D29: =IF($B29="","",IFERROR(INDEX($D$17:$D$28,MATCH($B29,$B$17:$B$28,0)),"")) | E29: =IFERROR(INDEX(Dim_Category[CategoryName],MATCH(INDEX(Dim_Vendor[DefaultCategoryID],MATCH($D29,Dim_Vendor[VendorName],0)),Dim_Category[CategoryID],0)),"") | H29: =IF($C29="","",IF(SignConvention="Negative = Expense",IF($C29<0,"Expense","Income"),IF($C29>0,"Expense","Income"))) | I29: =IF($C29="","",ABS($C29))
D30: =IF($B30="","",IFERROR(INDEX($D$17:$D$29,MATCH($B30,$B$17:$B$29,0)),"")) | E30: =IFERROR(INDEX(Dim_Category[CategoryName],MATCH(INDEX(Dim_Vendor[DefaultCategoryID],MATCH($D30,Dim_Vendor[VendorName],0)),Dim_Category[CategoryID],0)),"") | H30: =IF($C30="","",IF(SignConvention="Negative = Expense",IF($C30<0,"Expense","Income"),IF($C30>0,"Expense","Income"))) | I30: =IF($C30="","",ABS($C30))
D31: =IF($B31="","",IFERROR(INDEX($D$17:$D$30,MATCH($B31,$B$17:$B$30,0)),"")) | E31: =IFERROR(INDEX(Dim_Category[CategoryName],MATCH(INDEX(Dim_Vendor[DefaultCategoryID],MATCH($D31,Dim_Vendor[VendorName],0)),Dim_Category[CategoryID],0)),"") | H31: =IF($C31="","",IF(SignConvention="Negative = Expense",IF($C31<0,"Expense","Income"),IF($C31>0,"Expense","Income"))) | I31: =IF($C31="","",ABS($C31))
D32: =IF($B32="","",IFERROR(INDEX($D$17:$D$31,MATCH($B32,$B$17:$B$31,0)),"")) | E32: =IFERROR(INDEX(Dim_Category[CategoryName],MATCH(INDEX(Dim_Vendor[DefaultCategoryID],MATCH($D32,Dim_Vendor[VendorName],0)),Dim_Category[CategoryID],0)),"") | H32: =IF($C32="","",IF(SignConvention="Negative = Expense",IF($C32<0,"Expense","Income"),IF($C32>0,"Expense","Income"))) | I32: =IF($C32="","",ABS($C32))
D33: =IF($B33="","",IFERROR(INDEX($D$17:$D$32,MATCH($B33,$B$17:$B$32,0)),"")) | E33: =IFERROR(INDEX(Dim_Category[CategoryName],MATCH(INDEX(Dim_Vendor[DefaultCategoryID],MATCH($D33,Dim_Vendor[VendorName],0)),Dim_Category[CategoryID],0)),"") | H33: =IF($C33="","",IF(SignConvention="Negative = Expense",IF($C33<0,"Expense","Income"),IF($C33>0,"Expense","Income"))) | I33: =IF($C33="","",ABS($C33))
D34: =IF($B34="","",IFERROR(INDEX($D$17:$D$33,MATCH($B34,$B$17:$B$33,0)),"")) | E34: =IFERROR(INDEX(Dim_Category[CategoryName],MATCH(INDEX(Dim_Vendor[DefaultCategoryID],MATCH($D34,Dim_Vendor[VendorName],0)),Dim_Category[CategoryID],0)),"") | H34: =IF($C34="","",IF(SignConvention="Negative = Expense",IF($C34<0,"Expense","Income"),IF($C34>0,"Expense","Income"))) | I34: =IF($C34="","",ABS($C34))
D35: =IF($B35="","",IFERROR(INDEX($D$17:$D$34,MATCH($B35,$B$17:$B$34,0)),"")) | E35: =IFERROR(INDEX(Dim_Category[CategoryName],MATCH(INDEX(Dim_Vendor[DefaultCategoryID],MATCH($D35,Dim_Vendor[VendorName],0)),Dim_Category[CategoryID],0)),"") | H35: =IF($C35="","",IF(SignConvention="Negative = Expense",IF($C35<0,"Expense","Income"),IF($C35>0,"Expense","Income"))) | I35: =IF($C35="","",ABS($C35))
D36: =IF($B36="","",IFERROR(INDEX($D$17:$D$35,MATCH($B36,$B$17:$B$35,0)),"")) | E36: =IFERROR(INDEX(Dim_Category[CategoryName],MATCH(INDEX(Dim_Vendor[DefaultCategoryID],MATCH($D36,Dim_Vendor[VendorName],0)),Dim_Category[CategoryID],0)),"") | H36: =IF($C36="","",IF(SignConvention="Negative = Expense",IF($C36<0,"Expense","Income"),IF($C36>0,"Expense","Income"))) | I36: =IF($C36="","",ABS($C36))
D37: =IF($B37="","",IFERROR(INDEX($D$17:$D$36,MATCH($B37,$B$17:$B$36,0)),"")) | E37: =IFERROR(INDEX(Dim_Category[CategoryName],MATCH(INDEX(Dim_Vendor[DefaultCategoryID],MATCH($D37,Dim_Vendor[VendorName],0)),Dim_Category[CategoryID],0)),"") | H37: =IF($C37="","",IF(SignConvention="Negative = Expense",IF($C37<0,"Expense","Income"),IF($C37>0,"Expense","Income"))) | I37: =IF($C37="","",ABS($C37))
D38: =IF($B38="","",IFERROR(INDEX($D$17:$D$37,MATCH($B38,$B$17:$B$37,0)),"")) | E38: =IFERROR(INDEX(Dim_Category[CategoryName],MATCH(INDEX(Dim_Vendor[DefaultCategoryID],MATCH($D38,Dim_Vendor[VendorName],0)),Dim_Category[CategoryID],0)),"") | H38: =IF($C38="","",IF(SignConvention="Negative = Expense",IF($C38<0,"Expense","Income"),IF($C38>0,"Expense","Income"))) | I38: =IF($C38="","",ABS($C38))
D39: =IF($B39="","",IFERROR(INDEX($D$17:$D$38,MATCH($B39,$B$17:$B$38,0)),"")) | E39: =IFERROR(INDEX(Dim_Category[CategoryName],MATCH(INDEX(Dim_Vendor[DefaultCategoryID],MATCH($D39,Dim_Vendor[VendorName],0)),Dim_Category[CategoryID],0)),"") | H39: =IF($C39="","",IF(SignConvention="Negative = Expense",IF($C39<0,"Expense","Income"),IF($C39>0,"Expense","Income"))) | I39: =IF($C39="","",ABS($C39))
D40: =IF($B40="","",IFERROR(INDEX($D$17:$D$39,MATCH($B40,$B$17:$B$39,0)),"")) | E40: =IFERROR(INDEX(Dim_Category[CategoryName],MATCH(INDEX(Dim_Vendor[DefaultCategoryID],MATCH($D40,Dim_Vendor[VendorName],0)),Dim_Category[CategoryID],0)),"") | H40: =IF($C40="","",IF(SignConvention="Negative = Expense",IF($C40<0,"Expense","Income"),IF($C40>0,"Expense","Income"))) | I40: =IF($C40="","",ABS($C40))
D41: =IF($B41="","",IFERROR(INDEX($D$17:$D$40,MATCH($B41,$B$17:$B$40,0)),"")) | E41: =IFERROR(INDEX(Dim_Category[CategoryName],MATCH(INDEX(Dim_Vendor[DefaultCategoryID],MATCH($D41,Dim_Vendor[VendorName],0)),Dim_Category[CategoryID],0)),"") | H41: =IF($C41="","",IF(SignConvention="Negative = Expense",IF($C41<0,"Expense","Income"),IF($C41>0,"Expense","Income"))) | I41: =IF($C41="","",ABS($C41))
D42: =IF($B42="","",IFERROR(INDEX($D$17:$D$41,MATCH($B42,$B$17:$B$41,0)),"")) | E42: =IFERROR(INDEX(Dim_Category[CategoryName],MATCH(INDEX(Dim_Vendor[DefaultCategoryID],MATCH($D42,Dim_Vendor[VendorName],0)),Dim_Category[CategoryID],0)),"") | H42: =IF($C42="","",IF(SignConvention="Negative = Expense",IF($C42<0,"Expense","Income"),IF($C42>0,"Expense","Income"))) | I42: =IF($C42="","",ABS($C42))
D43: =IF($B43="","",IFERROR(INDEX($D$17:$D$42,MATCH($B43,$B$17:$B$42,0)),"")) | E43: =IFERROR(INDEX(Dim_Category[CategoryName],MATCH(INDEX(Dim_Vendor[DefaultCategoryID],MATCH($D43,Dim_Vendor[VendorName],0)),Dim_Category[CategoryID],0)),"") | H43: =IF($C43="","",IF(SignConvention="Negative = Expense",IF($C43<0,"Expense","Income"),IF($C43>0,"Expense","Income"))) | I43: =IF($C43="","",ABS($C43))
D44: =IF($B44="","",IFERROR(INDEX($D$17:$D$43,MATCH($B44,$B$17:$B$43,0)),"")) | E44: =IFERROR(INDEX(Dim_Category[CategoryName],MATCH(INDEX(Dim_Vendor[DefaultCategoryID],MATCH($D44,Dim_Vendor[VendorName],0)),Dim_Category[CategoryID],0)),"") | H44: =IF($C44="","",IF(SignConvention="Negative = Expense",IF($C44<0,"Expense","Income"),IF($C44>0,"Expense","Income"))) | I44: =IF($C44="","",ABS($C44))
D45: =IF($B45="","",IFERROR(INDEX($D$17:$D$44,MATCH($B45,$B$17:$B$44,0)),"")) | E45: =IFERROR(INDEX(Dim_Category[CategoryName],MATCH(INDEX(Dim_Vendor[DefaultCategoryID],MATCH($D45,Dim_Vendor[VendorName],0)),Dim_Category[CategoryID],0)),"") | H45: =IF($C45="","",IF(SignConvention="Negative = Expense",IF($C45<0,"Expense","Income"),IF($C45>0,"Expense","Income"))) | I45: =IF($C45="","",ABS($C45))
D46: =IF($B46="","",IFERROR(INDEX($D$17:$D$45,MATCH($B46,$B$17:$B$45,0)),"")) | E46: =IFERROR(INDEX(Dim_Category[CategoryName],MATCH(INDEX(Dim_Vendor[DefaultCategoryID],MATCH($D46,Dim_Vendor[VendorName],0)),Dim_Category[CategoryID],0)),"") | H46: =IF($C46="","",IF(SignConvention="Negative = Expense",IF($C46<0,"Expense","Income"),IF($C46>0,"Expense","Income"))) | I46: =IF($C46="","",ABS($C46))
D47: =IF($B47="","",IFERROR(INDEX($D$17:$D$46,MATCH($B47,$B$17:$B$46,0)),"")) | E47: =IFERROR(INDEX(Dim_Category[CategoryName],MATCH(INDEX(Dim_Vendor[DefaultCategoryID],MATCH($D47,Dim_Vendor[VendorName],0)),Dim_Category[CategoryID],0)),"") | H47: =IF($C47="","",IF(SignConvention="Negative = Expense",IF($C47<0,"Expense","Income"),IF($C47>0,"Expense","Income"))) | I47: =IF($C47="","",ABS($C47))
D48: =IF($B48="","",IFERROR(INDEX($D$17:$D$47,MATCH($B48,$B$17:$B$47,0)),"")) | E48: =IFERROR(INDEX(Dim_Category[CategoryName],MATCH(INDEX(Dim_Vendor[DefaultCategoryID],MATCH($D48,Dim_Vendor[VendorName],0)),Dim_Category[CategoryID],0)),"") | H48: =IF($C48="","",IF(SignConvention="Negative = Expense",IF($C48<0,"Expense","Income"),IF($C48>0,"Expense","Income"))) | I48: =IF($C48="","",ABS($C48))
D49: =IF($B49="","",IFERROR(INDEX($D$17:$D$48,MATCH($B49,$B$17:$B$48,0)),"")) | E49: =IFERROR(INDEX(Dim_Category[CategoryName],MATCH(INDEX(Dim_Vendor[DefaultCategoryID],MATCH($D49,Dim_Vendor[VendorName],0)),Dim_Category[CategoryID],0)),"") | H49: =IF($C49="","",IF(SignConvention="Negative = Expense",IF($C49<0,"Expense","Income"),IF($C49>0,"Expense","Income"))) | I49: =IF($C49="","",ABS($C49))
D50: =IF($B50="","",IFERROR(INDEX($D$17:$D$49,MATCH($B50,$B$17:$B$49,0)),"")) | E50: =IFERROR(INDEX(Dim_Category[CategoryName],MATCH(INDEX(Dim_Vendor[DefaultCategoryID],MATCH($D50,Dim_Vendor[VendorName],0)),Dim_Category[CategoryID],0)),"") | H50: =IF($C50="","",IF(SignConvention="Negative = Expense",IF($C50<0,"Expense","Income"),IF($C50>0,"Expense","Income"))) | I50: =IF($C50="","",ABS($C50))
D51: =IF($B51="","",IFERROR(INDEX($D$17:$D$50,MATCH($B51,$B$17:$B$50,0)),"")) | E51: =IFERROR(INDEX(Dim_Category[CategoryName],MATCH(INDEX(Dim_Vendor[DefaultCategoryID],MATCH($D51,Dim_Vendor[VendorName],0)),Dim_Category[CategoryID],0)),"") | H51: =IF($C51="","",IF(SignConvention="Negative = Expense",IF($C51<0,"Expense","Income"),IF($C51>0,"Expense","Income"))) | I51: =IF($C51="","",ABS($C51))
D52: =IF($B52="","",IFERROR(INDEX($D$17:$D$51,MATCH($B52,$B$17:$B$51,0)),"")) | E52: =IFERROR(INDEX(Dim_Category[CategoryName],MATCH(INDEX(Dim_Vendor[DefaultCategoryID],MATCH($D52,Dim_Vendor[VendorName],0)),Dim_Category[CategoryID],0)),"") | H52: =IF($C52="","",IF(SignConvention="Negative = Expense",IF($C52<0,"Expense","Income"),IF($C52>0,"Expense","Income"))) | I52: =IF($C52="","",ABS($C52))
D53: =IF($B53="","",IFERROR(INDEX($D$17:$D$52,MATCH($B53,$B$17:$B$52,0)),"")) | E53: =IFERROR(INDEX(Dim_Category[CategoryName],MATCH(INDEX(Dim_Vendor[DefaultCategoryID],MATCH($D53,Dim_Vendor[VendorName],0)),Dim_Category[CategoryID],0)),"") | H53: =IF($C53="","",IF(SignConvention="Negative = Expense",IF($C53<0,"Expense","Income"),IF($C53>0,"Expense","Income"))) | I53: =IF($C53="","",ABS($C53))
D54: =IF($B54="","",IFERROR(INDEX($D$17:$D$53,MATCH($B54,$B$17:$B$53,0)),"")) | E54: =IFERROR(INDEX(Dim_Category[CategoryName],MATCH(INDEX(Dim_Vendor[DefaultCategoryID],MATCH($D54,Dim_Vendor[VendorName],0)),Dim_Category[CategoryID],0)),"") | H54: =IF($C54="","",IF(SignConvention="Negative = Expense",IF($C54<0,"Expense","Income"),IF($C54>0,"Expense","Income"))) | I54: =IF($C54="","",ABS($C54))
D55: =IF($B55="","",IFERROR(INDEX($D$17:$D$54,MATCH($B55,$B$17:$B$54,0)),"")) | E55: =IFERROR(INDEX(Dim_Category[CategoryName],MATCH(INDEX(Dim_Vendor[DefaultCategoryID],MATCH($D55,Dim_Vendor[VendorName],0)),Dim_Category[CategoryID],0)),"") | H55: =IF($C55="","",IF(SignConvention="Negative = Expense",IF($C55<0,"Expense","Income"),IF($C55>0,"Expense","Income"))) | I55: =IF($C55="","",ABS($C55))
D56: =IF($B56="","",IFERROR(INDEX($D$17:$D$55,MATCH($B56,$B$17:$B$55,0)),"")) | E56: =IFERROR(INDEX(Dim_Category[CategoryName],MATCH(INDEX(Dim_Vendor[DefaultCategoryID],MATCH($D56,Dim_Vendor[VendorName],0)),Dim_Category[CategoryID],0)),"") | H56: =IF($C56="","",IF(SignConvention="Negative = Expense",IF($C56<0,"Expense","Income"),IF($C56>0,"Expense","Income"))) | I56: =IF($C56="","",ABS($C56))
D57: =IF($B57="","",IFERROR(INDEX($D$17:$D$56,MATCH($B57,$B$17:$B$56,0)),"")) | E57: =IFERROR(INDEX(Dim_Category[CategoryName],MATCH(INDEX(Dim_Vendor[DefaultCategoryID],MATCH($D57,Dim_Vendor[VendorName],0)),Dim_Category[CategoryID],0)),"") | H57: =IF($C57="","",IF(SignConvention="Negative = Expense",IF($C57<0,"Expense","Income"),IF($C57>0,"Expense","Income"))) | I57: =IF($C57="","",ABS($C57))
D58: =IF($B58="","",IFERROR(INDEX($D$17:$D$57,MATCH($B58,$B$17:$B$57,0)),"")) | E58: =IFERROR(INDEX(Dim_Category[CategoryName],MATCH(INDEX(Dim_Vendor[DefaultCategoryID],MATCH($D58,Dim_Vendor[VendorName],0)),Dim_Category[CategoryID],0)),"") | H58: =IF($C58="","",IF(SignConvention="Negative = Expense",IF($C58<0,"Expense","Income"),IF($C58>0,"Expense","Income"))) | I58: =IF($C58="","",ABS($C58))
D59: =IF($B59="","",IFERROR(INDEX($D$17:$D$58,MATCH($B59,$B$17:$B$58,0)),"")) | E59: =IFERROR(INDEX(Dim_Category[CategoryName],MATCH(INDEX(Dim_Vendor[DefaultCategoryID],MATCH($D59,Dim_Vendor[VendorName],0)),Dim_Category[CategoryID],0)),"") | H59: =IF($C59="","",IF(SignConvention="Negative = Expense",IF($C59<0,"Expense","Income"),IF($C59>0,"Expense","Income"))) | I59: =IF($C59="","",ABS($C59))
D60: =IF($B60="","",IFERROR(INDEX($D$17:$D$59,MATCH($B60,$B$17:$B$59,0)),"")) | E60: =IFERROR(INDEX(Dim_Category[CategoryName],MATCH(INDEX(Dim_Vendor[DefaultCategoryID],MATCH($D60,Dim_Vendor[VendorName],0)),Dim_Category[CategoryID],0)),"") | H60: =IF($C60="","",IF(SignConvention="Negative = Expense",IF($C60<0,"Expense","Income"),IF($C60>0,"Expense","Income"))) | I60: =IF($C60="","",ABS($C60))
D61: =IF($B61="","",IFERROR(INDEX($D$17:$D$60,MATCH($B61,$B$17:$B$60,0)),"")) | E61: =IFERROR(INDEX(Dim_Category[CategoryName],MATCH(INDEX(Dim_Vendor[DefaultCategoryID],MATCH($D61,Dim_Vendor[VendorName],0)),Dim_Category[CategoryID],0)),"") | H61: =IF($C61="","",IF(SignConvention="Negative = Expense",IF($C61<0,"Expense","Income"),IF($C61>0,"Expense","Income"))) | I61: =IF($C61="","",ABS($C61))
D62: =IF($B62="","",IFERROR(INDEX($D$17:$D$61,MATCH($B62,$B$17:$B$61,0)),"")) | E62: =IFERROR(INDEX(Dim_Category[CategoryName],MATCH(INDEX(Dim_Vendor[DefaultCategoryID],MATCH($D62,Dim_Vendor[VendorName],0)),Dim_Category[CategoryID],0)),"") | H62: =IF($C62="","",IF(SignConvention="Negative = Expense",IF($C62<0,"Expense","Income"),IF($C62>0,"Expense","Income"))) | I62: =IF($C62="","",ABS($C62))
D63: =IF($B63="","",IFERROR(INDEX($D$17:$D$62,MATCH($B63,$B$17:$B$62,0)),"")) | E63: =IFERROR(INDEX(Dim_Category[CategoryName],MATCH(INDEX(Dim_Vendor[DefaultCategoryID],MATCH($D63,Dim_Vendor[VendorName],0)),Dim_Category[CategoryID],0)),"") | H63: =IF($C63="","",IF(SignConvention="Negative = Expense",IF($C63<0,"Expense","Income"),IF($C63>0,"Expense","Income"))) | I63: =IF($C63="","",ABS($C63))
D64: =IF($B64="","",IFERROR(INDEX($D$17:$D$63,MATCH($B64,$B$17:$B$63,0)),"")) | E64: =IFERROR(INDEX(Dim_Category[CategoryName],MATCH(INDEX(Dim_Vendor[DefaultCategoryID],MATCH($D64,Dim_Vendor[VendorName],0)),Dim_Category[CategoryID],0)),"") | H64: =IF($C64="","",IF(SignConvention="Negative = Expense",IF($C64<0,"Expense","Income"),IF($C64>0,"Expense","Income"))) | I64: =IF($C64="","",ABS($C64))
D65: =IF($B65="","",IFERROR(INDEX($D$17:$D$64,MATCH($B65,$B$17:$B$64,0)),"")) | E65: =IFERROR(INDEX(Dim_Category[CategoryName],MATCH(INDEX(Dim_Vendor[DefaultCategoryID],MATCH($D65,Dim_Vendor[VendorName],0)),Dim_Category[CategoryID],0)),"") | H65: =IF($C65="","",IF(SignConvention="Negative = Expense",IF($C65<0,"Expense","Income"),IF($C65>0,"Expense","Income"))) | I65: =IF($C65="","",ABS($C65))
D66: =IF($B66="","",IFERROR(INDEX($D$17:$D$65,MATCH($B66,$B$17:$B$65,0)),"")) | E66: =IFERROR(INDEX(Dim_Category[CategoryName],MATCH(INDEX(Dim_Vendor[DefaultCategoryID],MATCH($D66,Dim_Vendor[VendorName],0)),Dim_Category[CategoryID],0)),"") | H66: =IF($C66="","",IF(SignConvention="Negative = Expense",IF($C66<0,"Expense","Income"),IF($C66>0,"Expense","Income"))) | I66: =IF($C66="","",ABS($C66))
D67: =IF($B67="","",IFERROR(INDEX($D$17:$D$66,MATCH($B67,$B$17:$B$66,0)),"")) | E67: =IFERROR(INDEX(Dim_Category[CategoryName],MATCH(INDEX(Dim_Vendor[DefaultCategoryID],MATCH($D67,Dim_Vendor[VendorName],0)),Dim_Category[CategoryID],0)),"") | H67: =IF($C67="","",IF(SignConvention="Negative = Expense",IF($C67<0,"Expense","Income"),IF($C67>0,"Expense","Income"))) | I67: =IF($C67="","",ABS($C67))
D68: =IF($B68="","",IFERROR(INDEX($D$17:$D$67,MATCH($B68,$B$17:$B$67,0)),"")) | E68: =IFERROR(INDEX(Dim_Category[CategoryName],MATCH(INDEX(Dim_Vendor[DefaultCategoryID],MATCH($D68,Dim_Vendor[VendorName],0)),Dim_Category[CategoryID],0)),"") | H68: =IF($C68="","",IF(SignConvention="Negative = Expense",IF($C68<0,"Expense","Income"),IF($C68>0,"Expense","Income"))) | I68: =IF($C68="","",ABS($C68))
D69: =IF($B69="","",IFERROR(INDEX($D$17:$D$68,MATCH($B69,$B$17:$B$68,0)),"")) | E69: =IFERROR(INDEX(Dim_Category[CategoryName],MATCH(INDEX(Dim_Vendor[DefaultCategoryID],MATCH($D69,Dim_Vendor[VendorName],0)),Dim_Category[CategoryID],0)),"") | H69: =IF($C69="","",IF(SignConvention="Negative = Expense",IF($C69<0,"Expense","Income"),IF($C69>0,"Expense","Income"))) | I69: =IF($C69="","",ABS($C69))
D70: =IF($B70="","",IFERROR(INDEX($D$17:$D$69,MATCH($B70,$B$17:$B$69,0)),"")) | E70: =IFERROR(INDEX(Dim_Category[CategoryName],MATCH(INDEX(Dim_Vendor[DefaultCategoryID],MATCH($D70,Dim_Vendor[VendorName],0)),Dim_Category[CategoryID],0)),"") | H70: =IF($C70="","",IF(SignConvention="Negative = Expense",IF($C70<0,"Expense","Income"),IF($C70>0,"Expense","Income"))) | I70: =IF($C70="","",ABS($C70))
D71: =IF($B71="","",IFERROR(INDEX($D$17:$D$70,MATCH($B71,$B$17:$B$70,0)),"")) | E71: =IFERROR(INDEX(Dim_Category[CategoryName],MATCH(INDEX(Dim_Vendor[DefaultCategoryID],MATCH($D71,Dim_Vendor[VendorName],0)),Dim_Category[CategoryID],0)),"") | H71: =IF($C71="","",IF(SignConvention="Negative = Expense",IF($C71<0,"Expense","Income"),IF($C71>0,"Expense","Income"))) | I71: =IF($C71="","",ABS($C71))
D72: =IF($B72="","",IFERROR(INDEX($D$17:$D$71,MATCH($B72,$B$17:$B$71,0)),"")) | E72: =IFERROR(INDEX(Dim_Category[CategoryName],MATCH(INDEX(Dim_Vendor[DefaultCategoryID],MATCH($D72,Dim_Vendor[VendorName],0)),Dim_Category[CategoryID],0)),"") | H72: =IF($C72="","",IF(SignConvention="Negative = Expense",IF($C72<0,"Expense","Income"),IF($C72>0,"Expense","Income"))) | I72: =IF($C72="","",ABS($C72))
D73: =IF($B73="","",IFERROR(INDEX($D$17:$D$72,MATCH($B73,$B$17:$B$72,0)),"")) | E73: =IFERROR(INDEX(Dim_Category[CategoryName],MATCH(INDEX(Dim_Vendor[DefaultCategoryID],MATCH($D73,Dim_Vendor[VendorName],0)),Dim_Category[CategoryID],0)),"") | H73: =IF($C73="","",IF(SignConvention="Negative = Expense",IF($C73<0,"Expense","Income"),IF($C73>0,"Expense","Income"))) | I73: =IF($C73="","",ABS($C73))
D74: =IF($B74="","",IFERROR(INDEX($D$17:$D$73,MATCH($B74,$B$17:$B$73,0)),"")) | E74: =IFERROR(INDEX(Dim_Category[CategoryName],MATCH(INDEX(Dim_Vendor[DefaultCategoryID],MATCH($D74,Dim_Vendor[VendorName],0)),Dim_Category[CategoryID],0)),"") | H74: =IF($C74="","",IF(SignConvention="Negative = Expense",IF($C74<0,"Expense","Income"),IF($C74>0,"Expense","Income"))) | I74: =IF($C74="","",ABS($C74))
D75: =IF($B75="","",IFERROR(INDEX($D$17:$D$74,MATCH($B75,$B$17:$B$74,0)),"")) | E75: =IFERROR(INDEX(Dim_Category[CategoryName],MATCH(INDEX(Dim_Vendor[DefaultCategoryID],MATCH($D75,Dim_Vendor[VendorName],0)),Dim_Category[CategoryID],0)),"") | H75: =IF($C75="","",IF(SignConvention="Negative = Expense",IF($C75<0,"Expense","Income"),IF($C75>0,"Expense","Income"))) | I75: =IF($C75="","",ABS($C75))
D76: =IF($B76="","",IFERROR(INDEX($D$17:$D$75,MATCH($B76,$B$17:$B$75,0)),"")) | E76: =IFERROR(INDEX(Dim_Category[CategoryName],MATCH(INDEX(Dim_Vendor[DefaultCategoryID],MATCH($D76,Dim_Vendor[VendorName],0)),Dim_Category[CategoryID],0)),"") | H76: =IF($C76="","",IF(SignConvention="Negative = Expense",IF($C76<0,"Expense","Income"),IF($C76>0,"Expense","Income"))) | I76: =IF($C76="","",ABS($C76))
D77: =IF($B77="","",IFERROR(INDEX($D$17:$D$76,MATCH($B77,$B$17:$B$76,0)),"")) | E77: =IFERROR(INDEX(Dim_Category[CategoryName],MATCH(INDEX(Dim_Vendor[DefaultCategoryID],MATCH($D77,Dim_Vendor[VendorName],0)),Dim_Category[CategoryID],0)),"") | H77: =IF($C77="","",IF(SignConvention="Negative = Expense",IF($C77<0,"Expense","Income"),IF($C77>0,"Expense","Income"))) | I77: =IF($C77="","",ABS($C77))
D78: =IF($B78="","",IFERROR(INDEX($D$17:$D$77,MATCH($B78,$B$17:$B$77,0)),"")) | E78: =IFERROR(INDEX(Dim_Category[CategoryName],MATCH(INDEX(Dim_Vendor[DefaultCategoryID],MATCH($D78,Dim_Vendor[VendorName],0)),Dim_Category[CategoryID],0)),"") | H78: =IF($C78="","",IF(SignConvention="Negative = Expense",IF($C78<0,"Expense","Income"),IF($C78>0,"Expense","Income"))) | I78: =IF($C78="","",ABS($C78))
D79: =IF($B79="","",IFERROR(INDEX($D$17:$D$78,MATCH($B79,$B$17:$B$78,0)),"")) | E79: =IFERROR(INDEX(Dim_Category[CategoryName],MATCH(INDEX(Dim_Vendor[DefaultCategoryID],MATCH($D79,Dim_Vendor[VendorName],0)),Dim_Category[CategoryID],0)),"") | H79: =IF($C79="","",IF(SignConvention="Negative = Expense",IF($C79<0,"Expense","Income"),IF($C79>0,"Expense","Income"))) | I79: =IF($C79="","",ABS($C79))
D80: =IF($B80="","",IFERROR(INDEX($D$17:$D$79,MATCH($B80,$B$17:$B$79,0)),"")) | E80: =IFERROR(INDEX(Dim_Category[CategoryName],MATCH(INDEX(Dim_Vendor[DefaultCategoryID],MATCH($D80,Dim_Vendor[VendorName],0)),Dim_Category[CategoryID],0)),"") | H80: =IF($C80="","",IF(SignConvention="Negative = Expense",IF($C80<0,"Expense","Income"),IF($C80>0,"Expense","Income"))) | I80: =IF($C80="","",ABS($C80))
D81: =IF($B81="","",IFERROR(INDEX($D$17:$D$80,MATCH($B81,$B$17:$B$80,0)),"")) | E81: =IFERROR(INDEX(Dim_Category[CategoryName],MATCH(INDEX(Dim_Vendor[DefaultCategoryID],MATCH($D81,Dim_Vendor[VendorName],0)),Dim_Category[CategoryID],0)),"") | H81: =IF($C81="","",IF(SignConvention="Negative = Expense",IF($C81<0,"Expense","Income"),IF($C81>0,"Expense","Income"))) | I81: =IF($C81="","",ABS($C81))
D82: =IF($B82="","",IFERROR(INDEX($D$17:$D$81,MATCH($B82,$B$17:$B$81,0)),"")) | E82: =IFERROR(INDEX(Dim_Category[CategoryName],MATCH(INDEX(Dim_Vendor[DefaultCategoryID],MATCH($D82,Dim_Vendor[VendorName],0)),Dim_Category[CategoryID],0)),"") | H82: =IF($C82="","",IF(SignConvention="Negative = Expense",IF($C82<0,"Expense","Income"),IF($C82>0,"Expense","Income"))) | I82: =IF($C82="","",ABS($C82))
D83: =IF($B83="","",IFERROR(INDEX($D$17:$D$82,MATCH($B83,$B$17:$B$82,0)),"")) | E83: =IFERROR(INDEX(Dim_Category[CategoryName],MATCH(INDEX(Dim_Vendor[DefaultCategoryID],MATCH($D83,Dim_Vendor[VendorName],0)),Dim_Category[CategoryID],0)),"") | H83: =IF($C83="","",IF(SignConvention="Negative = Expense",IF($C83<0,"Expense","Income"),IF($C83>0,"Expense","Income"))) | I83: =IF($C83="","",ABS($C83))
D84: =IF($B84="","",IFERROR(INDEX($D$17:$D$83,MATCH($B84,$B$17:$B$83,0)),"")) | E84: =IFERROR(INDEX(Dim_Category[CategoryName],MATCH(INDEX(Dim_Vendor[DefaultCategoryID],MATCH($D84,Dim_Vendor[VendorName],0)),Dim_Category[CategoryID],0)),"") | H84: =IF($C84="","",IF(SignConvention="Negative = Expense",IF($C84<0,"Expense","Income"),IF($C84>0,"Expense","Income"))) | I84: =IF($C84="","",ABS($C84))
D85: =IF($B85="","",IFERROR(INDEX($D$17:$D$84,MATCH($B85,$B$17:$B$84,0)),"")) | E85: =IFERROR(INDEX(Dim_Category[CategoryName],MATCH(INDEX(Dim_Vendor[DefaultCategoryID],MATCH($D85,Dim_Vendor[VendorName],0)),Dim_Category[CategoryID],0)),"") | H85: =IF($C85="","",IF(SignConvention="Negative = Expense",IF($C85<0,"Expense","Income"),IF($C85>0,"Expense","Income"))) | I85: =IF($C85="","",ABS($C85))
D86: =IF($B86="","",IFERROR(INDEX($D$17:$D$85,MATCH($B86,$B$17:$B$85,0)),"")) | E86: =IFERROR(INDEX(Dim_Category[CategoryName],MATCH(INDEX(Dim_Vendor[DefaultCategoryID],MATCH($D86,Dim_Vendor[VendorName],0)),Dim_Category[CategoryID],0)),"") | H86: =IF($C86="","",IF(SignConvention="Negative = Expense",IF($C86<0,"Expense","Income"),IF($C86>0,"Expense","Income"))) | I86: =IF($C86="","",ABS($C86))
D87: =IF($B87="","",IFERROR(INDEX($D$17:$D$86,MATCH($B87,$B$17:$B$86,0)),"")) | E87: =IFERROR(INDEX(Dim_Category[CategoryName],MATCH(INDEX(Dim_Vendor[DefaultCategoryID],MATCH($D87,Dim_Vendor[VendorName],0)),Dim_Category[CategoryID],0)),"") | H87: =IF($C87="","",IF(SignConvention="Negative = Expense",IF($C87<0,"Expense","Income"),IF($C87>0,"Expense","Income"))) | I87: =IF($C87="","",ABS($C87))
D88: =IF($B88="","",IFERROR(INDEX($D$17:$D$87,MATCH($B88,$B$17:$B$87,0)),"")) | E88: =IFERROR(INDEX(Dim_Category[CategoryName],MATCH(INDEX(Dim_Vendor[DefaultCategoryID],MATCH($D88,Dim_Vendor[VendorName],0)),Dim_Category[CategoryID],0)),"") | H88: =IF($C88="","",IF(SignConvention="Negative = Expense",IF($C88<0,"Expense","Income"),IF($C88>0,"Expense","Income"))) | I88: =IF($C88="","",ABS($C88))
D89: =IF($B89="","",IFERROR(INDEX($D$17:$D$88,MATCH($B89,$B$17:$B$88,0)),"")) | E89: =IFERROR(INDEX(Dim_Category[CategoryName],MATCH(INDEX(Dim_Vendor[DefaultCategoryID],MATCH($D89,Dim_Vendor[VendorName],0)),Dim_Category[CategoryID],0)),"") | H89: =IF($C89="","",IF(SignConvention="Negative = Expense",IF($C89<0,"Expense","Income"),IF($C89>0,"Expense","Income"))) | I89: =IF($C89="","",ABS($C89))
D90: =IF($B90="","",IFERROR(INDEX($D$17:$D$89,MATCH($B90,$B$17:$B$89,0)),"")) | E90: =IFERROR(INDEX(Dim_Category[CategoryName],MATCH(INDEX(Dim_Vendor[DefaultCategoryID],MATCH($D90,Dim_Vendor[VendorName],0)),Dim_Category[CategoryID],0)),"") | H90: =IF($C90="","",IF(SignConvention="Negative = Expense",IF($C90<0,"Expense","Income"),IF($C90>0,"Expense","Income"))) | I90: =IF($C90="","",ABS($C90))
D91: =IF($B91="","",IFERROR(INDEX($D$17:$D$90,MATCH($B91,$B$17:$B$90,0)),"")) | E91: =IFERROR(INDEX(Dim_Category[CategoryName],MATCH(INDEX(Dim_Vendor[DefaultCategoryID],MATCH($D91,Dim_Vendor[VendorName],0)),Dim_Category[CategoryID],0)),"") | H91: =IF($C91="","",IF(SignConvention="Negative = Expense",IF($C91<0,"Expense","Income"),IF($C91>0,"Expense","Income"))) | I91: =IF($C91="","",ABS($C91))
D92: =IF($B92="","",IFERROR(INDEX($D$17:$D$91,MATCH($B92,$B$17:$B$91,0)),"")) | E92: =IFERROR(INDEX(Dim_Category[CategoryName],MATCH(INDEX(Dim_Vendor[DefaultCategoryID],MATCH($D92,Dim_Vendor[VendorName],0)),Dim_Category[CategoryID],0)),"") | H92: =IF($C92="","",IF(SignConvention="Negative = Expense",IF($C92<0,"Expense","Income"),IF($C92>0,"Expense","Income"))) | I92: =IF($C92="","",ABS($C92))
D93: =IF($B93="","",IFERROR(INDEX($D$17:$D$92,MATCH($B93,$B$17:$B$92,0)),"")) | E93: =IFERROR(INDEX(Dim_Category[CategoryName],MATCH(INDEX(Dim_Vendor[DefaultCategoryID],MATCH($D93,Dim_Vendor[VendorName],0)),Dim_Category[CategoryID],0)),"") | H93: =IF($C93="","",IF(SignConvention="Negative = Expense",IF($C93<0,"Expense","Income"),IF($C93>0,"Expense","Income"))) | I93: =IF($C93="","",ABS($C93))
D94: =IF($B94="","",IFERROR(INDEX($D$17:$D$93,MATCH($B94,$B$17:$B$93,0)),"")) | E94: =IFERROR(INDEX(Dim_Category[CategoryName],MATCH(INDEX(Dim_Vendor[DefaultCategoryID],MATCH($D94,Dim_Vendor[VendorName],0)),Dim_Category[CategoryID],0)),"") | H94: =IF($C94="","",IF(SignConvention="Negative = Expense",IF($C94<0,"Expense","Income"),IF($C94>0,"Expense","Income"))) | I94: =IF($C94="","",ABS($C94))
D95: =IF($B95="","",IFERROR(INDEX($D$17:$D$94,MATCH($B95,$B$17:$B$94,0)),"")) | E95: =IFERROR(INDEX(Dim_Category[CategoryName],MATCH(INDEX(Dim_Vendor[DefaultCategoryID],MATCH($D95,Dim_Vendor[VendorName],0)),Dim_Category[CategoryID],0)),"") | H95: =IF($C95="","",IF(SignConvention="Negative = Expense",IF($C95<0,"Expense","Income"),IF($C95>0,"Expense","Income"))) | I95: =IF($C95="","",ABS($C95))
D96: =IF($B96="","",IFERROR(INDEX($D$17:$D$95,MATCH($B96,$B$17:$B$95,0)),"")) | E96: =IFERROR(INDEX(Dim_Category[CategoryName],MATCH(INDEX(Dim_Vendor[DefaultCategoryID],MATCH($D96,Dim_Vendor[VendorName],0)),Dim_Category[CategoryID],0)),"") | H96: =IF($C96="","",IF(SignConvention="Negative = Expense",IF($C96<0,"Expense","Income"),IF($C96>0,"Expense","Income"))) | I96: =IF($C96="","",ABS($C96))
D97: =IF($B97="","",IFERROR(INDEX($D$17:$D$96,MATCH($B97,$B$17:$B$96,0)),"")) | E97: =IFERROR(INDEX(Dim_Category[CategoryName],MATCH(INDEX(Dim_Vendor[DefaultCategoryID],MATCH($D97,Dim_Vendor[VendorName],0)),Dim_Category[CategoryID],0)),"") | H97: =IF($C97="","",IF(SignConvention="Negative = Expense",IF($C97<0,"Expense","Income"),IF($C97>0,"Expense","Income"))) | I97: =IF($C97="","",ABS($C97))
D98: =IF($B98="","",IFERROR(INDEX($D$17:$D$97,MATCH($B98,$B$17:$B$97,0)),"")) | E98: =IFERROR(INDEX(Dim_Category[CategoryName],MATCH(INDEX(Dim_Vendor[DefaultCategoryID],MATCH($D98,Dim_Vendor[VendorName],0)),Dim_Category[CategoryID],0)),"") | H98: =IF($C98="","",IF(SignConvention="Negative = Expense",IF($C98<0,"Expense","Income"),IF($C98>0,"Expense","Income"))) | I98: =IF($C98="","",ABS($C98))
D99: =IF($B99="","",IFERROR(INDEX($D$17:$D$98,MATCH($B99,$B$17:$B$98,0)),"")) | E99: =IFERROR(INDEX(Dim_Category[CategoryName],MATCH(INDEX(Dim_Vendor[DefaultCategoryID],MATCH($D99,Dim_Vendor[VendorName],0)),Dim_Category[CategoryID],0)),"") | H99: =IF($C99="","",IF(SignConvention="Negative = Expense",IF($C99<0,"Expense","Income"),IF($C99>0,"Expense","Income"))) | I99: =IF($C99="","",ABS($C99))
D100: =IF($B100="","",IFERROR(INDEX($D$17:$D$99,MATCH($B100,$B$17:$B$99,0)),"")) | E100: =IFERROR(INDEX(Dim_Category[CategoryName],MATCH(INDEX(Dim_Vendor[DefaultCategoryID],MATCH($D100,Dim_Vendor[VendorName],0)),Dim_Category[CategoryID],0)),"") | H100: =IF($C100="","",IF(SignConvention="Negative = Expense",IF($C100<0,"Expense","Income"),IF($C100>0,"Expense","Income"))) | I100: =IF($C100="","",ABS($C100))
D101: =IF($B101="","",IFERROR(INDEX($D$17:$D$100,MATCH($B101,$B$17:$B$100,0)),"")) | E101: =IFERROR(INDEX(Dim_Category[CategoryName],MATCH(INDEX(Dim_Vendor[DefaultCategoryID],MATCH($D101,Dim_Vendor[VendorName],0)),Dim_Category[CategoryID],0)),"") | H101: =IF($C101="","",IF(SignConvention="Negative = Expense",IF($C101<0,"Expense","Income"),IF($C101>0,"Expense","Income"))) | I101: =IF($C101="","",ABS($C101))
D102: =IF($B102="","",IFERROR(INDEX($D$17:$D$101,MATCH($B102,$B$17:$B$101,0)),"")) | E102: =IFERROR(INDEX(Dim_Category[CategoryName],MATCH(INDEX(Dim_Vendor[DefaultCategoryID],MATCH($D102,Dim_Vendor[VendorName],0)),Dim_Category[CategoryID],0)),"") | H102: =IF($C102="","",IF(SignConvention="Negative = Expense",IF($C102<0,"Expense","Income"),IF($C102>0,"Expense","Income"))) | I102: =IF($C102="","",ABS($C102))
D103: =IF($B103="","",IFERROR(INDEX($D$17:$D$102,MATCH($B103,$B$17:$B$102,0)),"")) | E103: =IFERROR(INDEX(Dim_Category[CategoryName],MATCH(INDEX(Dim_Vendor[DefaultCategoryID],MATCH($D103,Dim_Vendor[VendorName],0)),Dim_Category[CategoryID],0)),"") | H103: =IF($C103="","",IF(SignConvention="Negative = Expense",IF($C103<0,"Expense","Income"),IF($C103>0,"Expense","Income"))) | I103: =IF($C103="","",ABS($C103))
D104: =IF($B104="","",IFERROR(INDEX($D$17:$D$103,MATCH($B104,$B$17:$B$103,0)),"")) | E104: =IFERROR(INDEX(Dim_Category[CategoryName],MATCH(INDEX(Dim_Vendor[DefaultCategoryID],MATCH($D104,Dim_Vendor[VendorName],0)),Dim_Category[CategoryID],0)),"") | H104: =IF($C104="","",IF(SignConvention="Negative = Expense",IF($C104<0,"Expense","Income"),IF($C104>0,"Expense","Income"))) | I104: =IF($C104="","",ABS($C104))
...

Sheet Income
A1: Income
A4: Dim_Source
A5: SourceID | B5: SourceName
A6: 1 | B6: Employer Payroll Inc
A7: 2 | B7: Other
A10: Fact_Income — enter each paycheck/deposit here. Dropdowns keep entries consistent; ID columns (hidden) auto-lookup for reporting.
A11: IncomeID | B11: Date | C11: SourceName | D11: SourceID | E11: CategoryName | F11: CategoryID | G11: AccountName | H11: AccountID | I11: GrossAmount | J11: TaxesWithheld | K11: NetAmount | L11: RecurringFlag | M11: Notes | N11: Description
A12: =ROW()-11 | B12: 45839 | C12: Employer Payroll Inc | D12: =IFERROR(INDEX(Dim_Source[SourceID],MATCH($C12,Dim_Source[SourceName],0)),"") | E12: Payroll | F12: =IFERROR(INDEX(Dim_Category[CategoryID],MATCH($E12,Dim_Category[CategoryName],0)),"") | G12: Checking | H12: =IFERROR(INDEX(Dim_Account[AccountID],MATCH($G12,Dim_Account[AccountName],0)),"") | I12: 5100 | J12: 1224 | K12: =$I12-$J12 | L12: Yes | M12: Semi-monthly payroll
A13: =ROW()-11 | B13: 45853 | C13: Employer Payroll Inc | D13: =IFERROR(INDEX(Dim_Source[SourceID],MATCH($C13,Dim_Source[SourceName],0)),"") | E13: Payroll | F13: =IFERROR(INDEX(Dim_Category[CategoryID],MATCH($E13,Dim_Category[CategoryName],0)),"") | G13: Checking | H13: =IFERROR(INDEX(Dim_Account[AccountID],MATCH($G13,Dim_Account[AccountName],0)),"") | I13: 5100 | J13: 1224 | K13: =$I13-$J13 | L13: Yes | M13: Semi-monthly payroll
A14: =ROW()-11 | B14: 45870 | C14: Employer Payroll Inc | D14: =IFERROR(INDEX(Dim_Source[SourceID],MATCH($C14,Dim_Source[SourceName],0)),"") | E14: Payroll | F14: =IFERROR(INDEX(Dim_Category[CategoryID],MATCH($E14,Dim_Category[CategoryName],0)),"") | G14: Checking | H14: =IFERROR(INDEX(Dim_Account[AccountID],MATCH($G14,Dim_Account[AccountName],0)),"") | I14: 5100 | J14: 1224 | K14: =$I14-$J14 | L14: Yes | M14: Semi-monthly payroll
A15: =ROW()-11 | B15: 45884 | C15: Employer Payroll Inc | D15: =IFERROR(INDEX(Dim_Source[SourceID],MATCH($C15,Dim_Source[SourceName],0)),"") | E15: Payroll | F15: =IFERROR(INDEX(Dim_Category[CategoryID],MATCH($E15,Dim_Category[CategoryName],0)),"") | G15: Checking | H15: =IFERROR(INDEX(Dim_Account[AccountID],MATCH($G15,Dim_Account[AccountName],0)),"") | I15: 5100 | J15: 1224 | K15: =$I15-$J15 | L15: Yes | M15: Semi-monthly payroll
A16: =ROW()-11 | B16: 45901 | C16: Employer Payroll Inc | D16: =IFERROR(INDEX(Dim_Source[SourceID],MATCH($C16,Dim_Source[SourceName],0)),"") | E16: Payroll | F16: =IFERROR(INDEX(Dim_Category[CategoryID],MATCH($E16,Dim_Category[CategoryName],0)),"") | G16: Checking | H16: =IFERROR(INDEX(Dim_Account[AccountID],MATCH($G16,Dim_Account[AccountName],0)),"") | I16: 5100 | J16: 1224 | K16: =$I16-$J16 | L16: Yes | M16: Semi-monthly payroll
A17: =ROW()-11 | B17: 45915 | C17: Employer Payroll Inc | D17: =IFERROR(INDEX(Dim_Source[SourceID],MATCH($C17,Dim_Source[SourceName],0)),"") | E17: Payroll | F17: =IFERROR(INDEX(Dim_Category[CategoryID],MATCH($E17,Dim_Category[CategoryName],0)),"") | G17: Checking | H17: =IFERROR(INDEX(Dim_Account[AccountID],MATCH($G17,Dim_Account[AccountName],0)),"") | I17: 5100 | J17: 1224 | K17: =$I17-$J17 | L17: Yes | M17: Semi-monthly payroll
A18: =ROW()-11 | B18: 45931 | C18: Employer Payroll Inc | D18: =IFERROR(INDEX(Dim_Source[SourceID],MATCH($C18,Dim_Source[SourceName],0)),"") | E18: Payroll | F18: =IFERROR(INDEX(Dim_Category[CategoryID],MATCH($E18,Dim_Category[CategoryName],0)),"") | G18: Checking | H18: =IFERROR(INDEX(Dim_Account[AccountID],MATCH($G18,Dim_Account[AccountName],0)),"") | I18: 5100 | J18: 1224 | K18: =$I18-$J18 | L18: Yes | M18: Semi-monthly payroll
A19: =ROW()-11 | B19: 45945 | C19: Employer Payroll Inc | D19: =IFERROR(INDEX(Dim_Source[SourceID],MATCH($C19,Dim_Source[SourceName],0)),"") | E19: Payroll | F19: =IFERROR(INDEX(Dim_Category[CategoryID],MATCH($E19,Dim_Category[CategoryName],0)),"") | G19: Checking | H19: =IFERROR(INDEX(Dim_Account[AccountID],MATCH($G19,Dim_Account[AccountName],0)),"") | I19: 5100 | J19: 1224 | K19: =$I19-$J19 | L19: Yes | M19: Semi-monthly payroll
A20: =ROW()-11 | B20: 45962 | C20: Employer Payroll Inc | D20: =IFERROR(INDEX(Dim_Source[SourceID],MATCH($C20,Dim_Source[SourceName],0)),"") | E20: Payroll | F20: =IFERROR(INDEX(Dim_Category[CategoryID],MATCH($E20,Dim_Category[CategoryName],0)),"") | G20: Checking | H20: =IFERROR(INDEX(Dim_Account[AccountID],MATCH($G20,Dim_Account[AccountName],0)),"") | I20: 5100 | J20: 1224 | K20: =$I20-$J20 | L20: Yes | M20: Semi-monthly payroll
A21: =ROW()-11 | B21: 45976 | C21: Employer Payroll Inc | D21: =IFERROR(INDEX(Dim_Source[SourceID],MATCH($C21,Dim_Source[SourceName],0)),"") | E21: Payroll | F21: =IFERROR(INDEX(Dim_Category[CategoryID],MATCH($E21,Dim_Category[CategoryName],0)),"") | G21: Checking | H21: =IFERROR(INDEX(Dim_Account[AccountID],MATCH($G21,Dim_Account[AccountName],0)),"") | I21: 5100 | J21: 1224 | K21: =$I21-$J21 | L21: Yes | M21: Semi-monthly payroll
A22: =ROW()-11 | B22: 45992 | C22: Employer Payroll Inc | D22: =IFERROR(INDEX(Dim_Source[SourceID],MATCH($C22,Dim_Source[SourceName],0)),"") | E22: Payroll | F22: =IFERROR(INDEX(Dim_Category[CategoryID],MATCH($E22,Dim_Category[CategoryName],0)),"") | G22: Checking | H22: =IFERROR(INDEX(Dim_Account[AccountID],MATCH($G22,Dim_Account[AccountName],0)),"") | I22: 5100 | J22: 1224 | K22: =$I22-$J22 | L22: Yes | M22: Semi-monthly payroll
A23: =ROW()-11 | B23: 46006 | C23: Employer Payroll Inc | D23: =IFERROR(INDEX(Dim_Source[SourceID],MATCH($C23,Dim_Source[SourceName],0)),"") | E23: Payroll | F23: =IFERROR(INDEX(Dim_Category[CategoryID],MATCH($E23,Dim_Category[CategoryName],0)),"") | G23: Checking | H23: =IFERROR(INDEX(Dim_Account[AccountID],MATCH($G23,Dim_Account[AccountName],0)),"") | I23: 5100 | J23: 1224 | K23: =$I23-$J23 | L23: Yes | M23: Semi-monthly payroll
... A37: =ROW()-11 | B37: 46218 | C37: Employer Payroll Inc | D37: =IFERROR(INDEX(Dim_Source[SourceID],MATCH($C37,Dim_Source[SourceName],0)),"") | E37: Payroll | F37: =IFERROR(INDEX(Dim_Category[CategoryID],MATCH($E37,Dim_Category[CategoryName],0)),"") | G37: Checking | H37: =IFERROR(INDEX(Dim_Account[AccountID],MATCH($G37,Dim_Account[AccountName],0)),"") | I37: 5100 | J37: 1224 | K37: =$I37-$J37 | L37: Yes | M37: Semi-monthly payroll

Sheet Expenses
A1: Expenses
A4: Fact_Expenses — every purchase goes here. Pick Vendor/Category/Account/Payment Method from dropdowns.
A5: ExpenseID | B5: Date | C5: VendorName | D5: VendorID | E5: CategoryName | F5: CategoryID | G5: AccountName | H5: AccountID | I5: PaymentMethod | J5: PaymentMethodID | K5: Amount | L5: NeedWantFlag | M5: RecurringFlag | N5: Notes | O5: Description | P5: CurMonthAmt
A6: =ROW()-5 | B6: 45872 | C6: Mortgage Lender | D6: =IFERROR(INDEX(Dim_Vendor[VendorID],MATCH($C6,Dim_Vendor[VendorName],0)),"") | E6: Mortgage | F6: =IFERROR(INDEX(Dim_Category[CategoryID],MATCH($E6,Dim_Category[CategoryName],0)),"") | G6: Checking | H6: =IFERROR(INDEX(Dim_Account[AccountID],MATCH($G6,Dim_Account[AccountName],0)),"") | I6: ACH | J6: =IFERROR(INDEX(Dim_PaymentMethod[PaymentMethodID],MATCH($I6,Dim_PaymentMethod[MethodName],0)),"") | K6: 2197.96 | L6: Need | M6: Yes | N6: Monthly mortgage payment | P6: =IF(AND($B6>=CurMonthStart,$B6<=CurMonthEnd),$K6,0)
A7: =ROW()-5 | B7: 45875 | C7: Whole Foods | D7: =IFERROR(INDEX(Dim_Vendor[VendorID],MATCH($C7,Dim_Vendor[VendorName],0)),"") | E7: Groceries | F7: =IFERROR(INDEX(Dim_Category[CategoryID],MATCH($E7,Dim_Category[CategoryName],0)),"") | G7: Credit Card | H7: =IFERROR(INDEX(Dim_Account[AccountID],MATCH($G7,Dim_Account[AccountName],0)),"") | I7: Credit Card | J7: =IFERROR(INDEX(Dim_PaymentMethod[PaymentMethodID],MATCH($I7,Dim_PaymentMethod[MethodName],0)),"") | K7: 172.25 | L7: Need | M7: No | P7: =IF(AND($B7>=CurMonthStart,$B7<=CurMonthEnd),$K7,0)
A8: =ROW()-5 | B8: 45878 | C8: Costco | D8: =IFERROR(INDEX(Dim_Vendor[VendorID],MATCH($C8,Dim_Vendor[VendorName],0)),"") | E8: Groceries | F8: =IFERROR(INDEX(Dim_Category[CategoryID],MATCH($E8,Dim_Category[CategoryName],0)),"") | G8: Credit Card | H8: =IFERROR(INDEX(Dim_Account[AccountID],MATCH($G8,Dim_Account[AccountName],0)),"") | I8: Credit Card | J8: =IFERROR(INDEX(Dim_PaymentMethod[PaymentMethodID],MATCH($I8,Dim_PaymentMethod[MethodName],0)),"") | K8: 236.28 | L8: Need | M8: No | N8: Bulk groceries | P8: =IF(AND($B8>=CurMonthStart,$B8<=CurMonthEnd),$K8,0)
A9: =ROW()-5 | B9: 45881 | C9: Shell Gas Station | D9: =IFERROR(INDEX(Dim_Vendor[VendorID],MATCH($C9,Dim_Vendor[VendorName],0)),"") | E9: Car | F9: =IFERROR(INDEX(Dim_Category[CategoryID],MATCH($E9,Dim_Category[CategoryName],0)),"") | G9: Credit Card | H9: =IFERROR(INDEX(Dim_Account[AccountID],MATCH($G9,Dim_Account[AccountName],0)),"") | I9: Credit Card | J9: =IFERROR(INDEX(Dim_PaymentMethod[PaymentMethodID],MATCH($I9,Dim_PaymentMethod[MethodName],0)),"") | K9: 49.98 | L9: Need | M9: No | N9: Gas | P9: =IF(AND($B9>=CurMonthStart,$B9<=CurMonthEnd),$K9,0)
A10: =ROW()-5 | B10: 45884 | C10: AutoZone | D10: =IFERROR(INDEX(Dim_Vendor[VendorID],MATCH($C10,Dim_Vendor[VendorName],0)),"") | E10: Car | F10: =IFERROR(INDEX(Dim_Category[CategoryID],MATCH($E10,Dim_Category[CategoryName],0)),"") | G10: Credit Card | H10: =IFERROR(INDEX(Dim_Account[AccountID],MATCH($G10,Dim_Account[AccountName],0)),"") | I10: Credit Card | J10: =IFERROR(INDEX(Dim_PaymentMethod[PaymentMethodID],MATCH($I10,Dim_PaymentMethod[MethodName],0)),"") | K10: 40.22 | L10: Need | M10: No | N10: Wiper blades / oil | P10: =IF(AND($B10>=CurMonthStart,$B10<=CurMonthEnd),$K10,0)
A11: =ROW()-5 | B11: 45887 | C11: City Electric Co | D11: =IFERROR(INDEX(Dim_Vendor[VendorID],MATCH($C11,Dim_Vendor[VendorName],0)),"") | E11: Utilities | F11: =IFERROR(INDEX(Dim_Category[CategoryID],MATCH($E11,Dim_Category[CategoryName],0)),"") | G11: Checking | H11: =IFERROR(INDEX(Dim_Account[AccountID],MATCH($G11,Dim_Account[AccountName],0)),"") | I11: ACH | J11: =IFERROR(INDEX(Dim_PaymentMethod[PaymentMethodID],MATCH($I11,Dim_PaymentMethod[MethodName],0)),"") | K11: 132.24 | L11: Need | M11: Yes | P11: =IF(AND($B11>=CurMonthStart,$B11<=CurMonthEnd),$K11,0)
A12: =ROW()-5 | B12: 45890 | C12: Comcast Xfinity | D12: =IFERROR(INDEX(Dim_Vendor[VendorID],MATCH($C12,Dim_Vendor[VendorName],0)),"") | E12: Utilities | F12: =IFERROR(INDEX(Dim_Category[CategoryID],MATCH($E12,Dim_Category[CategoryName],0)),"") | G12: Checking | H12: =IFERROR(INDEX(Dim_Account[AccountID],MATCH($G12,Dim_Account[AccountName],0)),"") | I12: ACH | J12: =IFERROR(INDEX(Dim_PaymentMethod[PaymentMethodID],MATCH($I12,Dim_PaymentMethod[MethodName],0)),"") | K12: 85.01 | L12: Need | M12: Yes | N12: Internet | P12: =IF(AND($B12>=CurMonthStart,$B12<=CurMonthEnd),$K12,0)
A13: =ROW()-5 | B13: 45893 | C13: Verizon Wireless | D13: =IFERROR(INDEX(Dim_Vendor[VendorID],MATCH($C13,Dim_Vendor[VendorName],0)),"") | E13: Utilities | F13: =IFERROR(INDEX(Dim_Category[CategoryID],MATCH($E13,Dim_Category[CategoryName],0)),"") | G13: Checking | H13: =IFERROR(INDEX(Dim_Account[AccountID],MATCH($G13,Dim_Account[AccountName],0)),"") | I13: ACH | J13: =IFERROR(INDEX(Dim_PaymentMethod[PaymentMethodID],MATCH($I13,Dim_PaymentMethod[MethodName],0)),"") | K13: 88.72 | L13: Need | M13: Yes | N13: Mobile phone | P13: =IF(AND($B13>=CurMonthStart,$B13<=CurMonthEnd),$K13,0)
A14: =ROW()-5 | B14: 45896 | C14: State Farm Insurance | D14: =IFERROR(INDEX(Dim_Vendor[VendorID],MATCH($C14,Dim_Vendor[VendorName],0)),"") | E14: Insurance | F14: =IFERROR(INDEX(Dim_Category[CategoryID],MATCH($E14,Dim_Category[CategoryName],0)),"") | G14: Checking | H14: =IFERROR(INDEX(Dim_Account[AccountID],MATCH($G14,Dim_Account[AccountName],0)),"") | I14: ACH | J14: =IFERROR(INDEX(Dim_PaymentMethod[PaymentMethodID],MATCH($I14,Dim_PaymentMethod[MethodName],0)),"") | K14: 140.23 | L14: Need | M14: Yes | N14: Auto + home insurance | P14: =IF(AND($B14>=CurMonthStart,$B14<=CurMonthEnd),$K14,0)
A15: =ROW()-5 | B15: 45872 | C15: Kaiser Permanente | D15: =IFERROR(INDEX(Dim_Vendor[VendorID],MATCH($C15,Dim_Vendor[VendorName],0)),"") | E15: Healthcare | F15: =IFERROR(INDEX(Dim_Category[CategoryID],MATCH($E15,Dim_Category[CategoryName],0)),"") | G15: Credit Card | H15: =IFERROR(INDEX(Dim_Account[AccountID],MATCH($G15,Dim_Account[AccountName],0)),"") | I15: Credit Card | J15: =IFERROR(INDEX(Dim_PaymentMethod[PaymentMethodID],MATCH($I15,Dim_PaymentMethod[MethodName],0)),"") | K15: 41.61 | L15: Need | M15: No | N15: Copay | P15: =IF(AND($B15>=CurMonthStart,$B15<=CurMonthEnd),$K15,0)
A16: =ROW()-5 | B16: 45875 | C16: Chipotle | D16: =IFERROR(INDEX(Dim_Vendor[VendorID],MATCH($C16,Dim_Vendor[VendorName],0)),"") | E16: Dining & Entertainment | F16: =IFERROR(INDEX(Dim_Category[CategoryID],MATCH($E16,Dim_Category[CategoryName],0)),"") | G16: Credit Card | H16: =IFERROR(INDEX(Dim_Account[AccountID],MATCH($G16,Dim_Account[AccountName],0)),"") | I16: Credit Card | J16: =IFERROR(INDEX(Dim_PaymentMethod[PaymentMethodID],MATCH($I16,Dim_PaymentMethod[MethodName],0)),"") | K16: 14.25 | L16: Want | M16: No | P16: =IF(AND($B16>=CurMonthStart,$B16<=CurMonthEnd),$K16,0)
A17: =ROW()-5 | B17: 45878 | C17: Netflix | D17: =IFERROR(INDEX(Dim_Vendor[VendorID],MATCH($C17,Dim_Vendor[VendorName],0)),"") | E17: Dining & Entertainment | F17: =IFERROR(INDEX(Dim_Category[CategoryID],MATCH($E17,Dim_Category[CategoryName],0)),"") | G17: Credit Card | H17: =IFERROR(INDEX(Dim_Account[AccountID],MATCH($G17,Dim_Account[AccountName],0)),"") | I17: Credit Card | J17: =IFERROR(INDEX(Dim_PaymentMethod[PaymentMethodID],MATCH($I17,Dim_PaymentMethod[MethodName],0)),"") | K17: 15.49 | L17: Want | M17: Yes | N17: Streaming subscription | P17: =IF(AND($B17>=CurMonthStart,$B17<=CurMonthEnd),$K17,0)
A18: =ROW()-5 | B18: 45881 | C18: AMC Theatres | D18: =IFERROR(INDEX(Dim_Vendor[VendorID],MATCH($C18,Dim_Vendor[VendorName],0)),"") | E18: Dining & Entertainment | F18: =IFERROR(INDEX(Dim_Category[CategoryID],MATCH($E18,Dim_Category[CategoryName],0)),"") | G18: Credit Card | H18: =IFERROR(INDEX(Dim_Account[AccountID],MATCH($G18,Dim_Account[AccountName],0)),"") | I18: Credit Card | J18: =IFERROR(INDEX(Dim_PaymentMethod[PaymentMethodID],MATCH($I18,Dim_PaymentMethod[MethodName],0)),"") | K18: 30.56 | L18: Want | M18: No | P18: =IF(AND($B18>=CurMonthStart,$B18<=CurMonthEnd),$K18,0)
A19: =ROW()-5 | B19: 45884 | C19: Planet Fitness | D19: =IFERROR(INDEX(Dim_Vendor[VendorID],MATCH($C19,Dim_Vendor[VendorName],0)),"") | E19: Personal Care | F19: =IFERROR(INDEX(Dim_Category[CategoryID],MATCH($E19,Dim_Category[CategoryName],0)),"") | G19: Checking | H19: =IFERROR(INDEX(Dim_Account[AccountID],MATCH($G19,Dim_Account[AccountName],0)),"") | I19: ACH | J19: =IFERROR(INDEX(Dim_PaymentMethod[PaymentMethodID],MATCH($I19,Dim_PaymentMethod[MethodName],0)),"") | K19: 25.01 | L19: Want | M19: Yes | N19: Gym membership | P19: =IF(AND($B19>=CurMonthStart,$B19<=CurMonthEnd),$K19,0)
A20: =ROW()-5 | B20: 45887 | C20: Amazon | D20: =IFERROR(INDEX(Dim_Vendor[VendorID],MATCH($C20,Dim_Vendor[VendorName],0)),"") | E20: Shopping | F20: =IFERROR(INDEX(Dim_Category[CategoryID],MATCH($E20,Dim_Category[CategoryName],0)),"") | G20: Credit Card | H20: =IFERROR(INDEX(Dim_Account[AccountID],MATCH($G20,Dim_Account[AccountName],0)),"") | I20: Credit Card | J20: =IFERROR(INDEX(Dim_PaymentMethod[PaymentMethodID],MATCH($I20,Dim_PaymentMethod[MethodName],0)),"") | K20: 63.28 | L20: Want | M20: No | P20: =IF(AND($B20>=CurMonthStart,$B20<=CurMonthEnd),$K20,0)
A21: =ROW()-5 | B21: 45890 | C21: Target | D21: =IFERROR(INDEX(Dim_Vendor[VendorID],MATCH($C21,Dim_Vendor[VendorName],0)),"") | E21: Shopping | F21: =IFERROR(INDEX(Dim_Category[CategoryID],MATCH($E21,Dim_Category[CategoryName],0)),"") | G21: Credit Card | H21: =IFERROR(INDEX(Dim_Account[AccountID],MATCH($G21,Dim_Account[AccountName],0)),"") | I21: Credit Card | J21: =IFERROR(INDEX(Dim_PaymentMethod[PaymentMethodID],MATCH($I21,Dim_PaymentMethod[MethodName],0)),"") | K21: 51.7 | L21: Want | M21: No | P21: =IF(AND($B21>=CurMonthStart,$B21<=CurMonthEnd),$K21,0)
A22: =ROW()-5 | B22: 45903 | C22: Mortgage Lender | D22: =IFERROR(INDEX(Dim_Vendor[VendorID],MATCH($C22,Dim_Vendor[VendorName],0)),"") | E22: Mortgage | F22: =IFERROR(INDEX(Dim_Category[CategoryID],MATCH($E22,Dim_Category[CategoryName],0)),"") | G22: Checking | H22: =IFERROR(INDEX(Dim_Account[AccountID],MATCH($G22,Dim_Account[AccountName],0)),"") | I22: ACH | J22: =IFERROR(INDEX(Dim_PaymentMethod[PaymentMethodID],MATCH($I22,Dim_PaymentMethod[MethodName],0)),"") | K22: 2201.56 | L22: Need | M22: Yes | N22: Monthly mortgage payment | P22: =IF(AND($B22>=CurMonthStart,$B22<=CurMonthEnd),$K22,0)
A23: =ROW()-5 | B23: 45906 | C23: Whole Foods | D23: =IFERROR(INDEX(Dim_Vendor[VendorID],MATCH($C23,Dim_Vendor[VendorName],0)),"") | E23: Groceries | F23: =IFERROR(INDEX(Dim_Category[CategoryID],MATCH($E23,Dim_Category[CategoryName],0)),"") | G23: Credit Card | H23: =IFERROR(INDEX(Dim_Account[AccountID],MATCH($G23,Dim_Account[AccountName],0)),"") | I23: Credit Card | J23: =IFERROR(INDEX(Dim_PaymentMethod[PaymentMethodID],MATCH($I23,Dim_PaymentMethod[MethodName],0)),"") | K23: 187.76 | L23: Need | M23: No | P23: =IF(AND($B23>=CurMonthStart,$B23<=CurMonthEnd),$K23,0)
A24: =ROW()-5 | B24: 45909 | C24: Costco | D24: =IFERROR(INDEX(Dim_Vendor[VendorID],MATCH($C24,Dim_Vendor[VendorName],0)),"") | E24: Groceries | F24: =IFERROR(INDEX(Dim_Category[CategoryID],MATCH($E24,Dim_Category[CategoryName],0)),"") | G24: Credit Card | H24: =IFERROR(INDEX(Dim_Account[AccountID],MATCH($G24,Dim_Account[AccountName],0)),"") | I24: Credit Card | J24: =IFERROR(INDEX(Dim_PaymentMethod[PaymentMethodID],MATCH($I24,Dim_PaymentMethod[MethodName],0)),"") | K24: 234.14 | L24: Need | M24: No | N24: Bulk groceries | P24: =IF(AND($B24>=CurMonthStart,$B24<=CurMonthEnd),$K24,0)
A25: =ROW()-5 | B25: 45912 | C25: Shell Gas Station | D25: =IFERROR(INDEX(Dim_Vendor[VendorID],MATCH($C25,Dim_Vendor[VendorName],0)),"") | E25: Car | F25: =IFERROR(INDEX(Dim_Category[CategoryID],MATCH($E25,Dim_Category[CategoryName],0)),"") | G25: Credit Card | H25: =IFERROR(INDEX(Dim_Account[AccountID],MATCH($G25,Dim_Account[AccountName],0)),"") | I25: Credit Card | J25: =IFERROR(INDEX(Dim_PaymentMethod[PaymentMethodID],MATCH($I25,Dim_PaymentMethod[MethodName],0)),"") | K25: 53.05 | L25: Need | M25: No | N25: Gas | P25: =IF(AND($B25>=CurMonthStart,$B25<=CurMonthEnd),$K25,0)
A26: =ROW()-5 | B26: 45915 | C26: AutoZone | D26: =IFERROR(INDEX(Dim_Vendor[VendorID],MATCH($C26,Dim_Vendor[VendorName],0)),"") | E26: Car | F26: =IFERROR(INDEX(Dim_Category[CategoryID],MATCH($E26,Dim_Category[CategoryName],0)),"") | G26: Credit Card | H26: =IFERROR(INDEX(Dim_Account[AccountID],MATCH($G26,Dim_Account[AccountName],0)),"") | I26: Credit Card | J26: =IFERROR(INDEX(Dim_PaymentMethod[PaymentMethodID],MATCH($I26,Dim_PaymentMethod[MethodName],0)),"") | K26: 40.67 | L26: Need | M26: No | N26: Wiper blades / oil | P26: =IF(AND($B26>=CurMonthStart,$B26<=CurMonthEnd),$K26,0)
A27: =ROW()-5 | B27: 45918 | C27: City Electric Co | D27: =IFERROR(INDEX(Dim_Vendor[VendorID],MATCH($C27,Dim_Vendor[VendorName],0)),"") | E27: Utilities | F27: =IFERROR(INDEX(Dim_Category[CategoryID],MATCH($E27,Dim_Category[CategoryName],0)),"") | G27: Checking | H27: =IFERROR(INDEX(Dim_Account[AccountID],MATCH($G27,Dim_Account[AccountName],0)),"") | I27: ACH | J27: =IFERROR(INDEX(Dim_PaymentMethod[PaymentMethodID],MATCH($I27,Dim_PaymentMethod[MethodName],0)),"") | K27: 118.45 | L27: Need | M27: Yes | P27: =IF(AND($B27>=CurMonthStart,$B27<=CurMonthEnd),$K27,0)
A28: =ROW()-5 | B28: 45921 | C28: Comcast Xfinity | D28: =IFERROR(INDEX(Dim_Vendor[VendorID],MATCH($C28,Dim_Vendor[VendorName],0)),"") | E28: Utilities | F28: =IFERROR(INDEX(Dim_Category[CategoryID],MATCH($E28,Dim_Category[CategoryName],0)),"") | G28: Checking | H28: =IFERROR(INDEX(Dim_Account[AccountID],MATCH($G28,Dim_Account[AccountName],0)),"") | I28: ACH | J28: =IFERROR(INDEX(Dim_PaymentMethod[PaymentMethodID],MATCH($I28,Dim_PaymentMethod[MethodName],0)),"") | K28: 83.9 | L28: Need | M28: Yes | N28: Internet | P28: =IF(AND($B28>=CurMonthStart,$B28<=CurMonthEnd),$K28,0)
A29: =ROW()-5 | B29: 45924 | C29: Verizon Wireless | D29: =IFERROR(INDEX(Dim_Vendor[VendorID],MATCH($C29,Dim_Vendor[VendorName],0)),"") | E29: Utilities | F29: =IFERROR(INDEX(Dim_Category[CategoryID],MATCH($E29,Dim_Category[CategoryName],0)),"") | G29: Checking | H29: =IFERROR(INDEX(Dim_Account[AccountID],MATCH($G29,Dim_Account[AccountName],0)),"") | I29: ACH | J29: =IFERROR(INDEX(Dim_PaymentMethod[PaymentMethodID],MATCH($I29,Dim_PaymentMethod[MethodName],0)),"") | K29: 98.01 | L29: Need | M29: Yes | N29: Mobile phone | P29: =IF(AND($B29>=CurMonthStart,$B29<=CurMonthEnd),$K29,0)
A30: =ROW()-5 | B30: 45927 | C30: State Farm Insurance | D30: =IFERROR(INDEX(Dim_Vendor[VendorID],MATCH($C30,Dim_Vendor[VendorName],0)),"") | E30: Insurance | F30: =IFERROR(INDEX(Dim_Category[CategoryID],MATCH($E30,Dim_Category[CategoryName],0)),"") | G30: Checking | H30: =IFERROR(INDEX(Dim_Account[AccountID],MATCH($G30,Dim_Account[AccountName],0)),"") | I30: ACH | J30: =IFERROR(INDEX(Dim_PaymentMethod[PaymentMethodID],MATCH($I30,Dim_PaymentMethod[MethodName],0)),"") | K30: 138.37 | L30: Need | M30: Yes | N30: Auto + home insurance | P30: =IF(AND($B30>=CurMonthStart,$B30<=CurMonthEnd),$K30,0)
A31: =ROW()-5 | B31: 45903 | C31: Kaiser Permanente | D31: =IFERROR(INDEX(Dim_Vendor[VendorID],MATCH($C31,Dim_Vendor[VendorName],0)),"") | E31: Healthcare | F31: =IFERROR(INDEX(Dim_Category[CategoryID],MATCH($E31,Dim_Category[CategoryName],0)),"") | G31: Credit Card | H31: =IFERROR(INDEX(Dim_Account[AccountID],MATCH($G31,Dim_Account[AccountName],0)),"") | I31: Credit Card | J31: =IFERROR(INDEX(Dim_PaymentMethod[PaymentMethodID],MATCH($I31,Dim_PaymentMethod[MethodName],0)),"") | K31: 42.52 | L31: Need | M31: No | N31: Copay | P31: =IF(AND($B31>=CurMonthStart,$B31<=CurMonthEnd),$K31,0)
A32: =ROW()-5 | B32: 45906 | C32: Chipotle | D32: =IFERROR(INDEX(Dim_Vendor[VendorID],MATCH($C32,Dim_Vendor[VendorName],0)),"") | E32: Dining & Entertainment | F32: =IFERROR(INDEX(Dim_Category[CategoryID],MATCH($E32,Dim_Category[CategoryName],0)),"") | G32: Credit Card | H32: =IFERROR(INDEX(Dim_Account[AccountID],MATCH($G32,Dim_Account[AccountName],0)),"") | I32: Credit Card | J32: =IFERROR(INDEX(Dim_PaymentMethod[PaymentMethodID],MATCH($I32,Dim_PaymentMethod[MethodName],0)),"") | K32: 14.25 | L32: Want | M32: No | P32: =IF(AND($B32>=CurMonthStart,$B32<=CurMonthEnd),$K32,0)
A33: =ROW()-5 | B33: 45909 | C33: Netflix | D33: =IFERROR(INDEX(Dim_Vendor[VendorID],MATCH($C33,Dim_Vendor[VendorName],0)),"") | E33: Dining & Entertainment | F33: =IFERROR(INDEX(Dim_Category[CategoryID],MATCH($E33,Dim_Category[CategoryName],0)),"") | G33: Credit Card | H33: =IFERROR(INDEX(Dim_Account[AccountID],MATCH($G33,Dim_Account[AccountName],0)),"") | I33: Credit Card | J33: =IFERROR(INDEX(Dim_PaymentMethod[PaymentMethodID],MATCH($I33,Dim_PaymentMethod[MethodName],0)),"") | K33: 15.49 | L33: Want | M33: Yes | N33: Streaming subscription | P33: =IF(AND($B33>=CurMonthStart,$B33<=CurMonthEnd),$K33,0)
A34: =ROW()-5 | B34: 45912 | C34: AMC Theatres | D34: =IFERROR(INDEX(Dim_Vendor[VendorID],MATCH($C34,Dim_Vendor[VendorName],0)),"") | E34: Dining & Entertainment | F34: =IFERROR(INDEX(Dim_Category[CategoryID],MATCH($E34,Dim_Category[CategoryName],0)),"") | G34: Credit Card | H34: =IFERROR(INDEX(Dim_Account[AccountID],MATCH($G34,Dim_Account[AccountName],0)),"") | I34: Credit Card | J34: =IFERROR(INDEX(Dim_PaymentMethod[PaymentMethodID],MATCH($I34,Dim_PaymentMethod[MethodName],0)),"") | K34: 34.34 | L34: Want | M34: No | P34: =IF(AND($B34>=CurMonthStart,$B34<=CurMonthEnd),$K34,0)
A35: =ROW()-5 | B35: 45915 | C35: Planet Fitness | D35: =IFERROR(INDEX(Dim_Vendor[VendorID],MATCH($C35,Dim_Vendor[VendorName],0)),"") | E35: Personal Care | F35: =IFERROR(INDEX(Dim_Category[CategoryID],MATCH($E35,Dim_Category[CategoryName],0)),"") | G35: Checking | H35: =IFERROR(INDEX(Dim_Account[AccountID],MATCH($G35,Dim_Account[AccountName],0)),"") | I35: ACH | J35: =IFERROR(INDEX(Dim_PaymentMethod[PaymentMethodID],MATCH($I35,Dim_PaymentMethod[MethodName],0)),"") | K35: 24.34 | L35: Want | M35: Yes | N35: Gym membership | P35: =IF(AND($B35>=CurMonthStart,$B35<=CurMonthEnd),$K35,0)
A36: =ROW()-5 | B36: 45918 | C36: Amazon | D36: =IFERROR(INDEX(Dim_Vendor[VendorID],MATCH($C36,Dim_Vendor[VendorName],0)),"") | E36: Shopping | F36: =IFERROR(INDEX(Dim_Category[CategoryID],MATCH($E36,Dim_Category[CategoryName],0)),"") | G36: Credit Card | H36: =IFERROR(INDEX(Dim_Account[AccountID],MATCH($G36,Dim_Account[AccountName],0)),"") | I36: Credit Card | J36: =IFERROR(INDEX(Dim_PaymentMethod[PaymentMethodID],MATCH($I36,Dim_PaymentMethod[MethodName],0)),"") | K36: 64.01 | L36: Want | M36: No | P36: =IF(AND($B36>=CurMonthStart,$B36<=CurMonthEnd),$K36,0)
A37: =ROW()-5 | B37: 45921 | C37: Target | D37: =IFERROR(INDEX(Dim_Vendor[VendorID],MATCH($C37,Dim_Vendor[VendorName],0)),"") | E37: Shopping | F37: =IFERROR(INDEX(Dim_Category[CategoryID],MATCH($E37,Dim_Category[CategoryName],0)),"") | G37: Credit Card | H37: =IFERROR(INDEX(Dim_Account[AccountID],MATCH($G37,Dim_Account[AccountName],0)),"") | I37: Credit Card | J37: =IFERROR(INDEX(Dim_PaymentMethod[PaymentMethodID],MATCH($I37,Dim_PaymentMethod[MethodName],0)),"") | K37: 50.81 | L37: Want | M37: No | P37: =IF(AND($B37>=CurMonthStart,$B37<=CurMonthEnd),$K37,0)
A38: =ROW()-5 | B38: 45933 | C38: Mortgage Lender | D38: =IFERROR(INDEX(Dim_Vendor[VendorID],MATCH($C38,Dim_Vendor[VendorName],0)),"") | E38: Mortgage | F38: =IFERROR(INDEX(Dim_Category[CategoryID],MATCH($E38,Dim_Category[CategoryName],0)),"") | G38: Checking | H38: =IFERROR(INDEX(Dim_Account[AccountID],MATCH($G38,Dim_Account[AccountName],0)),"") | I38: ACH | J38: =IFERROR(INDEX(Dim_PaymentMethod[PaymentMethodID],MATCH($I38,Dim_PaymentMethod[MethodName],0)),"") | K38: 2269.54 | L38: Need | M38: Yes | N38: Monthly mortgage payment | P38: =IF(AND($B38>=CurMonthStart,$B38<=CurMonthEnd),$K38,0)
A39: =ROW()-5 | B39: 45936 | C39: Whole Foods | D39: =IFERROR(INDEX(Dim_Vendor[VendorID],MATCH($C39,Dim_Vendor[VendorName],0)),"") | E39: Groceries | F39: =IFERROR(INDEX(Dim_Category[CategoryID],MATCH($E39,Dim_Category[CategoryName],0)),"") | G39: Credit Card | H39: =IFERROR(INDEX(Dim_Account[AccountID],MATCH($G39,Dim_Account[AccountName],0)),"") | I39: Credit Card | J39: =IFERROR(INDEX(Dim_PaymentMethod[PaymentMethodID],MATCH($I39,Dim_PaymentMethod[MethodName],0)),"") | K39: 189.51 | L39: Need | M39: No | P39: =IF(AND($B39>=CurMonthStart,$B39<=CurMonthEnd),$K39,0)
A40: =ROW()-5 | B40: 45939 | C40: Costco | D40: =IFERROR(INDEX(Dim_Vendor[VendorID],MATCH($C40,Dim_Vendor[VendorName],0)),"") | E40: Groceries | F40: =IFERROR(INDEX(Dim_Category[CategoryID],MATCH($E40,Dim_Category[CategoryName],0)),"") | G40: Credit Card | H40: =IFERROR(INDEX(Dim_Account[AccountID],MATCH($G40,Dim_Account[AccountName],0)),"") | I40: Credit Card | J40: =IFERROR(INDEX(Dim_PaymentMethod[PaymentMethodID],MATCH($I40,Dim_PaymentMethod[MethodName],0)),"") | K40: 257.14 | L40: Need | M40: No | N40: Bulk groceries | P40: =IF(AND($B40>=CurMonthStart,$B40<=CurMonthEnd),$K40,0)
A41: =ROW()-5 | B41: 45942 | C41: Shell Gas Station | D41: =IFERROR(INDEX(Dim_Vendor[VendorID],MATCH($C41,Dim_Vendor[VendorName],0)),"") | E41: Car | F41: =IFERROR(INDEX(Dim_Category[CategoryID],MATCH($E41,Dim_Category[CategoryName],0)),"") | G41: Credit Card | H41: =IFERROR(INDEX(Dim_Account[AccountID],MATCH($G41,Dim_Account[AccountName],0)),"") | I41: Credit Card | J41: =IFERROR(INDEX(Dim_PaymentMethod[PaymentMethodID],MATCH($I41,Dim_PaymentMethod[MethodName],0)),"") | K41: 54.22 | L41: Need | M41: No | N41: Gas | P41: =IF(AND($B41>=CurMonthStart,$B41<=CurMonthEnd),$K41,0)
A42: =ROW()-5 | B42: 45945 | C42: AutoZone | D42: =IFERROR(INDEX(Dim_Vendor[VendorID],MATCH($C42,Dim_Vendor[VendorName],0)),"") | E42: Car | F42: =IFERROR(INDEX(Dim_Category[CategoryID],MATCH($E42,Dim_Category[CategoryName],0)),"") | G42: Credit Card | H42: =IFERROR(INDEX(Dim_Account[AccountID],MATCH($G42,Dim_Account[AccountName],0)),"") | I42: Credit Card | J42: =IFERROR(INDEX(Dim_PaymentMethod[PaymentMethodID],MATCH($I42,Dim_PaymentMethod[MethodName],0)),"") | K42: 38.97 | L42: Need | M42: No | N42: Wiper blades / oil | P42: =IF(AND($B42>=CurMonthStart,$B42<=CurMonthEnd),$K42,0)
A43: =ROW()-5 | B43: 45948 | C43: City Electric Co | D43: =IFERROR(INDEX(Dim_Vendor[VendorID],MATCH($C43,Dim_Vendor[VendorName],0)),"") | E43: Utilities | F43: =IFERROR(INDEX(Dim_Category[CategoryID],MATCH($E43,Dim_Category[CategoryName],0)),"") | G43: Checking | H43: =IFERROR(INDEX(Dim_Account[AccountID],MATCH($G43,Dim_Account[AccountName],0)),"") | I43: ACH | J43: =IFERROR(INDEX(Dim_PaymentMethod[PaymentMethodID],MATCH($I43,Dim_PaymentMethod[MethodName],0)),"") | K43: 138.33 | L43: Need | M43: Yes | P43: =IF(AND($B43>=CurMonthStart,$B43<=CurMonthEnd),$K43,0)
A44: =ROW()-5 | B44: 45951 | C44: Comcast Xfinity | D44: =IFERROR(INDEX(Dim_Vendor[VendorID],MATCH($C44,Dim_Vendor[VendorName],0)),"") | E44: Utilities | F44: =IFERROR(INDEX(Dim_Category[CategoryID],MATCH($E44,Dim_Category[CategoryName],0)),"") | G44: Checking | H44: =IFERROR(INDEX(Dim_Account[AccountID],MATCH($G44,Dim_Account[AccountName],0)),"") | I44: ACH | J44: =IFERROR(INDEX(Dim_PaymentMethod[PaymentMethodID],MATCH($I44,Dim_PaymentMethod[MethodName],0)),"") | K44: 78.44 | L44: Need | M44: Yes | N44: Internet | P44: =IF(AND($B44>=CurMonthStart,$B44<=CurMonthEnd),$K44,0)
A45: =ROW()-5 | B45: 45954 | C45: Verizon Wireless | D45: =IFERROR(INDEX(Dim_Vendor[VendorID],MATCH($C45,Dim_Vendor[VendorName],0)),"") | E45: Utilities | F45: =IFERROR(INDEX(Dim_Category[CategoryID],MATCH($E45,Dim_Category[CategoryName],0)),"") | G45: Checking | H45: =IFERROR(INDEX(Dim_Account[AccountID],MATCH($G45,Dim_Account[AccountName],0)),"") | I45: ACH | J45: =IFERROR(INDEX(Dim_PaymentMethod[PaymentMethodID],MATCH($I45,Dim_PaymentMethod[MethodName],0)),"") | K45: 95.79 | L45: Need | M45: Yes | N45: Mobile phone | P45: =IF(AND($B45>=CurMonthStart,$B45<=CurMonthEnd),$K45,0)
A46: =ROW()-5 | B46: 45957 | C46: State Farm Insurance | D46: =IFERROR(INDEX(Dim_Vendor[VendorID],MATCH($C46,Dim_Vendor[VendorName],0)),"") | E46: Insurance | F46: =IFERROR(INDEX(Dim_Category[CategoryID],MATCH($E46,Dim_Category[CategoryName],0)),"") | G46: Checking | H46: =IFERROR(INDEX(Dim_Account[AccountID],MATCH($G46,Dim_Account[AccountName],0)),"") | I46: ACH | J46: =IFERROR(INDEX(Dim_PaymentMethod[PaymentMethodID],MATCH($I46,Dim_PaymentMethod[MethodName],0)),"") | K46: 149.48 | L46: Need | M46: Yes | N46: Auto + home insurance | P46: =IF(AND($B46>=CurMonthStart,$B46<=CurMonthEnd),$K46,0)
A47: =ROW()-5 | B47: 45933 | C47: Kaiser Permanente | D47: =IFERROR(INDEX(Dim_Vendor[VendorID],MATCH($C47,Dim_Vendor[VendorName],0)),"") | E47: Healthcare | F47: =IFERROR(INDEX(Dim_Category[CategoryID],MATCH($E47,Dim_Category[CategoryName],0)),"") | G47: Credit Card | H47: =IFERROR(INDEX(Dim_Account[AccountID],MATCH($G47,Dim_Account[AccountName],0)),"") | I47: Credit Card | J47: =IFERROR(INDEX(Dim_PaymentMethod[PaymentMethodID],MATCH($I47,Dim_PaymentMethod[MethodName],0)),"") | K47: 45.85 | L47: Need | M47: No | N47: Copay | P47: =IF(AND($B47>=CurMonthStart,$B47<=CurMonthEnd),$K47,0)
A48: =ROW()-5 | B48: 45936 | C48: Chipotle | D48: =IFERROR(INDEX(Dim_Vendor[VendorID],MATCH($C48,Dim_Vendor[VendorName],0)),"") | E48: Dining & Entertainment | F48: =IFERROR(INDEX(Dim_Category[CategoryID],MATCH($E48,Dim_Category[CategoryName],0)),"") | G48: Credit Card | H48: =IFERROR(INDEX(Dim_Account[AccountID],MATCH($G48,Dim_Account[AccountName],0)),"") | I48: Credit Card | J48: =IFERROR(INDEX(Dim_PaymentMethod[PaymentMethodID],MATCH($I48,Dim_PaymentMethod[MethodName],0)),"") | K48: 14.25 | L48: Want | M48: No | P48: =IF(AND($B48>=CurMonthStart,$B48<=CurMonthEnd),$K48,0)
A49: =ROW()-5 | B49: 45939 | C49: Netflix | D49: =IFERROR(INDEX(Dim_Vendor[VendorID],MATCH($C49,Dim_Vendor[VendorName],0)),"") | E49: Dining & Entertainment | F49: =IFERROR(INDEX(Dim_Category[CategoryID],MATCH($E49,Dim_Category[CategoryName],0)),"") | G49: Credit Card | H49: =IFERROR(INDEX(Dim_Account[AccountID],MATCH($G49,Dim_Account[AccountName],0)),"") | I49: Credit Card | J49: =IFERROR(INDEX(Dim_PaymentMethod[PaymentMethodID],MATCH($I49,Dim_PaymentMethod[MethodName],0)),"") | K49: 15.49 | L49: Want | M49: Yes | N49: Streaming subscription | P49: =IF(AND($B49>=CurMonthStart,$B49<=CurMonthEnd),$K49,0)
A50: =ROW()-5 | B50: 45942 | C50: AMC Theatres | D50: =IFERROR(INDEX(Dim_Vendor[VendorID],MATCH($C50,Dim_Vendor[VendorName],0)),"") | E50: Dining & Entertainment | F50: =IFERROR(INDEX(Dim_Category[CategoryID],MATCH($E50,Dim_Category[CategoryName],0)),"") | G50: Credit Card | H50: =IFERROR(INDEX(Dim_Account[AccountID],MATCH($G50,Dim_Account[AccountName],0)),"") | I50: Credit Card | J50: =IFERROR(INDEX(Dim_PaymentMethod[PaymentMethodID],MATCH($I50,Dim_PaymentMethod[MethodName],0)),"") | K50: 33.85 | L50: Want | M50: No | P50: =IF(AND($B50>=CurMonthStart,$B50<=CurMonthEnd),$K50,0)
A51: =ROW()-5 | B51: 45945 | C51: Planet Fitness | D51: =IFERROR(INDEX(Dim_Vendor[VendorID],MATCH($C51,Dim_Vendor[VendorName],0)),"") | E51: Personal Care | F51: =IFERROR(INDEX(Dim_Category[CategoryID],MATCH($E51,Dim_Category[CategoryName],0)),"") | G51: Checking | H51: =IFERROR(INDEX(Dim_Account[AccountID],MATCH($G51,Dim_Account[AccountName],0)),"") | I51: ACH | J51: =IFERROR(INDEX(Dim_PaymentMethod[PaymentMethodID],MATCH($I51,Dim_PaymentMethod[MethodName],0)),"") | K51: 25.3 | L51: Want | M51: Yes | N51: Gym membership | P51: =IF(AND($B51>=CurMonthStart,$B51<=CurMonthEnd),$K51,0)
A52: =ROW()-5 | B52: 45948 | C52: Amazon | D52: =IFERROR(INDEX(Dim_Vendor[VendorID],MATCH($C52,Dim_Vendor[VendorName],0)),"") | E52: Shopping | F52: =IFERROR(INDEX(Dim_Category[CategoryID],MATCH($E52,Dim_Category[CategoryName],0)),"") | G52: Credit Card | H52: =IFERROR(INDEX(Dim_Account[AccountID],MATCH($G52,Dim_Account[AccountName],0)),"") | I52: Credit Card | J52: =IFERROR(INDEX(Dim_PaymentMethod[PaymentMethodID],MATCH($I52,Dim_PaymentMethod[MethodName],0)),"") | K52: 70.71 | L52: Want | M52: No | P52: =IF(AND($B52>=CurMonthStart,$B52<=CurMonthEnd),$K52,0)
A53: =ROW()-5 | B53: 45951 | C53: Target | D53: =IFERROR(INDEX(Dim_Vendor[VendorID],MATCH($C53,Dim_Vendor[VendorName],0)),"") | E53: Shopping | F53: =IFERROR(INDEX(Dim_Category[CategoryID],MATCH($E53,Dim_Category[CategoryName],0)),"") | G53: Credit Card | H53: =IFERROR(INDEX(Dim_Account[AccountID],MATCH($G53,Dim_Account[AccountName],0)),"") | I53: Credit Card | J53: =IFERROR(INDEX(Dim_PaymentMethod[PaymentMethodID],MATCH($I53,Dim_PaymentMethod[MethodName],0)),"") | K53: 50.37 | L53: Want | M53: No | P53: =IF(AND($B53>=CurMonthStart,$B53<=CurMonthEnd),$K53,0)
A54: =ROW()-5 | B54: 45964 | C54: Mortgage Lender | D54: =IFERROR(INDEX(Dim_Vendor[VendorID],MATCH($C54,Dim_Vendor[VendorName],0)),"") | E54: Mortgage | F54: =IFERROR(INDEX(Dim_Category[CategoryID],MATCH($E54,Dim_Category[CategoryName],0)),"") | G54: Checking | H54: =IFERROR(INDEX(Dim_Account[AccountID],MATCH($G54,Dim_Account[AccountName],0)),"") | I54: ACH | J54: =IFERROR(INDEX(Dim_PaymentMethod[PaymentMethodID],MATCH($I54,Dim_PaymentMethod[MethodName],0)),"") | K54: 2056.4 | L54: Need | M54: Yes | N54: Monthly mortgage payment | P54: =IF(AND($B54>=CurMonthStart,$B54<=CurMonthEnd),$K54,0)
A55: =ROW()-5 | B55: 45967 | C55: Whole Foods | D55: =IFERROR(INDEX(Dim_Vendor[VendorID],MATCH($C55,Dim_Vendor[VendorName],0)),"") | E55: Groceries | F55: =IFERROR(INDEX(Dim_Category[CategoryID],MATCH($E55,Dim_Category[CategoryName],0)),"") | G55: Credit Card | H55: =IFERROR(INDEX(Dim_Account[AccountID],MATCH($G55,Dim_Account[AccountName],0)),"") | I55: Credit Card | J55: =IFERROR(INDEX(Dim_PaymentMethod[PaymentMethodID],MATCH($I55,Dim_PaymentMethod[MethodName],0)),"") | K55: 180.14 | L55: Need | M55: No | P55: =IF(AND($B55>=CurMonthStart,$B55<=CurMonthEnd),$K55,0)
A56: =ROW()-5 | B56: 45970 | C56: Costco | D56: =IFERROR(INDEX(Dim_Vendor[VendorID],MATCH($C56,Dim_Vendor[VendorName],0)),"") | E56: Groceries | F56: =IFERROR(INDEX(Dim_Category[CategoryID],MATCH($E56,Dim_Category[CategoryName],0)),"") | G56: Credit Card | H56: =IFERROR(INDEX(Dim_Account[AccountID],MATCH($G56,Dim_Account[AccountName],0)),"") | I56: Credit Card | J56: =IFERROR(INDEX(Dim_PaymentMethod[PaymentMethodID],MATCH($I56,Dim_PaymentMethod[MethodName],0)),"") | K56: 228.62 | L56: Need | M56: No | N56: Bulk groceries | P56: =IF(AND($B56>=CurMonthStart,$B56<=CurMonthEnd),$K56,0)
A57: =ROW()-5 | B57: 45973 | C57: Shell Gas Station | D57: =IFERROR(INDEX(Dim_Vendor[VendorID],MATCH($C57,Dim_Vendor[VendorName],0)),"") | E57: Car | F57: =IFERROR(INDEX(Dim_Category[CategoryID],MATCH($E57,Dim_Category[CategoryName],0)),"") | G57: Credit Card | H57: =IFERROR(INDEX(Dim_Account[AccountID],MATCH($G57,Dim_Account[AccountName],0)),"") | I57: Credit Card | J57: =IFERROR(INDEX(Dim_PaymentMethod[PaymentMethodID],MATCH($I57,Dim_PaymentMethod[MethodName],0)),"") | K57: 50.06 | L57: Need | M57: No | N57: Gas | P57: =IF(AND($B57>=CurMonthStart,$B57<=CurMonthEnd),$K57,0)
A58: =ROW()-5 | B58: 45976 | C58: AutoZone | D58: =IFERROR(INDEX(Dim_Vendor[VendorID],MATCH($C58,Dim_Vendor[VendorName],0)),"") | E58: Car | F58: =IFERROR(INDEX(Dim_Category[CategoryID],MATCH($E58,Dim_Category[CategoryName],0)),"") | G58: Credit Card | H58: =IFERROR(INDEX(Dim_Account[AccountID],MATCH($G58,Dim_Account[AccountName],0)),"") | I58: Credit Card | J58: =IFERROR(INDEX(Dim_PaymentMethod[PaymentMethodID],MATCH($I58,Dim_PaymentMethod[MethodName],0)),"") | K58: 36.28 | L58: Need | M58: No | N58: Wiper blades / oil | P58: =IF(AND($B58>=CurMonthStart,$B58<=CurMonthEnd),$K58,0)
A59: =ROW()-5 | B59: 45979 | C59: City Electric Co | D59: =IFERROR(INDEX(Dim_Vendor[VendorID],MATCH($C59,Dim_Vendor[VendorName],0)),"") | E59: Utilities | F59: =IFERROR(INDEX(Dim_Category[CategoryID],MATCH($E59,Dim_Category[CategoryName],0)),"") | G59: Checking | H59: =IFERROR(INDEX(Dim_Account[AccountID],MATCH($G59,Dim_Account[AccountName],0)),"") | I59: ACH | J59: =IFERROR(INDEX(Dim_PaymentMethod[PaymentMethodID],MATCH($I59,Dim_PaymentMethod[MethodName],0)),"") | K59: 124.03 | L59: Need | M59: Yes | P59: =IF(AND($B59>=CurMonthStart,$B59<=CurMonthEnd),$K59,0)
A60: =ROW()-5 | B60: 45982 | C60: Comcast Xfinity | D60: =IFERROR(INDEX(Dim_Vendor[VendorID],MATCH($C60,Dim_Vendor[VendorName],0)),"") | E60: Utilities | F60: =IFERROR(INDEX(Dim_Category[CategoryID],MATCH($E60,Dim_Category[CategoryName],0)),"") | G60: Checking | H60: =IFERROR(INDEX(Dim_Account[AccountID],MATCH($G60,Dim_Account[AccountName],0)),"") | I60: ACH | J60: =IFERROR(INDEX(Dim_PaymentMethod[PaymentMethodID],MATCH($I60,Dim_PaymentMethod[MethodName],0)),"") | K60: 81.73 | L60: Need | M60: Yes | N60: Internet | P60: =IF(AND($B60>=CurMonthStart,$B60<=CurMonthEnd),$K60,0)
A61: =ROW()-5 | B61: 45985 | C61: Verizon Wireless | D61: =IFERROR(INDEX(Dim_Vendor[VendorID],MATCH($C61,Dim_Vendor[VendorName],0)),"") | E61: Utilities | F61: =IFERROR(INDEX(Dim_Category[CategoryID],MATCH($E61,Dim_Category[CategoryName],0)),"") | G61: Checking | H61: =IFERROR(INDEX(Dim_Account[AccountID],MATCH($G61,Dim_Account[AccountName],0)),"") | I61: ACH | J61: =IFERROR(INDEX(Dim_PaymentMethod[PaymentMethodID],MATCH($I61,Dim_PaymentMethod[MethodName],0)),"") | K61: 92.95 | L61: Need | M61: Yes | N61: Mobile phone | P61: =IF(AND($B61>=CurMonthStart,$B61<=CurMonthEnd),$K61,0)
A62: =ROW()-5 | B62: 45988 | C62: State Farm Insurance | D62: =IFERROR(INDEX(Dim_Vendor[VendorID],MATCH($C62,Dim_Vendor[VendorName],0)),"") | E62: Insurance | F62: =IFERROR(INDEX(Dim_Category[CategoryID],MATCH($E62,Dim_Category[CategoryName],0)),"") | G62: Checking | H62: =IFERROR(INDEX(Dim_Account[AccountID],MATCH($G62,Dim_Account[AccountName],0)),"") | I62: ACH | J62: =IFERROR(INDEX(Dim_PaymentMethod[PaymentMethodID],MATCH($I62,Dim_PaymentMethod[MethodName],0)),"") | K62: 139.05 | L62: Need | M62: Yes | N62: Auto + home insurance | P62: =IF(AND($B62>=CurMonthStart,$B62<=CurMonthEnd),$K62,0)
A63: =ROW()-5 | B63: 45964 | C63: Kaiser Permanente | D63: =IFERROR(INDEX(Dim_Vendor[VendorID],MATCH($C63,Dim_Vendor[VendorName],0)),"") | E63: Healthcare | F63: =IFERROR(INDEX(Dim_Category[CategoryID],MATCH($E63,Dim_Category[CategoryName],0)),"") | G63: Credit Card | H63: =IFERROR(INDEX(Dim_Account[AccountID],MATCH($G63,Dim_Account[AccountName],0)),"") | I63: Credit Card | J63: =IFERROR(INDEX(Dim_PaymentMethod[PaymentMethodID],MATCH($I63,Dim_PaymentMethod[MethodName],0)),"") | K63: 42.91 | L63: Need | M63: No | N63: Copay | P63: =IF(AND($B63>=CurMonthStart,$B63<=CurMonthEnd),$K63,0)
A64: =ROW()-5 | B64: 45967 | C64: Chipotle | D64: =IFERROR(INDEX(Dim_Vendor[VendorID],MATCH($C64,Dim_Vendor[VendorName],0)),"") | E64: Dining & Entertainment | F64: =IFERROR(INDEX(Dim_Category[CategoryID],MATCH($E64,Dim_Category[CategoryName],0)),"") | G64: Credit Card | H64: =IFERROR(INDEX(Dim_Account[AccountID],MATCH($G64,Dim_Account[AccountName],0)),"") | I64: Credit Card | J64: =IFERROR(INDEX(Dim_PaymentMethod[PaymentMethodID],MATCH($I64,Dim_PaymentMethod[MethodName],0)),"") | K64: 14.25 | L64: Want | M64: No | P64: =IF(AND($B64>=CurMonthStart,$B64<=CurMonthEnd),$K64,0)
A65: =ROW()-5 | B65: 45970 | C65: Netflix | D65: =IFERROR(INDEX(Dim_Vendor[VendorID],MATCH($C65,Dim_Vendor[VendorName],0)),"") | E65: Dining & Entertainment | F65: =IFERROR(INDEX(Dim_Category[CategoryID],MATCH($E65,Dim_Category[CategoryName],0)),"") | G65: Credit Card | H65: =IFERROR(INDEX(Dim_Account[AccountID],MATCH($G65,Dim_Account[AccountName],0)),"") | I65: Credit Card | J65: =IFERROR(INDEX(Dim_PaymentMethod[PaymentMethodID],MATCH($I65,Dim_PaymentMethod[MethodName],0)),"") | K65: 15.49 | L65: Want | M65: Yes | N65: Streaming subscription | P65: =IF(AND($B65>=CurMonthStart,$B65<=CurMonthEnd),$K65,0)
A66: =ROW()-5 | B66: 45973 | C66: AMC Theatres | D66: =IFERROR(INDEX(Dim_Vendor[VendorID],MATCH($C66,Dim_Vendor[VendorName],0)),"") | E66: Dining & Entertainment | F66: =IFERROR(INDEX(Dim_Category[CategoryID],MATCH($E66,Dim_Category[CategoryName],0)),"") | G66: Credit Card | H66: =IFERROR(INDEX(Dim_Account[AccountID],MATCH($G66,Dim_Account[AccountName],0)),"") | I66: Credit Card | J66: =IFERROR(INDEX(Dim_PaymentMethod[PaymentMethodID],MATCH($I66,Dim_PaymentMethod[MethodName],0)),"") | K66: 30.81 | L66: Want | M66: No | P66: =IF(AND($B66>=CurMonthStart,$B66<=CurMonthEnd),$K66,0)
A67: =ROW()-5 | B67: 45976 | C67: Planet Fitness | D67: =IFERROR(INDEX(Dim_Vendor[VendorID],MATCH($C67,Dim_Vendor[VendorName],0)),"") | E67: Personal Care | F67: =IFERROR(INDEX(Dim_Category[CategoryID],MATCH($E67,Dim_Category[CategoryName],0)),"") | G67: Checking | H67: =IFERROR(INDEX(Dim_Account[AccountID],MATCH($G67,Dim_Account[AccountName],0)),"") | I67: ACH | J67: =IFERROR(INDEX(Dim_PaymentMethod[PaymentMethodID],MATCH($I67,Dim_PaymentMethod[MethodName],0)),"") | K67: 26.74 | L67: Want | M67: Yes | N67: Gym membership | P67: =IF(AND($B67>=CurMonthStart,$B67<=CurMonthEnd),$K67,0)
A68: =ROW()-5 | B68: 45979 | C68: Amazon | D68: =IFERROR(INDEX(Dim_Vendor[VendorID],MATCH($C68,Dim_Vendor[VendorName],0)),"") | E68: Shopping | F68: =IFERROR(INDEX(Dim_Category[CategoryID],MATCH($E68,Dim_Category[CategoryName],0)),"") | G68: Credit Card | H68: =IFERROR(INDEX(Dim_Account[AccountID],MATCH($G68,Dim_Account[AccountName],0)),"") | I68: Credit Card | J68: =IFERROR(INDEX(Dim_PaymentMethod[PaymentMethodID],MATCH($I68,Dim_PaymentMethod[MethodName],0)),"") | K68: 70.09 | L68: Want | M68: No | P68: =IF(AND($B68>=CurMonthStart,$B68<=CurMonthEnd),$K68,0)
A69: =ROW()-5 | B69: 45982 | C69: Target | D69: =IFERROR(INDEX(Dim_Vendor[VendorID],MATCH($C69,Dim_Vendor[VendorName],0)),"") | E69: Shopping | F69: =IFERROR(INDEX(Dim_Category[CategoryID],MATCH($E69,Dim_Category[CategoryName],0)),"") | G69: Credit Card | H69: =IFERROR(INDEX(Dim_Account[AccountID],MATCH($G69,Dim_Account[AccountName],0)),"") | I69: Credit Card | J69: =IFERROR(INDEX(Dim_PaymentMethod[PaymentMethodID],MATCH($I69,Dim_PaymentMethod[MethodName],0)),"") | K69: 55.27 | L69: Want | M69: No | P69: =IF(AND($B69>=CurMonthStart,$B69<=CurMonthEnd),$K69,0)
A70: =ROW()-5 | B70: 45994 | C70: Mortgage Lender | D70: =IFERROR(INDEX(Dim_Vendor[VendorID],MATCH($C70,Dim_Vendor[VendorName],0)),"") | E70: Mortgage | F70: =IFERROR(INDEX(Dim_Category[CategoryID],MATCH($E70,Dim_Category[CategoryName],0)),"") | G70: Checking | H70: =IFERROR(INDEX(Dim_Account[AccountID],MATCH($G70,Dim_Account[AccountName],0)),"") | I70: ACH | J70: =IFERROR(INDEX(Dim_PaymentMethod[PaymentMethodID],MATCH($I70,Dim_PaymentMethod[MethodName],0)),"") | K70: 2036.87 | L70: Need | M70: Yes | N70: Monthly mortgage payment | P70: =IF(AND($B70>=CurMonthStart,$B70<=CurMonthEnd),$K70,0)
A71: =ROW()-5 | B71: 45997 | C71: Whole Foods | D71: =IFERROR(INDEX(Dim_Vendor[VendorID],MATCH($C71,Dim_Vendor[VendorName],0)),"") | E71: Groceries | F71: =IFERROR(INDEX(Dim_Category[CategoryID],MATCH($E71,Dim_Category[CategoryName],0)),"") | G71: Credit Card | H71: =IFERROR(INDEX(Dim_Account[AccountID],MATCH($G71,Dim_Account[AccountName],0)),"") | I71: Credit Card | J71: =IFERROR(INDEX(Dim_PaymentMethod[PaymentMethodID],MATCH($I71,Dim_PaymentMethod[MethodName],0)),"") | K71: 193.25 | L71: Need | M71: No | P71: =IF(AND($B71>=CurMonthStart,$B71<=CurMonthEnd),$K71,0)
A72: =ROW()-5 | B72: 46000 | C72: Costco | D72: =IFERROR(INDEX(Dim_Vendor[VendorID],MATCH($C72,Dim_Vendor[VendorName],0)),"") | E72: Groceries | F72: =IFERROR(INDEX(Dim_Category[CategoryID],MATCH($E72,Dim_Category[CategoryName],0)),"") | G72: Credit Card | H72: =IFERROR(INDEX(Dim_Account[AccountID],MATCH($G72,Dim_Account[AccountName],0)),"") | I72: Credit Card | J72: =IFERROR(INDEX(Dim_PaymentMethod[PaymentMethodID],MATCH($I72,Dim_PaymentMethod[MethodName],0)),"") | K72: 231.9 | L72: Need | M72: No | N72: Bulk groceries | P72: =IF(AND($B72>=CurMonthStart,$B72<=CurMonthEnd),$K72,0)
A73: =ROW()-5 | B73: 46003 | C73: Shell Gas Station | D73: =IFERROR(INDEX(Dim_Vendor[VendorID],MATCH($C73,Dim_Vendor[VendorName],0)),"") | E73: Car | F73: =IFERROR(INDEX(Dim_Category[CategoryID],MATCH($E73,Dim_Category[CategoryName],0)),"") | G73: Credit Card | H73: =IFERROR(INDEX(Dim_Account[AccountID],MATCH($G73,Dim_Account[AccountName],0)),"") | I73: Credit Card | J73: =IFERROR(INDEX(Dim_PaymentMethod[PaymentMethodID],MATCH($I73,Dim_PaymentMethod[MethodName],0)),"") | K73: 51.29 | L73: Need | M73: No | N73: Gas | P73: =IF(AND($B73>=CurMonthStart,$B73<=CurMonthEnd),$K73,0)
A74: =ROW()-5 | B74: 46006 | C74: AutoZone | D74: =IFERROR(INDEX(Dim_Vendor[VendorID],MATCH($C74,Dim_Vendor[VendorName],0)),"") | E74: Car | F74: =IFERROR(INDEX(Dim_Category[CategoryID],MATCH($E74,Dim_Category[CategoryName],0)),"") | G74: Credit Card | H74: =IFERROR(INDEX(Dim_Account[AccountID],MATCH($G74,Dim_Account[AccountName],0)),"") | I74: Credit Card | J74: =IFERROR(INDEX(Dim_PaymentMethod[PaymentMethodID],MATCH($I74,Dim_PaymentMethod[MethodName],0)),"") | K74: 41.79 | L74: Need | M74: No | N74: Wiper blades / oil | P74: =IF(AND($B74>=CurMonthStart,$B74<=CurMonthEnd),$K74,0)
A75: =ROW()-5 | B75: 46009 | C75: City Electric Co | D75: =IFERROR(INDEX(Dim_Vendor[VendorID],MATCH($C75,Dim_Vendor[VendorName],0)),"") | E75: Utilities | F75: =IFERROR(INDEX(Dim_Category[CategoryID],MATCH($E75,Dim_Category[CategoryName],0)),"") | G75: Checking | H75: =IFERROR(INDEX(Dim_Account[AccountID],MATCH($G75,Dim_Account[AccountName],0)),"") | I75: ACH | J75: =IFERROR(INDEX(Dim_PaymentMethod[PaymentMethodID],MATCH($I75,Dim_PaymentMethod[MethodName],0)),"") | K75: 131.48 | L75: Need | M75: Yes | P75: =IF(AND($B75>=CurMonthStart,$B75<=CurMonthEnd),$K75,0)
A76: =ROW()-5 | B76: 46012 | C76: Comcast Xfinity | D76: =IFERROR(INDEX(Dim_Vendor[VendorID],MATCH($C76,Dim_Vendor[VendorName],0)),"") | E76: Utilities | F76: =IFERROR(INDEX(Dim_Category[CategoryID],MATCH($E76,Dim_Category[CategoryName],0)),"") | G76: Checking | H76: =IFERROR(INDEX(Dim_Account[AccountID],MATCH($G76,Dim_Account[AccountName],0)),"") | I76: ACH | J76: =IFERROR(INDEX(Dim_PaymentMethod[PaymentMethodID],MATCH($I76,Dim_PaymentMethod[MethodName],0)),"") | K76: 80.72 | L76: Need | M76: Yes | N76: Internet | P76: =IF(AND($B76>=CurMonthStart,$B76<=CurMonthEnd),$K76,0)
A77: =ROW()-5 | B77: 46015 | C77: Verizon Wireless | D77: =IFERROR(INDEX(Dim_Vendor[VendorID],MATCH($C77,Dim_Vendor[VendorName],0)),"") | E77: Utilities | F77: =IFERROR(INDEX(Dim_Category[CategoryID],MATCH($E77,Dim_Category[CategoryName],0)),"") | G77: Checking | H77: =IFERROR(INDEX(Dim_Account[AccountID],MATCH($G77,Dim_Account[AccountName],0)),"") | I77: ACH | J77: =IFERROR(INDEX(Dim_PaymentMethod[PaymentMethodID],MATCH($I77,Dim_PaymentMethod[MethodName],0)),"") | K77: 97.81 | L77: Need | M77: Yes | N77: Mobile phone | P77: =IF(AND($B77>=CurMonthStart,$B77<=CurMonthEnd),$K77,0)
A78: =ROW()-5 | B78: 46018 | C78: State Farm Insurance | D78: =IFERROR(INDEX(Dim_Vendor[VendorID],MATCH($C78,Dim_Vendor[VendorName],0)),"") | E78: Insurance | F78: =IFERROR(INDEX(Dim_Category[CategoryID],MATCH($E78,Dim_Category[CategoryName],0)),"") | G78: Checking | H78: =IFERROR(INDEX(Dim_Account[AccountID],MATCH($G78,Dim_Account[AccountName],0)),"") | I78: ACH | J78: =IFERROR(INDEX(Dim_PaymentMethod[PaymentMethodID],MATCH($I78,Dim_PaymentMethod[MethodName],0)),"") | K78: 149.79 | L78: Need | M78: Yes | N78: Auto + home insurance | P78: =IF(AND($B78>=CurMonthStart,$B78<=CurMonthEnd),$K78,0)
A79: =ROW()-5 | B79: 45994 | C79: Kaiser Permanente | D79: =IFERROR(INDEX(Dim_Vendor[VendorID],MATCH($C79,Dim_Vendor[VendorName],0)),"") | E79: Healthcare | F79: =IFERROR(INDEX(Dim_Category[CategoryID],MATCH($E79,Dim_Category[CategoryName],0)),"") | G79: Credit Card | H79: =IFERROR(INDEX(Dim_Account[AccountID],MATCH($G79,Dim_Account[AccountName],0)),"") | I79: Credit Card | J79: =IFERROR(INDEX(Dim_PaymentMethod[PaymentMethodID],MATCH($I79,Dim_PaymentMethod[MethodName],0)),"") | K79: 46.99 | L79: Need | M79: No | N79: Copay | P79: =IF(AND($B79>=CurMonthStart,$B79<=CurMonthEnd),$K79,0)
A80: =ROW()-5 | B80: 45997 | C80: Chipotle | D80: =IFERROR(INDEX(Dim_Vendor[VendorID],MATCH($C80,Dim_Vendor[VendorName],0)),"") | E80: Dining & Entertainment | F80: =IFERROR(INDEX(Dim_Category[CategoryID],MATCH($E80,Dim_Category[CategoryName],0)),"") | G80: Credit Card | H80: =IFERROR(INDEX(Dim_Account[AccountID],MATCH($G80,Dim_Account[AccountName],0)),"") | I80: Credit Card | J80: =IFERROR(INDEX(Dim_PaymentMethod[PaymentMethodID],MATCH($I80,Dim_PaymentMethod[MethodName],0)),"") | K80: 14.25 | L80: Want | M80: No | P80: =IF(AND($B80>=CurMonthStart,$B80<=CurMonthEnd),$K80,0)
A81: =ROW()-5 | B81: 46000 | C81: Netflix | D81: =IFERROR(INDEX(Dim_Vendor[VendorID],MATCH($C81,Dim_Vendor[VendorName],0)),"") | E81: Dining & Entertainment | F81: =IFERROR(INDEX(Dim_Category[CategoryID],MATCH($E81,Dim_Category[CategoryName],0)),"") | G81: Credit Card | H81: =IFERROR(INDEX(Dim_Account[AccountID],MATCH($G81,Dim_Account[AccountName],0)),"") | I81: Credit Card | J81: =IFERROR(INDEX(Dim_PaymentMethod[PaymentMethodID],MATCH($I81,Dim_PaymentMethod[MethodName],0)),"") | K81: 15.49 | L81: Want | M81: Yes | N81: Streaming subscription | P81: =IF(AND($B81>=CurMonthStart,$B81<=CurMonthEnd),$K81,0)
A82: =ROW()-5 | B82: 46003 | C82: AMC Theatres | D82: =IFERROR(INDEX(Dim_Vendor[VendorID],MATCH($C82,Dim_Vendor[VendorName],0)),"") | E82: Dining & Entertainment | F82: =IFERROR(INDEX(Dim_Category[CategoryID],MATCH($E82,Dim_Category[CategoryName],0)),"") | G82: Credit Card | H82: =IFERROR(INDEX(Dim_Account[AccountID],MATCH($G82,Dim_Account[AccountName],0)),"") | I82: Credit Card | J82: =IFERROR(INDEX(Dim_PaymentMethod[PaymentMethodID],MATCH($I82,Dim_PaymentMethod[MethodName],0)),"") | K82: 30.61 | L82: Want | M82: No | P82: =IF(AND($B82>=CurMonthStart,$B82<=CurMonthEnd),$K82,0)
A83: =ROW()-5 | B83: 46006 | C83: Planet Fitness | D83: =IFERROR(INDEX(Dim_Vendor[VendorID],MATCH($C83,Dim_Vendor[VendorName],0)),"") | E83: Personal Care | F83: =IFERROR(INDEX(Dim_Category[CategoryID],MATCH($E83,Dim_Category[CategoryName],0)),"") | G83: Checking | H83: =IFERROR(INDEX(Dim_Account[AccountID],MATCH($G83,Dim_Account[AccountName],0)),"") | I83: ACH | J83: =IFERROR(INDEX(Dim_PaymentMethod[PaymentMethodID],MATCH($I83,Dim_PaymentMethod[MethodName],0)),"") | K83: 23.12 | L83: Want | M83: Yes | N83: Gym membership | P83: =IF(AND($B83>=CurMonthStart,$B83<=CurMonthEnd),$K83,0)
A84: =ROW()-5 | B84: 46009 | C84: Amazon | D84: =IFERROR(INDEX(Dim_Vendor[VendorID],MATCH($C84,Dim_Vendor[VendorName],0)),"") | E84: Shopping | F84: =IFERROR(INDEX(Dim_Category[CategoryID],MATCH($E84,Dim_Category[CategoryName],0)),"") | G84: Credit Card | H84: =IFERROR(INDEX(Dim_Account[AccountID],MATCH($G84,Dim_Account[AccountName],0)),"") | I84: Credit Card | J84: =IFERROR(INDEX(Dim_PaymentMethod[PaymentMethodID],MATCH($I84,Dim_PaymentMethod[MethodName],0)),"") | K84: 66.45 | L84: Want | M84: No | P84: =IF(AND($B84>=CurMonthStart,$B84<=CurMonthEnd),$K84,0)
A85: =ROW()-5 | B85: 46012 | C85: Target | D85: =IFERROR(INDEX(Dim_Vendor[VendorID],MATCH($C85,Dim_Vendor[VendorName],0)),"") | E85: Shopping | F85: =IFERROR(INDEX(Dim_Category[CategoryID],MATCH($E85,Dim_Category[CategoryName],0)),"") | G85: Credit Card | H85: =IFERROR(INDEX(Dim_Account[AccountID],MATCH($G85,Dim_Account[AccountName],0)),"") | I85: Credit Card | J85: =IFERROR(INDEX(Dim_PaymentMethod[PaymentMethodID],MATCH($I85,Dim_PaymentMethod[MethodName],0)),"") | K85: 52.3 | L85: Want | M85: No | P85: =IF(AND($B85>=CurMonthStart,$B85<=CurMonthEnd),$K85,0)
A86: =ROW()-5 | B86: 46025 | C86: Mortgage Lender | D86: =IFERROR(INDEX(Dim_Vendor[VendorID],MATCH($C86,Dim_Vendor[VendorName],0)),"") | E86: Mortgage | F86: =IFERROR(INDEX(Dim_Category[CategoryID],MATCH($E86,Dim_Category[CategoryName],0)),"") | G86: Checking | H86: =IFERROR(INDEX(Dim_Account[AccountID],MATCH($G86,Dim_Account[AccountName],0)),"") | I86: ACH | J86: =IFERROR(INDEX(Dim_PaymentMethod[PaymentMethodID],MATCH($I86,Dim_PaymentMethod[MethodName],0)),"") | K86: 2050.58 | L86: Need | M86: Yes | N86: Monthly mortgage payment | P86: =IF(AND($B86>=CurMonthStart,$B86<=CurMonthEnd),$K86,0)
A87: =ROW()-5 | B87: 46028 | C87: Whole Foods | D87: =IFERROR(INDEX(Dim_Vendor[VendorID],MATCH($C87,Dim_Vendor[VendorName],0)),"") | E87: Groceries | F87: =IFERROR(INDEX(Dim_Category[CategoryID],MATCH($E87,Dim_Category[CategoryName],0)),"") | G87: Credit Card | H87: =IFERROR(INDEX(Dim_Account[AccountID],MATCH($G87,Dim_Account[AccountName],0)),"") | I87: Credit Card | J87: =IFERROR(INDEX(Dim_PaymentMethod[PaymentMethodID],MATCH($I87,Dim_PaymentMethod[MethodName],0)),"") | K87: 199.63 | L87: Need | M87: No | P87: =IF(AND($B87>=CurMonthStart,$B87<=CurMonthEnd),$K87,0)
A88: =ROW()-5 | B88: 46031 | C88: Costco | D88: =IFERROR(INDEX(Dim_Vendor[VendorID],MATCH($C88,Dim_Vendor[VendorName],0)),"") | E88: Groceries | F88: =IFERROR(INDEX(Dim_Category[CategoryID],MATCH($E88,Dim_Category[CategoryName],0)),"") | G88: Credit Card | H88: =IFERROR(INDEX(Dim_Account[AccountID],MATCH($G88,Dim_Account[AccountName],0)),"") | I88: Credit Card | J88: =IFERROR(INDEX(Dim_PaymentMethod[PaymentMethodID],MATCH($I88,Dim_PaymentMethod[MethodName],0)),"") | K88: 259.86 | L88: Need | M88: No | N88: Bulk groceries | P88: =IF(AND($B88>=CurMonthStart,$B88<=CurMonthEnd),$K88,0)
A89: =ROW()-5 | B89: 46034 | C89: Shell Gas Station | D89: =IFERROR(INDEX(Dim_Vendor[VendorID],MATCH($C89,Dim_Vendor[VendorName],0)),"") | E89: Car | F89: =IFERROR(INDEX(Dim_Category[CategoryID],MATCH($E89,Dim_Category[CategoryName],0)),"") | G89: Credit Card | H89: =IFERROR(INDEX(Dim_Account[AccountID],MATCH($G89,Dim_Account[AccountName],0)),"") | I89: Credit Card | J89: =IFERROR(INDEX(Dim_PaymentMethod[PaymentMethodID],MATCH($I89,Dim_PaymentMethod[MethodName],0)),"") | K89: 50.75 | L89: Need | M89: No | N89: Gas | P89: =IF(AND($B89>=CurMonthStart,$B89<=CurMonthEnd),$K89,0)
A90: =ROW()-5 | B90: 46037 | C90: AutoZone | D90: =IFERROR(INDEX(Dim_Vendor[VendorID],MATCH($C90,Dim_Vendor[VendorName],0)),"") | E90: Car | F90: =IFERROR(INDEX(Dim_Category[CategoryID],MATCH($E90,Dim_Category[CategoryName],0)),"") | G90: Credit Card | H90: =IFERROR(INDEX(Dim_Account[AccountID],MATCH($G90,Dim_Account[AccountName],0)),"") | I90: Credit Card | J90: =IFERROR(INDEX(Dim_PaymentMethod[PaymentMethodID],MATCH($I90,Dim_PaymentMethod[MethodName],0)),"") | K90: 39.71 | L90: Need | M90: No | N90: Wiper blades / oil | P90: =IF(AND($B90>=CurMonthStart,$B90<=CurMonthEnd),$K90,0)
A91: =ROW()-5 | B91: 46040 | C91: City Electric Co | D91: =IFERROR(INDEX(Dim_Vendor[VendorID],MATCH($C91,Dim_Vendor[VendorName],0)),"") | E91: Utilities | F91: =IFERROR(INDEX(Dim_Category[CategoryID],MATCH($E91,Dim_Category[CategoryName],0)),"") | G91: Checking | H91: =IFERROR(INDEX(Dim_Account[AccountID],MATCH($G91,Dim_Account[AccountName],0)),"") | I91: ACH | J91: =IFERROR(INDEX(Dim_PaymentMethod[PaymentMethodID],MATCH($I91,Dim_PaymentMethod[MethodName],0)),"") | K91: 126.45 | L91: Need | M91: Yes | P91: =IF(AND($B91>=CurMonthStart,$B91<=CurMonthEnd),$K91,0)
A92: =ROW()-5 | B92: 46043 | C92: Comcast Xfinity | D92: =IFERROR(INDEX(Dim_Vendor[VendorID],MATCH($C92,Dim_Vendor[VendorName],0)),"") | E92: Utilities | F92: =IFERROR(INDEX(Dim_Category[CategoryID],MATCH($E92,Dim_Category[CategoryName],0)),"") | G92: Checking | H92: =IFERROR(INDEX(Dim_Account[AccountID],MATCH($G92,Dim_Account[AccountName],0)),"") | I92: ACH | J92: =IFERROR(INDEX(Dim_PaymentMethod[PaymentMethodID],MATCH($I92,Dim_PaymentMethod[MethodName],0)),"") | K92: 85.3 | L92: Need | M92: Yes | N92: Internet | P92: =IF(AND($B92>=CurMonthStart,$B92<=CurMonthEnd),$K92,0)
A93: =ROW()-5 | B93: 46046 | C93: Verizon Wireless | D93: =IFERROR(INDEX(Dim_Vendor[VendorID],MATCH($C93,Dim_Vendor[VendorName],0)),"") | E93: Utilities | F93: =IFERROR(INDEX(Dim_Category[CategoryID],MATCH($E93,Dim_Category[CategoryName],0)),"") | G93: Checking | H93: =IFERROR(INDEX(Dim_Account[AccountID],MATCH($G93,Dim_Account[AccountName],0)),"") | I93: ACH | J93: =IFERROR(INDEX(Dim_PaymentMethod[PaymentMethodID],MATCH($I93,Dim_PaymentMethod[MethodName],0)),"") | K93: 94.37 | L93: Need | M93: Yes | N93: Mobile phone | P93: =IF(AND($B93>=CurMonthStart,$B93<=CurMonthEnd),$K93,0)
A94: =ROW()-5 | B94: 46049 | C94: State Farm Insurance | D94: =IFERROR(INDEX(Dim_Vendor[VendorID],MATCH($C94,Dim_Vendor[VendorName],0)),"") | E94: Insurance | F94: =IFERROR(INDEX(Dim_Category[CategoryID],MATCH($E94,Dim_Category[CategoryName],0)),"") | G94: Checking | H94: =IFERROR(INDEX(Dim_Account[AccountID],MATCH($G94,Dim_Account[AccountName],0)),"") | I94: ACH | J94: =IFERROR(INDEX(Dim_PaymentMethod[PaymentMethodID],MATCH($I94,Dim_PaymentMethod[MethodName],0)),"") | K94: 136.66 | L94: Need | M94: Yes | N94: Auto + home insurance | P94: =IF(AND($B94>=CurMonthStart,$B94<=CurMonthEnd),$K94,0)
A95: =ROW()-5 | B95: 46025 | C95: Kaiser Permanente | D95: =IFERROR(INDEX(Dim_Vendor[VendorID],MATCH($C95,Dim_Vendor[VendorName],0)),"") | E95: Healthcare | F95: =IFERROR(INDEX(Dim_Category[CategoryID],MATCH($E95,Dim_Category[CategoryName],0)),"") | G95: Credit Card | H95: =IFERROR(INDEX(Dim_Account[AccountID],MATCH($G95,Dim_Account[AccountName],0)),"") | I95: Credit Card | J95: =IFERROR(INDEX(Dim_PaymentMethod[PaymentMethodID],MATCH($I95,Dim_PaymentMethod[MethodName],0)),"") | K95: 43.18 | L95: Need | M95: No | N95: Copay | P95: =IF(AND($B95>=CurMonthStart,$B95<=CurMonthEnd),$K95,0)
A96: =ROW()-5 | B96: 46028 | C96: Chipotle | D96: =IFERROR(INDEX(Dim_Vendor[VendorID],MATCH($C96,Dim_Vendor[VendorName],0)),"") | E96: Dining & Entertainment | F96: =IFERROR(INDEX(Dim_Category[CategoryID],MATCH($E96,Dim_Category[CategoryName],0)),"") | G96: Credit Card | H96: =IFERROR(INDEX(Dim_Account[AccountID],MATCH($G96,Dim_Account[AccountName],0)),"") | I96: Credit Card | J96: =IFERROR(INDEX(Dim_PaymentMethod[PaymentMethodID],MATCH($I96,Dim_PaymentMethod[MethodName],0)),"") | K96: 14.25 | L96: Want | M96: No | P96: =IF(AND($B96>=CurMonthStart,$B96<=CurMonthEnd),$K96,0)
A97: =ROW()-5 | B97: 46031 | C97: Netflix | D97: =IFERROR(INDEX(Dim_Vendor[VendorID],MATCH($C97,Dim_Vendor[VendorName],0)),"") | E97: Dining & Entertainment | F97: =IFERROR(INDEX(Dim_Category[CategoryID],MATCH($E97,Dim_Category[CategoryName],0)),"") | G97: Credit Card | H97: =IFERROR(INDEX(Dim_Account[AccountID],MATCH($G97,Dim_Account[AccountName],0)),"") | I97: Credit Card | J97: =IFERROR(INDEX(Dim_PaymentMethod[PaymentMethodID],MATCH($I97,Dim_PaymentMethod[MethodName],0)),"") | K97: 15.49 | L97: Want | M97: Yes | N97: Streaming subscription | P97: =IF(AND($B97>=CurMonthStart,$B97<=CurMonthEnd),$K97,0)
A98: =ROW()-5 | B98: 46034 | C98: AMC Theatres | D98: =IFERROR(INDEX(Dim_Vendor[VendorID],MATCH($C98,Dim_Vendor[VendorName],0)),"") | E98: Dining & Entertainment | F98: =IFERROR(INDEX(Dim_Category[CategoryID],MATCH($E98,Dim_Category[CategoryName],0)),"") | G98: Credit Card | H98: =IFERROR(INDEX(Dim_Account[AccountID],MATCH($G98,Dim_Account[AccountName],0)),"") | I98: Credit Card | J98: =IFERROR(INDEX(Dim_PaymentMethod[PaymentMethodID],MATCH($I98,Dim_PaymentMethod[MethodName],0)),"") | K98: 32.31 | L98: Want | M98: No | P98: =IF(AND($B98>=CurMonthStart,$B98<=CurMonthEnd),$K98,0)
A99: =ROW()-5 | B99: 46037 | C99: Planet Fitness | D99: =IFERROR(INDEX(Dim_Vendor[VendorID],MATCH($C99,Dim_Vendor[VendorName],0)),"") | E99: Personal Care | F99: =IFERROR(INDEX(Dim_Category[CategoryID],MATCH($E99,Dim_Category[CategoryName],0)),"") | G99: Checking | H99: =IFERROR(INDEX(Dim_Account[AccountID],MATCH($G99,Dim_Account[AccountName],0)),"") | I99: ACH | J99: =IFERROR(INDEX(Dim_PaymentMethod[PaymentMethodID],MATCH($I99,Dim_PaymentMethod[MethodName],0)),"") | K99: 24.04 | L99: Want | M99: Yes | N99: Gym membership | P99: =IF(AND($B99>=CurMonthStart,$B99<=CurMonthEnd),$K99,0)
A100: =ROW()-5 | B100: 46040 | C100: Amazon | D100: =IFERROR(INDEX(Dim_Vendor[VendorID],MATCH($C100,Dim_Vendor[VendorName],0)),"") | E100: Shopping | F100: =IFERROR(INDEX(Dim_Category[CategoryID],MATCH($E100,Dim_Category[CategoryName],0)),"") | G100: Credit Card | H100: =IFERROR(INDEX(Dim_Account[AccountID],MATCH($G100,Dim_Account[AccountName],0)),"") | I100: Credit Card | J100: =IFERROR(INDEX(Dim_PaymentMethod[PaymentMethodID],MATCH($I100,Dim_PaymentMethod[MethodName],0)),"") | K100: 69.4 | L100: Want | M100: No | P100: =IF(AND($B100>=CurMonthStart,$B100<=CurMonthEnd),$K100,0)
A101: =ROW()-5 | B101: 46043 | C101: Target | D101: =IFERROR(INDEX(Dim_Vendor[VendorID],MATCH($C101,Dim_Vendor[VendorName],0)),"") | E101: Shopping | F101: =IFERROR(INDEX(Dim_Category[CategoryID],MATCH($E101,Dim_Category[CategoryName],0)),"") | G101: Credit Card | H101: =IFERROR(INDEX(Dim_Account[AccountID],MATCH($G101,Dim_Account[AccountName],0)),"") | I101: Credit Card | J101: =IFERROR(INDEX(Dim_PaymentMethod[PaymentMethodID],MATCH($I101,Dim_PaymentMethod[MethodName],0)),"") | K101: 57.78 | L101: Want | M101: No | P101: =IF(AND($B101>=CurMonthStart,$B101<=CurMonthEnd),$K101,0)
A102: =ROW()-5 | B102: 46056 | C102: Mortgage Lender | D102: =IFERROR(INDEX(Dim_Vendor[VendorID],MATCH($C102,Dim_Vendor[VendorName],0)),"") | E102: Mortgage | F102: =IFERROR(INDEX(Dim_Category[CategoryID],MATCH($E102,Dim_Category[CategoryName],0)),"") | G102: Checking | H102: =IFERROR(INDEX(Dim_Account[AccountID],MATCH($G102,Dim_Account[AccountName],0)),"") | I102: ACH | J102: =IFERROR(INDEX(Dim_PaymentMethod[PaymentMethodID],MATCH($I102,Dim_PaymentMethod[MethodName],0)),"") | K102: 2115.39 | L102: Need | M102: Yes | N102: Monthly mortgage payment | P102: =IF(AND($B102>=CurMonthStart,$B102<=CurMonthEnd),$K102,0)
...

Sheet Savings
A1: Savings
A4: TOTAL SAVED (ALL GOALS) | D4: MONTHLY SAVINGS (THIS MONTH) | G4: SAVINGS RATE
A5: =SUM(Dim_Goal[CurrentAmount]) | D5: =SUMIFS(Fact_SavingsTransfers[Amount],Fact_SavingsTransfers[Date],">="&CurMonthStart,Fact_SavingsTransfers[Date],"<="&CurMonthEnd) | G5: =IFERROR(SUMIFS(Fact_SavingsTransfers[Amount],Fact_SavingsTransfers[Date],">="&CurMonthStart,Fact_SavingsTransfers[Date],"<="&CurMonthEnd)/SUMIFS(Fact_Income[NetAmount],Fact_Income[Date],">="&CurMonthStart,Fact_Income[Date],"<="&CurMonthEnd),0)
A9: Savings Goals — set a target; log transfers below to track progress automatically
A10: GoalID | B10: GoalName | C10: TargetAmount | D10: TargetDate | E10: Priority | F10: CurrentAmount | G10: Remaining | H10: Completion % | I10: Avg Monthly Contribution | J10: Projected Completion Date
A11: 1 | B11: Emergency Fund | C11: 25000 | D11: 46387 | E11: High | F11: =SUMIFS(Fact_SavingsTransfers[Amount],Fact_SavingsTransfers[GoalName],$B11) | G11: =MAX($C11-$F11,0) | H11: =MIN($F11/$C11,1) | I11: =IFERROR($F11/MAX(COUNTIFS(Fact_SavingsTransfers[GoalName],$B11),1),0) | J11: =IF($I11>0,TodayDate+($G11/$I11)*30,"N/A")
A12: 2 | B12: Vacation | C12: 6000 | D12: 46539 | E12: Medium | F12: =SUMIFS(Fact_SavingsTransfers[Amount],Fact_SavingsTransfers[GoalName],$B12) | G12: =MAX($C12-$F12,0) | H12: =MIN($F12/$C12,1) | I12: =IFERROR($F12/MAX(COUNTIFS(Fact_SavingsTransfers[GoalName],$B12),1),0) | J12: =IF($I12>0,TodayDate+($G12/$I12)*30,"N/A")
A13: 3 | B13: New Car | C13: 12000 | D13: 46752 | E13: Medium | F13: =SUMIFS(Fact_SavingsTransfers[Amount],Fact_SavingsTransfers[GoalName],$B13) | G13: =MAX($C13-$F13,0) | H13: =MIN($F13/$C13,1) | I13: =IFERROR($F13/MAX(COUNTIFS(Fact_SavingsTransfers[GoalName],$B13),1),0) | J13: =IF($I13>0,TodayDate+($G13/$I13)*30,"N/A")
A16: Fact_SavingsTransfers — log every deposit toward a goal
A17: TransferID | B17: Date | C17: GoalName | D17: GoalID | E17: AccountName | F17: AccountID | G17: Amount
A18: =ROW()-17 | B18: 45872 | C18: Emergency Fund | D18: =IFERROR(INDEX(Dim_Goal[GoalID],MATCH($C18,Dim_Goal[GoalName],0)),"") | E18: Savings | F18: =IFERROR(INDEX(Dim_Account[AccountID],MATCH($E18,Dim_Account[AccountName],0)),"") | G18: 500
A19: =ROW()-17 | B19: 45903 | C19: Emergency Fund | D19: =IFERROR(INDEX(Dim_Goal[GoalID],MATCH($C19,Dim_Goal[GoalName],0)),"") | E19: Savings | F19: =IFERROR(INDEX(Dim_Account[AccountID],MATCH($E19,Dim_Account[AccountName],0)),"") | G19: 500
A20: =ROW()-17 | B20: 45917 | C20: Vacation | D20: =IFERROR(INDEX(Dim_Goal[GoalID],MATCH($C20,Dim_Goal[GoalName],0)),"") | E20: Savings | F20: =IFERROR(INDEX(Dim_Account[AccountID],MATCH($E20,Dim_Account[AccountName],0)),"") | G20: 150
A21: =ROW()-17 | B21: 45933 | C21: Emergency Fund | D21: =IFERROR(INDEX(Dim_Goal[GoalID],MATCH($C21,Dim_Goal[GoalName],0)),"") | E21: Savings | F21: =IFERROR(INDEX(Dim_Account[AccountID],MATCH($E21,Dim_Account[AccountName],0)),"") | G21: 500
A22: =ROW()-17 | B22: 45950 | C22: New Car | D22: =IFERROR(INDEX(Dim_Goal[GoalID],MATCH($C22,Dim_Goal[GoalName],0)),"") | E22: Savings | F22: =IFERROR(INDEX(Dim_Account[AccountID],MATCH($E22,Dim_Account[AccountName],0)),"") | G22: 200
A23: =ROW()-17 | B23: 45964 | C23: Emergency Fund | D23: =IFERROR(INDEX(Dim_Goal[GoalID],MATCH($C23,Dim_Goal[GoalName],0)),"") | E23: Savings | F23: =IFERROR(INDEX(Dim_Account[AccountID],MATCH($E23,Dim_Account[AccountName],0)),"") | G23: 500
A24: =ROW()-17 | B24: 45978 | C24: Vacation | D24: =IFERROR(INDEX(Dim_Goal[GoalID],MATCH($C24,Dim_Goal[GoalName],0)),"") | E24: Savings | F24: =IFERROR(INDEX(Dim_Account[AccountID],MATCH($E24,Dim_Account[AccountName],0)),"") | G24: 150
A25: =ROW()-17 | B25: 45994 | C25: Emergency Fund | D25: =IFERROR(INDEX(Dim_Goal[GoalID],MATCH($C25,Dim_Goal[GoalName],0)),"") | E25: Savings | F25: =IFERROR(INDEX(Dim_Account[AccountID],MATCH($E25,Dim_Account[AccountName],0)),"") | G25: 500
A26: =ROW()-17 | B26: 46025 | C26: Emergency Fund | D26: =IFERROR(INDEX(Dim_Goal[GoalID],MATCH($C26,Dim_Goal[GoalName],0)),"") | E26: Savings | F26: =IFERROR(INDEX(Dim_Account[AccountID],MATCH($E26,Dim_Account[AccountName],0)),"") | G26: 500
A27: =ROW()-17 | B27: 46039 | C27: Vacation | D27: =IFERROR(INDEX(Dim_Goal[GoalID],MATCH($C27,Dim_Goal[GoalName],0)),"") | E27: Savings | F27: =IFERROR(INDEX(Dim_Account[AccountID],MATCH($E27,Dim_Account[AccountName],0)),"") | G27: 150
A28: =ROW()-17 | B28: 46042 | C28: New Car | D28: =IFERROR(INDEX(Dim_Goal[GoalID],MATCH($C28,Dim_Goal[GoalName],0)),"") | E28: Savings | F28: =IFERROR(INDEX(Dim_Account[AccountID],MATCH($E28,Dim_Account[AccountName],0)),"") | G28: 200
A29: =ROW()-17 | B29: 46056 | C29: Emergency Fund | D29: =IFERROR(INDEX(Dim_Goal[GoalID],MATCH($C29,Dim_Goal[GoalName],0)),"") | E29: Savings | F29: =IFERROR(INDEX(Dim_Account[AccountID],MATCH($E29,Dim_Account[AccountName],0)),"") | G29: 500
... A39: =ROW()-17 | B39: 46223 | C39: New Car | D39: =IFERROR(INDEX(Dim_Goal[GoalID],MATCH($C39,Dim_Goal[GoalName],0)),"") | E39: Savings | F39: =IFERROR(INDEX(Dim_Account[AccountID],MATCH($E39,Dim_Account[AccountName],0)),"") | G39: 200

Sheet Budget
A1: Budget
A4: TOTAL MONTHLY BUDGET | C4: TOTAL ACTUAL (THIS MONTH) | E4: REMAINING | G4: OVERALL UTILIZATION
A5: =SUM(Budget[MonthlyBudget]) | C5: =SUM(Budget[Actual]) | E5: =SUM(Budget[MonthlyBudget])-SUM(Budget[Actual]) | G5: =SUM(Budget[Actual])/SUM(Budget[MonthlyBudget])
A9: Category Budgets — set MonthlyBudget per category; Actual pulls live from Expenses + Bank Import this month
A10: CategoryName | B10: MonthlyBudget | C10: Actual | D10: Remaining | E10: Variance % | F10: Status | G10: Progress
A11: Mortgage | B11: 2200 | C11: =SUMIFS(Fact_Expenses[Amount],Fact_Expenses[CategoryName],$A11,Fact_Expenses[Date],">="&CurMonthStart,Fact_Expenses[Date],"<="&CurMonthEnd)+SUMIFS(BankImportRaw[AbsAmount],BankImportRaw[CategoryName],$A11,BankImportRaw[TransactionType],"Expense",BankImportRaw[Date],">="&CurMonthStart,BankImportRaw[Date],"<="&CurMonthEnd) | D11: =$B11-$C11 | E11: =IFERROR($C11/$B11-1,0) | F11: =_xlfn.IFS($C11/$B11>1,"Over Budget",$C11/$B11>=0.8,"Near Limit",TRUE,"Under Budget") | G11: =MIN($C11/$B11,1.5)
A12: Utilities | B12: 320 | C12: =SUMIFS(Fact_Expenses[Amount],Fact_Expenses[CategoryName],$A12,Fact_Expenses[Date],">="&CurMonthStart,Fact_Expenses[Date],"<="&CurMonthEnd)+SUMIFS(BankImportRaw[AbsAmount],BankImportRaw[CategoryName],$A12,BankImportRaw[TransactionType],"Expense",BankImportRaw[Date],">="&CurMonthStart,BankImportRaw[Date],"<="&CurMonthEnd) | D12: =$B12-$C12 | E12: =IFERROR($C12/$B12-1,0) | F12: =_xlfn.IFS($C12/$B12>1,"Over Budget",$C12/$B12>=0.8,"Near Limit",TRUE,"Under Budget") | G12: =MIN($C12/$B12,1.5)
A13: Car | B13: 250 | C13: =SUMIFS(Fact_Expenses[Amount],Fact_Expenses[CategoryName],$A13,Fact_Expenses[Date],">="&CurMonthStart,Fact_Expenses[Date],"<="&CurMonthEnd)+SUMIFS(BankImportRaw[AbsAmount],BankImportRaw[CategoryName],$A13,BankImportRaw[TransactionType],"Expense",BankImportRaw[Date],">="&CurMonthStart,BankImportRaw[Date],"<="&CurMonthEnd) | D13: =$B13-$C13 | E13: =IFERROR($C13/$B13-1,0) | F13: =_xlfn.IFS($C13/$B13>1,"Over Budget",$C13/$B13>=0.8,"Near Limit",TRUE,"Under Budget") | G13: =MIN($C13/$B13,1.5)
A14: Groceries | B14: 650 | C14: =SUMIFS(Fact_Expenses[Amount],Fact_Expenses[CategoryName],$A14,Fact_Expenses[Date],">="&CurMonthStart,Fact_Expenses[Date],"<="&CurMonthEnd)+SUMIFS(BankImportRaw[AbsAmount],BankImportRaw[CategoryName],$A14,BankImportRaw[TransactionType],"Expense",BankImportRaw[Date],">="&CurMonthStart,BankImportRaw[Date],"<="&CurMonthEnd) | D14: =$B14-$C14 | E14: =IFERROR($C14/$B14-1,0) | F14: =_xlfn.IFS($C14/$B14>1,"Over Budget",$C14/$B14>=0.8,"Near Limit",TRUE,"Under Budget") | G14: =MIN($C14/$B14,1.5)
A15: Insurance | B15: 300 | C15: =SUMIFS(Fact_Expenses[Amount],Fact_Expenses[CategoryName],$A15,Fact_Expenses[Date],">="&CurMonthStart,Fact_Expenses[Date],"<="&CurMonthEnd)+SUMIFS(BankImportRaw[AbsAmount],BankImportRaw[CategoryName],$A15,BankImportRaw[TransactionType],"Expense",BankImportRaw[Date],">="&CurMonthStart,BankImportRaw[Date],"<="&CurMonthEnd) | D15: =$B15-$C15 | E15: =IFERROR($C15/$B15-1,0) | F15: =_xlfn.IFS($C15/$B15>1,"Over Budget",$C15/$B15>=0.8,"Near Limit",TRUE,"Under Budget") | G15: =MIN($C15/$B15,1.5)
A16: Healthcare | B16: 150 | C16: =SUMIFS(Fact_Expenses[Amount],Fact_Expenses[CategoryName],$A16,Fact_Expenses[Date],">="&CurMonthStart,Fact_Expenses[Date],"<="&CurMonthEnd)+SUMIFS(BankImportRaw[AbsAmount],BankImportRaw[CategoryName],$A16,BankImportRaw[TransactionType],"Expense",BankImportRaw[Date],">="&CurMonthStart,BankImportRaw[Date],"<="&CurMonthEnd) | D16: =$B16-$C16 | E16: =IFERROR($C16/$B16-1,0) | F16: =_xlfn.IFS($C16/$B16>1,"Over Budget",$C16/$B16>=0.8,"Near Limit",TRUE,"Under Budget") | G16: =MIN($C16/$B16,1.5)
A17: Dining & Entertainment | B17: 200 | C17: =SUMIFS(Fact_Expenses[Amount],Fact_Expenses[CategoryName],$A17,Fact_Expenses[Date],">="&CurMonthStart,Fact_Expenses[Date],"<="&CurMonthEnd)+SUMIFS(BankImportRaw[AbsAmount],BankImportRaw[CategoryName],$A17,BankImportRaw[TransactionType],"Expense",BankImportRaw[Date],">="&CurMonthStart,BankImportRaw[Date],"<="&CurMonthEnd) | D17: =$B17-$C17 | E17: =IFERROR($C17/$B17-1,0) | F17: =_xlfn.IFS($C17/$B17>1,"Over Budget",$C17/$B17>=0.8,"Near Limit",TRUE,"Under Budget") | G17: =MIN($C17/$B17,1.5)
A18: Personal Care | B18: 80 | C18: =SUMIFS(Fact_Expenses[Amount],Fact_Expenses[CategoryName],$A18,Fact_Expenses[Date],">="&CurMonthStart,Fact_Expenses[Date],"<="&CurMonthEnd)+SUMIFS(BankImportRaw[AbsAmount],BankImportRaw[CategoryName],$A18,BankImportRaw[TransactionType],"Expense",BankImportRaw[Date],">="&CurMonthStart,BankImportRaw[Date],"<="&CurMonthEnd) | D18: =$B18-$C18 | E18: =IFERROR($C18/$B18-1,0) | F18: =_xlfn.IFS($C18/$B18>1,"Over Budget",$C18/$B18>=0.8,"Near Limit",TRUE,"Under Budget") | G18: =MIN($C18/$B18,1.5)
A19: Shopping | B19: 200 | C19: =SUMIFS(Fact_Expenses[Amount],Fact_Expenses[CategoryName],$A19,Fact_Expenses[Date],">="&CurMonthStart,Fact_Expenses[Date],"<="&CurMonthEnd)+SUMIFS(BankImportRaw[AbsAmount],BankImportRaw[CategoryName],$A19,BankImportRaw[TransactionType],"Expense",BankImportRaw[Date],">="&CurMonthStart,BankImportRaw[Date],"<="&CurMonthEnd) | D19: =$B19-$C19 | E19: =IFERROR($C19/$B19-1,0) | F19: =_xlfn.IFS($C19/$B19>1,"Over Budget",$C19/$B19>=0.8,"Near Limit",TRUE,"Under Budget") | G19: =MIN($C19/$B19,1.5)
A20: Miscellaneous | B20: 100 | C20: =SUMIFS(Fact_Expenses[Amount],Fact_Expenses[CategoryName],$A20,Fact_Expenses[Date],">="&CurMonthStart,Fact_Expenses[Date],"<="&CurMonthEnd)+SUMIFS(BankImportRaw[AbsAmount],BankImportRaw[CategoryName],$A20,BankImportRaw[TransactionType],"Expense",BankImportRaw[Date],">="&CurMonthStart,BankImportRaw[Date],"<="&CurMonthEnd) | D20: =$B20-$C20 | E20: =IFERROR($C20/$B20-1,0) | F20: =_xlfn.IFS($C20/$B20>1,"Over Budget",$C20/$B20>=0.8,"Near Limit",TRUE,"Under Budget") | G20: =MIN($C20/$B20,1.5)

Sheet Categories
A1: Categories
A4: Dim_Category — add a row here to make a new category available everywhere
A5: CategoryID | B5: CategoryName | C5: CategoryType | D5: EssentialCategory
A6: 1 | B6: Mortgage | C6: Expense | D6: Yes
A7: 2 | B7: Utilities | C7: Expense | D7: Yes
A8: 3 | B8: Car | C8: Expense | D8: Yes
A9: 4 | B9: Groceries | C9: Expense | D9: Yes
A10: 5 | B10: Insurance | C10: Expense | D10: Yes
A11: 6 | B11: Healthcare | C11: Expense | D11: Yes
A12: 7 | B12: Dining & Entertainment | C12: Expense | D12: No
A13: 8 | B13: Personal Care | C13: Expense | D13: No
A14: 9 | B14: Shopping | C14: Expense | D14: No
A15: 10 | B15: Miscellaneous | C15: Expense | D15: No
A16: 11 | B16: Payroll | C16: Income | D16: No
A17: 12 | B17: Other Income | C17: Income | D17: No

Sheet Vendors
A1: Vendors
A4: Dim_Vendor — add a row here to make a new vendor available in Expenses
A5: VendorID | B5: VendorName | C5: DefaultCategoryID | D5: CurMonthSpend | E5: YTDSpend
A6: 1 | B6: Mortgage Lender | C6: 1 | D6: =SUMIFS(Fact_Expenses[Amount],Fact_Expenses[VendorName],$B6,Fact_Expenses[Date],">="&CurMonthStart,Fact_Expenses[Date],"<="&CurMonthEnd)+SUMIFS(BankImportRaw[AbsAmount],BankImportRaw[VendorName],$B6,BankImportRaw[TransactionType],"Expense",BankImportRaw[Date],">="&CurMonthStart,BankImportRaw[Date],"<="&CurMonthEnd) | E6: =SUMIFS(Fact_Expenses[Amount],Fact_Expenses[VendorName],$B6,Fact_Expenses[Date],">="&CurYearStart,Fact_Expenses[Date],"<="&CurYearEnd)+SUMIFS(BankImportRaw[AbsAmount],BankImportRaw[VendorName],$B6,BankImportRaw[TransactionType],"Expense",BankImportRaw[Date],">="&CurYearStart,BankImportRaw[Date],"<="&CurYearEnd)
A7: 2 | B7: City Electric Co | C7: 2 | D7: =SUMIFS(Fact_Expenses[Amount],Fact_Expenses[VendorName],$B7,Fact_Expenses[Date],">="&CurMonthStart,Fact_Expenses[Date],"<="&CurMonthEnd)+SUMIFS(BankImportRaw[AbsAmount],BankImportRaw[VendorName],$B7,BankImportRaw[TransactionType],"Expense",BankImportRaw[Date],">="&CurMonthStart,BankImportRaw[Date],"<="&CurMonthEnd) | E7: =SUMIFS(Fact_Expenses[Amount],Fact_Expenses[VendorName],$B7,Fact_Expenses[Date],">="&CurYearStart,Fact_Expenses[Date],"<="&CurYearEnd)+SUMIFS(BankImportRaw[AbsAmount],BankImportRaw[VendorName],$B7,BankImportRaw[TransactionType],"Expense",BankImportRaw[Date],">="&CurYearStart,BankImportRaw[Date],"<="&CurYearEnd)
A8: 3 | B8: Comcast Xfinity | C8: 2 | D8: =SUMIFS(Fact_Expenses[Amount],Fact_Expenses[VendorName],$B8,Fact_Expenses[Date],">="&CurMonthStart,Fact_Expenses[Date],"<="&CurMonthEnd)+SUMIFS(BankImportRaw[AbsAmount],BankImportRaw[VendorName],$B8,BankImportRaw[TransactionType],"Expense",BankImportRaw[Date],">="&CurMonthStart,BankImportRaw[Date],"<="&CurMonthEnd) | E8: =SUMIFS(Fact_Expenses[Amount],Fact_Expenses[VendorName],$B8,Fact_Expenses[Date],">="&CurYearStart,Fact_Expenses[Date],"<="&CurYearEnd)+SUMIFS(BankImportRaw[AbsAmount],BankImportRaw[VendorName],$B8,BankImportRaw[TransactionType],"Expense",BankImportRaw[Date],">="&CurYearStart,BankImportRaw[Date],"<="&CurYearEnd)
A9: 4 | B9: Verizon Wireless | C9: 2 | D9: =SUMIFS(Fact_Expenses[Amount],Fact_Expenses[VendorName],$B9,Fact_Expenses[Date],">="&CurMonthStart,Fact_Expenses[Date],"<="&CurMonthEnd)+SUMIFS(BankImportRaw[AbsAmount],BankImportRaw[VendorName],$B9,BankImportRaw[TransactionType],"Expense",BankImportRaw[Date],">="&CurMonthStart,BankImportRaw[Date],"<="&CurMonthEnd) | E9: =SUMIFS(Fact_Expenses[Amount],Fact_Expenses[VendorName],$B9,Fact_Expenses[Date],">="&CurYearStart,Fact_Expenses[Date],"<="&CurYearEnd)+SUMIFS(BankImportRaw[AbsAmount],BankImportRaw[VendorName],$B9,BankImportRaw[TransactionType],"Expense",BankImportRaw[Date],">="&CurYearStart,BankImportRaw[Date],"<="&CurYearEnd)
A10: 5 | B10: Shell Gas Station | C10: 3 | D10: =SUMIFS(Fact_Expenses[Amount],Fact_Expenses[VendorName],$B10,Fact_Expenses[Date],">="&CurMonthStart,Fact_Expenses[Date],"<="&CurMonthEnd)+SUMIFS(BankImportRaw[AbsAmount],BankImportRaw[VendorName],$B10,BankImportRaw[TransactionType],"Expense",BankImportRaw[Date],">="&CurMonthStart,BankImportRaw[Date],"<="&CurMonthEnd) | E10: =SUMIFS(Fact_Expenses[Amount],Fact_Expenses[VendorName],$B10,Fact_Expenses[Date],">="&CurYearStart,Fact_Expenses[Date],"<="&CurYearEnd)+SUMIFS(BankImportRaw[AbsAmount],BankImportRaw[VendorName],$B10,BankImportRaw[TransactionType],"Expense",BankImportRaw[Date],">="&CurYearStart,BankImportRaw[Date],"<="&CurYearEnd)
A11: 6 | B11: AutoZone | C11: 3 | D11: =SUMIFS(Fact_Expenses[Amount],Fact_Expenses[VendorName],$B11,Fact_Expenses[Date],">="&CurMonthStart,Fact_Expenses[Date],"<="&CurMonthEnd)+SUMIFS(BankImportRaw[AbsAmount],BankImportRaw[VendorName],$B11,BankImportRaw[TransactionType],"Expense",BankImportRaw[Date],">="&CurMonthStart,BankImportRaw[Date],"<="&CurMonthEnd) | E11: =SUMIFS(Fact_Expenses[Amount],Fact_Expenses[VendorName],$B11,Fact_Expenses[Date],">="&CurYearStart,Fact_Expenses[Date],"<="&CurYearEnd)+SUMIFS(BankImportRaw[AbsAmount],BankImportRaw[VendorName],$B11,BankImportRaw[TransactionType],"Expense",BankImportRaw[Date],">="&CurYearStart,BankImportRaw[Date],"<="&CurYearEnd)
A12: 7 | B12: Whole Foods | C12: 4 | D12: =SUMIFS(Fact_Expenses[Amount],Fact_Expenses[VendorName],$B12,Fact_Expenses[Date],">="&CurMonthStart,Fact_Expenses[Date],"<="&CurMonthEnd)+SUMIFS(BankImportRaw[AbsAmount],BankImportRaw[VendorName],$B12,BankImportRaw[TransactionType],"Expense",BankImportRaw[Date],">="&CurMonthStart,BankImportRaw[Date],"<="&CurMonthEnd) | E12: =SUMIFS(Fact_Expenses[Amount],Fact_Expenses[VendorName],$B12,Fact_Expenses[Date],">="&CurYearStart,Fact_Expenses[Date],"<="&CurYearEnd)+SUMIFS(BankImportRaw[AbsAmount],BankImportRaw[VendorName],$B12,BankImportRaw[TransactionType],"Expense",BankImportRaw[Date],">="&CurYearStart,BankImportRaw[Date],"<="&CurYearEnd)
A13: 8 | B13: Costco | C13: 4 | D13: =SUMIFS(Fact_Expenses[Amount],Fact_Expenses[VendorName],$B13,Fact_Expenses[Date],">="&CurMonthStart,Fact_Expenses[Date],"<="&CurMonthEnd)+SUMIFS(BankImportRaw[AbsAmount],BankImportRaw[VendorName],$B13,BankImportRaw[TransactionType],"Expense",BankImportRaw[Date],">="&CurMonthStart,BankImportRaw[Date],"<="&CurMonthEnd) | E13: =SUMIFS(Fact_Expenses[Amount],Fact_Expenses[VendorName],$B13,Fact_Expenses[Date],">="&CurYearStart,Fact_Expenses[Date],"<="&CurYearEnd)+SUMIFS(BankImportRaw[AbsAmount],BankImportRaw[VendorName],$B13,BankImportRaw[TransactionType],"Expense",BankImportRaw[Date],">="&CurYearStart,BankImportRaw[Date],"<="&CurYearEnd)
A14: 9 | B14: State Farm Insurance | C14: 5 | D14: =SUMIFS(Fact_Expenses[Amount],Fact_Expenses[VendorName],$B14,Fact_Expenses[Date],">="&CurMonthStart,Fact_Expenses[Date],"<="&CurMonthEnd)+SUMIFS(BankImportRaw[AbsAmount],BankImportRaw[VendorName],$B14,BankImportRaw[TransactionType],"Expense",BankImportRaw[Date],">="&CurMonthStart,BankImportRaw[Date],"<="&CurMonthEnd) | E14: =SUMIFS(Fact_Expenses[Amount],Fact_Expenses[VendorName],$B14,Fact_Expenses[Date],">="&CurYearStart,Fact_Expenses[Date],"<="&CurYearEnd)+SUMIFS(BankImportRaw[AbsAmount],BankImportRaw[VendorName],$B14,BankImportRaw[TransactionType],"Expense",BankImportRaw[Date],">="&CurYearStart,BankImportRaw[Date],"<="&CurYearEnd)
A15: 10 | B15: Kaiser Permanente | C15: 6 | D15: =SUMIFS(Fact_Expenses[Amount],Fact_Expenses[VendorName],$B15,Fact_Expenses[Date],">="&CurMonthStart,Fact_Expenses[Date],"<="&CurMonthEnd)+SUMIFS(BankImportRaw[AbsAmount],BankImportRaw[VendorName],$B15,BankImportRaw[TransactionType],"Expense",BankImportRaw[Date],">="&CurMonthStart,BankImportRaw[Date],"<="&CurMonthEnd) | E15: =SUMIFS(Fact_Expenses[Amount],Fact_Expenses[VendorName],$B15,Fact_Expenses[Date],">="&CurYearStart,Fact_Expenses[Date],"<="&CurYearEnd)+SUMIFS(BankImportRaw[AbsAmount],BankImportRaw[VendorName],$B15,BankImportRaw[TransactionType],"Expense",BankImportRaw[Date],">="&CurYearStart,BankImportRaw[Date],"<="&CurYearEnd)
A16: 11 | B16: Chipotle | C16: 7 | D16: =SUMIFS(Fact_Expenses[Amount],Fact_Expenses[VendorName],$B16,Fact_Expenses[Date],">="&CurMonthStart,Fact_Expenses[Date],"<="&CurMonthEnd)+SUMIFS(BankImportRaw[AbsAmount],BankImportRaw[VendorName],$B16,BankImportRaw[TransactionType],"Expense",BankImportRaw[Date],">="&CurMonthStart,BankImportRaw[Date],"<="&CurMonthEnd) | E16: =SUMIFS(Fact_Expenses[Amount],Fact_Expenses[VendorName],$B16,Fact_Expenses[Date],">="&CurYearStart,Fact_Expenses[Date],"<="&CurYearEnd)+SUMIFS(BankImportRaw[AbsAmount],BankImportRaw[VendorName],$B16,BankImportRaw[TransactionType],"Expense",BankImportRaw[Date],">="&CurYearStart,BankImportRaw[Date],"<="&CurYearEnd)
A17: 12 | B17: Netflix | C17: 7 | D17: =SUMIFS(Fact_Expenses[Amount],Fact_Expenses[VendorName],$B17,Fact_Expenses[Date],">="&CurMonthStart,Fact_Expenses[Date],"<="&CurMonthEnd)+SUMIFS(BankImportRaw[AbsAmount],BankImportRaw[VendorName],$B17,BankImportRaw[TransactionType],"Expense",BankImportRaw[Date],">="&CurMonthStart,BankImportRaw[Date],"<="&CurMonthEnd) | E17: =SUMIFS(Fact_Expenses[Amount],Fact_Expenses[VendorName],$B17,Fact_Expenses[Date],">="&CurYearStart,Fact_Expenses[Date],"<="&CurYearEnd)+SUMIFS(BankImportRaw[AbsAmount],BankImportRaw[VendorName],$B17,BankImportRaw[TransactionType],"Expense",BankImportRaw[Date],">="&CurYearStart,BankImportRaw[Date],"<="&CurYearEnd)
... A23: 18 | B23: Other Income Source | C23: 12 | D23: =SUMIFS(Fact_Expenses[Amount],Fact_Expenses[VendorName],$B23,Fact_Expenses[Date],">="&CurMonthStart,Fact_Expenses[Date],"<="&CurMonthEnd)+SUMIFS(BankImportRaw[AbsAmount],BankImportRaw[VendorName],$B23,BankImportRaw[TransactionType],"Expense",BankImportRaw[Date],">="&CurMonthStart,BankImportRaw[Date],"<="&CurMonthEnd) | E23: =SUMIFS(Fact_Expenses[Amount],Fact_Expenses[VendorName],$B23,Fact_Expenses[Date],">="&CurYearStart,Fact_Expenses[Date],"<="&CurYearEnd)+SUMIFS(BankImportRaw[AbsAmount],BankImportRaw[VendorName],$B23,BankImportRaw[TransactionType],"Expense",BankImportRaw[Date],">="&CurYearStart,BankImportRaw[Date],"<="&CurYearEnd)

Sheet Accounts
A1: Accounts
A4: Dim_Account — add a row here to make a new account available everywhere
A5: AccountID | B5: AccountName | C5: AccountType | D5: Balance
A6: 1 | B6: Checking | C6: Checking | D6: 4820.55
A7: 2 | B7: Savings | C7: Savings | D7: 18250
A8: 3 | B8: Credit Card | C8: Credit Card | D8: -1240.33
A11: Account Totals
A12: Total All Accounts | B12: =SUM(Dim_Account[Balance])

Sheet Settings
A1: Settings
A4: System Date Anchors (used by all SUMIFS date filters)
A5: Today's Date | B5: =TODAY()
A6: Current Month Start | B6: =EOMONTH(TodayDate,-1)+1
A7: Current Month End | B7: =EOMONTH(TodayDate,0)
A8: Last Month Start | B8: =EOMONTH(TodayDate,-2)+1
A9: Last Month End | B9: =EOMONTH(TodayDate,-1)
A10: Current Year Start | B10: =DATE(YEAR(TodayDate),1,1)
A11: Current Year End | B11: =DATE(YEAR(TodayDate),12,31)
A14: Dim_PaymentMethod
A15: PaymentMethodID | B15: MethodName
A16: 1 | B16: Credit Card
A17: 2 | B17: Debit Card
A18: 3 | B18: Cash
A19: 4 | B19: ACH
A20: 5 | B20: Check
A23: Controlled Vocabulary Lists (used for data-validation dropdowns)
A24: List_YesNo | B24: List_NeedWant
A25: Yes | B25: Need
A26: No | B26: Want

Sheet Dim_Date
A1: DateID | B1: Date | C1: Month | D1: MonthNumber | E1: Quarter | F1: Year
A2: =INT(B2) | B2: 45658 | C2: =TEXT(B2,"mmm") | D2: =MONTH(B2) | E2: =ROUNDUP(MONTH(B2)/3,0) | F2: =YEAR(B2)
A3: =INT(B3) | B3: 45659 | C3: =TEXT(B3,"mmm") | D3: =MONTH(B3) | E3: =ROUNDUP(MONTH(B3)/3,0) | F3: =YEAR(B3)
A4: =INT(B4) | B4: 45660 | C4: =TEXT(B4,"mmm") | D4: =MONTH(B4) | E4: =ROUNDUP(MONTH(B4)/3,0) | F4: =YEAR(B4)
A5: =INT(B5) | B5: 45661 | C5: =TEXT(B5,"mmm") | D5: =MONTH(B5) | E5: =ROUNDUP(MONTH(B5)/3,0) | F5: =YEAR(B5)
A6: =INT(B6) | B6: 45662 | C6: =TEXT(B6,"mmm") | D6: =MONTH(B6) | E6: =ROUNDUP(MONTH(B6)/3,0) | F6: =YEAR(B6)
A7: =INT(B7) | B7: 45663 | C7: =TEXT(B7,"mmm") | D7: =MONTH(B7) | E7: =ROUNDUP(MONTH(B7)/3,0) | F7: =YEAR(B7)
A8: =INT(B8) | B8: 45664 | C8: =TEXT(B8,"mmm") | D8: =MONTH(B8) | E8: =ROUNDUP(MONTH(B8)/3,0) | F8: =YEAR(B8)
A9: =INT(B9) | B9: 45665 | C9: =TEXT(B9,"mmm") | D9: =MONTH(B9) | E9: =ROUNDUP(MONTH(B9)/3,0) | F9: =YEAR(B9)
A10: =INT(B10) | B10: 45666 | C10: =TEXT(B10,"mmm") | D10: =MONTH(B10) | E10: =ROUNDUP(MONTH(B10)/3,0) | F10: =YEAR(B10)
A11: =INT(B11) | B11: 45667 | C11: =TEXT(B11,"mmm") | D11: =MONTH(B11) | E11: =ROUNDUP(MONTH(B11)/3,0) | F11: =YEAR(B11)
A12: =INT(B12) | B12: 45668 | C12: =TEXT(B12,"mmm") | D12: =MONTH(B12) | E12: =ROUNDUP(MONTH(B12)/3,0) | F12: =YEAR(B12)
A13: =INT(B13) | B13: 45669 | C13: =TEXT(B13,"mmm") | D13: =MONTH(B13) | E13: =ROUNDUP(MONTH(B13)/3,0) | F13: =YEAR(B13)
... A1096: =INT(B1096) | B1096: 46752 | C1096: =TEXT(B1096,"mmm") | D1096: =MONTH(B1096) | E1096: =ROUNDUP(MONTH(B1096)/3,0) | F1096: =YEAR(B1096)

Sheet ChartData
A1: Month | B1: MonthEnd | C1: Income | D1: Expenses | E1: NetSavings | F1: CumSavings
A2: =EDATE(TodayDate,-12) | B2: =EOMONTH(A2,0) | C2: =SUMIFS(Fact_Income[NetAmount],Fact_Income[Date],">="&EOMONTH(A2,-1)+1,Fact_Income[Date],"<="&B2)+SUMIFS(BankImportRaw[AbsAmount],BankImportRaw[TransactionType],"Income",BankImportRaw[Date],">="&EOMONTH(A2,-1)+1,BankImportRaw[Date],"<="&B2) | D2: =SUMIFS(Fact_Expenses[Amount],Fact_Expenses[Date],">="&EOMONTH(A2,-1)+1,Fact_Expenses[Date],"<="&B2)+SUMIFS(BankImportRaw[AbsAmount],BankImportRaw[TransactionType],"Expense",BankImportRaw[Date],">="&EOMONTH(A2,-1)+1,BankImportRaw[Date],"<="&B2) | E2: =C2-D2 | F2: =SUM($E$2:E2)
A3: =EDATE(TodayDate,-11) | B3: =EOMONTH(A3,0) | C3: =SUMIFS(Fact_Income[NetAmount],Fact_Income[Date],">="&EOMONTH(A3,-1)+1,Fact_Income[Date],"<="&B3)+SUMIFS(BankImportRaw[AbsAmount],BankImportRaw[TransactionType],"Income",BankImportRaw[Date],">="&EOMONTH(A3,-1)+1,BankImportRaw[Date],"<="&B3) | D3: =SUMIFS(Fact_Expenses[Amount],Fact_Expenses[Date],">="&EOMONTH(A3,-1)+1,Fact_Expenses[Date],"<="&B3)+SUMIFS(BankImportRaw[AbsAmount],BankImportRaw[TransactionType],"Expense",BankImportRaw[Date],">="&EOMONTH(A3,-1)+1,BankImportRaw[Date],"<="&B3) | E3: =C3-D3 | F3: =SUM($E$2:E3)
A4: =EDATE(TodayDate,-10) | B4: =EOMONTH(A4,0) | C4: =SUMIFS(Fact_Income[NetAmount],Fact_Income[Date],">="&EOMONTH(A4,-1)+1,Fact_Income[Date],"<="&B4)+SUMIFS(BankImportRaw[AbsAmount],BankImportRaw[TransactionType],"Income",BankImportRaw[Date],">="&EOMONTH(A4,-1)+1,BankImportRaw[Date],"<="&B4) | D4: =SUMIFS(Fact_Expenses[Amount],Fact_Expenses[Date],">="&EOMONTH(A4,-1)+1,Fact_Expenses[Date],"<="&B4)+SUMIFS(BankImportRaw[AbsAmount],BankImportRaw[TransactionType],"Expense",BankImportRaw[Date],">="&EOMONTH(A4,-1)+1,BankImportRaw[Date],"<="&B4) | E4: =C4-D4 | F4: =SUM($E$2:E4)
A5: =EDATE(TodayDate,-9) | B5: =EOMONTH(A5,0) | C5: =SUMIFS(Fact_Income[NetAmount],Fact_Income[Date],">="&EOMONTH(A5,-1)+1,Fact_Income[Date],"<="&B5)+SUMIFS(BankImportRaw[AbsAmount],BankImportRaw[TransactionType],"Income",BankImportRaw[Date],">="&EOMONTH(A5,-1)+1,BankImportRaw[Date],"<="&B5) | D5: =SUMIFS(Fact_Expenses[Amount],Fact_Expenses[Date],">="&EOMONTH(A5,-1)+1,Fact_Expenses[Date],"<="&B5)+SUMIFS(BankImportRaw[AbsAmount],BankImportRaw[TransactionType],"Expense",BankImportRaw[Date],">="&EOMONTH(A5,-1)+1,BankImportRaw[Date],"<="&B5) | E5: =C5-D5 | F5: =SUM($E$2:E5)
A6: =EDATE(TodayDate,-8) | B6: =EOMONTH(A6,0) | C6: =SUMIFS(Fact_Income[NetAmount],Fact_Income[Date],">="&EOMONTH(A6,-1)+1,Fact_Income[Date],"<="&B6)+SUMIFS(BankImportRaw[AbsAmount],BankImportRaw[TransactionType],"Income",BankImportRaw[Date],">="&EOMONTH(A6,-1)+1,BankImportRaw[Date],"<="&B6) | D6: =SUMIFS(Fact_Expenses[Amount],Fact_Expenses[Date],">="&EOMONTH(A6,-1)+1,Fact_Expenses[Date],"<="&B6)+SUMIFS(BankImportRaw[AbsAmount],BankImportRaw[TransactionType],"Expense",BankImportRaw[Date],">="&EOMONTH(A6,-1)+1,BankImportRaw[Date],"<="&B6) | E6: =C6-D6 | F6: =SUM($E$2:E6)
A7: =EDATE(TodayDate,-7) | B7: =EOMONTH(A7,0) | C7: =SUMIFS(Fact_Income[NetAmount],Fact_Income[Date],">="&EOMONTH(A7,-1)+1,Fact_Income[Date],"<="&B7)+SUMIFS(BankImportRaw[AbsAmount],BankImportRaw[TransactionType],"Income",BankImportRaw[Date],">="&EOMONTH(A7,-1)+1,BankImportRaw[Date],"<="&B7) | D7: =SUMIFS(Fact_Expenses[Amount],Fact_Expenses[Date],">="&EOMONTH(A7,-1)+1,Fact_Expenses[Date],"<="&B7)+SUMIFS(BankImportRaw[AbsAmount],BankImportRaw[TransactionType],"Expense",BankImportRaw[Date],">="&EOMONTH(A7,-1)+1,BankImportRaw[Date],"<="&B7) | E7: =C7-D7 | F7: =SUM($E$2:E7)
A8: =EDATE(TodayDate,-6) | B8: =EOMONTH(A8,0) | C8: =SUMIFS(Fact_Income[NetAmount],Fact_Income[Date],">="&EOMONTH(A8,-1)+1,Fact_Income[Date],"<="&B8)+SUMIFS(BankImportRaw[AbsAmount],BankImportRaw[TransactionType],"Income",BankImportRaw[Date],">="&EOMONTH(A8,-1)+1,BankImportRaw[Date],"<="&B8) | D8: =SUMIFS(Fact_Expenses[Amount],Fact_Expenses[Date],">="&EOMONTH(A8,-1)+1,Fact_Expenses[Date],"<="&B8)+SUMIFS(BankImportRaw[AbsAmount],BankImportRaw[TransactionType],"Expense",BankImportRaw[Date],">="&EOMONTH(A8,-1)+1,BankImportRaw[Date],"<="&B8) | E8: =C8-D8 | F8: =SUM($E$2:E8)
A9: =EDATE(TodayDate,-5) | B9: =EOMONTH(A9,0) | C9: =SUMIFS(Fact_Income[NetAmount],Fact_Income[Date],">="&EOMONTH(A9,-1)+1,Fact_Income[Date],"<="&B9)+SUMIFS(BankImportRaw[AbsAmount],BankImportRaw[TransactionType],"Income",BankImportRaw[Date],">="&EOMONTH(A9,-1)+1,BankImportRaw[Date],"<="&B9) | D9: =SUMIFS(Fact_Expenses[Amount],Fact_Expenses[Date],">="&EOMONTH(A9,-1)+1,Fact_Expenses[Date],"<="&B9)+SUMIFS(BankImportRaw[AbsAmount],BankImportRaw[TransactionType],"Expense",BankImportRaw[Date],">="&EOMONTH(A9,-1)+1,BankImportRaw[Date],"<="&B9) | E9: =C9-D9 | F9: =SUM($E$2:E9)
A10: =EDATE(TodayDate,-4) | B10: =EOMONTH(A10,0) | C10: =SUMIFS(Fact_Income[NetAmount],Fact_Income[Date],">="&EOMONTH(A10,-1)+1,Fact_Income[Date],"<="&B10)+SUMIFS(BankImportRaw[AbsAmount],BankImportRaw[TransactionType],"Income",BankImportRaw[Date],">="&EOMONTH(A10,-1)+1,BankImportRaw[Date],"<="&B10) | D10: =SUMIFS(Fact_Expenses[Amount],Fact_Expenses[Date],">="&EOMONTH(A10,-1)+1,Fact_Expenses[Date],"<="&B10)+SUMIFS(BankImportRaw[AbsAmount],BankImportRaw[TransactionType],"Expense",BankImportRaw[Date],">="&EOMONTH(A10,-1)+1,BankImportRaw[Date],"<="&B10) | E10: =C10-D10 | F10: =SUM($E$2:E10)
A11: =EDATE(TodayDate,-3) | B11: =EOMONTH(A11,0) | C11: =SUMIFS(Fact_Income[NetAmount],Fact_Income[Date],">="&EOMONTH(A11,-1)+1,Fact_Income[Date],"<="&B11)+SUMIFS(BankImportRaw[AbsAmount],BankImportRaw[TransactionType],"Income",BankImportRaw[Date],">="&EOMONTH(A11,-1)+1,BankImportRaw[Date],"<="&B11) | D11: =SUMIFS(Fact_Expenses[Amount],Fact_Expenses[Date],">="&EOMONTH(A11,-1)+1,Fact_Expenses[Date],"<="&B11)+SUMIFS(BankImportRaw[AbsAmount],BankImportRaw[TransactionType],"Expense",BankImportRaw[Date],">="&EOMONTH(A11,-1)+1,BankImportRaw[Date],"<="&B11) | E11: =C11-D11 | F11: =SUM($E$2:E11)
A12: =EDATE(TodayDate,-2) | B12: =EOMONTH(A12,0) | C12: =SUMIFS(Fact_Income[NetAmount],Fact_Income[Date],">="&EOMONTH(A12,-1)+1,Fact_Income[Date],"<="&B12)+SUMIFS(BankImportRaw[AbsAmount],BankImportRaw[TransactionType],"Income",BankImportRaw[Date],">="&EOMONTH(A12,-1)+1,BankImportRaw[Date],"<="&B12) | D12: =SUMIFS(Fact_Expenses[Amount],Fact_Expenses[Date],">="&EOMONTH(A12,-1)+1,Fact_Expenses[Date],"<="&B12)+SUMIFS(BankImportRaw[AbsAmount],BankImportRaw[TransactionType],"Expense",BankImportRaw[Date],">="&EOMONTH(A12,-1)+1,BankImportRaw[Date],"<="&B12) | E12: =C12-D12 | F12: =SUM($E$2:E12)
A13: =EDATE(TodayDate,-1) | B13: =EOMONTH(A13,0) | C13: =SUMIFS(Fact_Income[NetAmount],Fact_Income[Date],">="&EOMONTH(A13,-1)+1,Fact_Income[Date],"<="&B13)+SUMIFS(BankImportRaw[AbsAmount],BankImportRaw[TransactionType],"Income",BankImportRaw[Date],">="&EOMONTH(A13,-1)+1,BankImportRaw[Date],"<="&B13) | D13: =SUMIFS(Fact_Expenses[Amount],Fact_Expenses[Date],">="&EOMONTH(A13,-1)+1,Fact_Expenses[Date],"<="&B13)+SUMIFS(BankImportRaw[AbsAmount],BankImportRaw[TransactionType],"Expense",BankImportRaw[Date],">="&EOMONTH(A13,-1)+1,BankImportRaw[Date],"<="&B13) | E13: =C13-D13 | F13: =SUM($E$2:E13)
A14: =EDATE(TodayDate,0) | B14: =EOMONTH(A14,0) | C14: =SUMIFS(Fact_Income[NetAmount],Fact_Income[Date],">="&EOMONTH(A14,-1)+1,Fact_Income[Date],"<="&B14)+SUMIFS(BankImportRaw[AbsAmount],BankImportRaw[TransactionType],"Income",BankImportRaw[Date],">="&EOMONTH(A14,-1)+1,BankImportRaw[Date],"<="&B14) | D14: =SUMIFS(Fact_Expenses[Amount],Fact_Expenses[Date],">="&EOMONTH(A14,-1)+1,Fact_Expenses[Date],"<="&B14)+SUMIFS(BankImportRaw[AbsAmount],BankImportRaw[TransactionType],"Expense",BankImportRaw[Date],">="&EOMONTH(A14,-1)+1,BankImportRaw[Date],"<="&B14) | E14: =C14-D14 | F14: =SUM($E$2:E14)
